Workbook

Sheet customer_master
A1: ABC Finance | Customer Master | May 2026
A2: Customer_ID | B2: Customer_Name | C2: Date_of_Birth | D2: Age | E2: Gender | F2: Mobile | G2: Alternate_Mobile | H2: Address | I2: City | J2: CIBIL_Score | K2: PIN_Code | L2: Aadhaar_Number | M2: PAN_Number | N2: KYC_Status | O2: Occupation_Type | P2: Monthly_Income | Q2: Vehicle_Make | R2: Vehicle_Model | S2: Vehicle_Type | T2: Registration_Number | U2: Vehicle_Cost | V2: Branch_Code | W2: Branch_Name | X2: RM_Name | Y2: Amount_Disbursed | Z2: Tenure_Months | AA2: Interest_Rate_% | AB2: EMI_Amount | AC2: Disbursement_Date | AD2: Maturity_Date | AE2: Repayment_Mode
A3: CUST0001 | B3: Vijay Mishra | C3: 29669 | D3: =DATEDIF(Table1[[#This Row],[Date_of_Birth]],TODAY(),"Y") -> 45 | E3: Male | F3: 9210053353 | G3: 9685582861 | H3: 433, MG Road, Indore | I3: Indore | J3: 673 | K3: 452001 | L3: XXXX-XXXX-9290 | M3: GPOSS7873H | N3: Pending | O3: Business | P3: 35000 | Q3: Bajaj | R3: Pulsar | S3: Two-Wheeler | T3: UP99GF5552 | U3: 70851 | V3: BR001 | W3: Indore | X3: Amit Sharma | Y3: 54982 | Z3: 36 | AA3: 14.31 | AB3: =-PMT((Table1[[#This Row],[Interest_Rate_%]]/100)/12,Table1[[#This Row],[Tenure_Months]],Table1[[#This Row],[Amount_Disbursed]]) -> 1887.4434 | AC3: 45674 | AD3: =EDATE(Table1[[#This Row],[Disbursement_Date]],Table1[[#This Row],[Tenure_Months]]) -> 46769 | AE3: NACH
A4: CUST0003 | B4: Mamta Dwivedi | C4: 28926 | D4: =DATEDIF(Table1[[#This Row],[Date_of_Birth]],TODAY(),"Y") -> 47 | E4: Female | F4: 9918739736 | H4: 614, Adhartal, Jabalpur | I4: Jabalpur | J4: 682 | K4: 482004 | L4: XXXX-XXXX-6258 | M4: YWVHB2290C | N4: Pending | O4: Salaried | P4: 25000 | Q4: Maruti | R4: Brezza | S4: SUV | T4: RJ80CE9645 | U4: 1136474 | V4: BR003 | W4: Jabalpur | X4: Vikas Singh | Y4: 858828 | Z4: 36 | AA4: 11.79 | AB4: =-PMT((Table1[[#This Row],[Interest_Rate_%]]/100)/12,Table1[[#This Row],[Tenure_Months]],Table1[[#This Row],[Amount_Disbursed]]) -> 28439.315 | AC4: 45197 | AD4: =EDATE(Table1[[#This Row],[Disbursement_Date]],Table1[[#This Row],[Tenure_Months]]) -> 46293 | AE4: PDC
A5: CUST0004 | B5: Mahesh Patel | C5: 34499 | D5: =DATEDIF(Table1[[#This Row],[Date_of_Birth]],TODAY(),"Y") -> 31 | E5: Male | F5: 9541417711 | G5: 9882839238 | H5: 670, Lashkar, Gwalior | I5: Gwalior | J5: 667 | K5: 474001 | L5: XXXX-XXXX-2298 | M5: IWGEL7912F | N5: Complete | O5: Self-Employed | P5: 30000 | Q5: Hero | R5: Splendor | S5: Two-Wheeler | T5: RJ80BA9856 | U5: 50000 | V5: BR004 | W5: Gwalior | X5: Neha Mishra | Y5: 35571 | Z5: 48 | AA5: 13.36 | AB5: =-PMT((Table1[[#This Row],[Interest_Rate_%]]/100)/12,Table1[[#This Row],[Tenure_Months]],Table1[[#This Row],[Amount_Disbursed]]) -> 960.64883 | AC5: 46014 | AD5: =EDATE(Table1[[#This Row],[Disbursement_Date]],Table1[[#This Row],[Tenure_Months]]) -> 47475 | AE5: NACH
A6: CUST0005 | B6: Santosh Mishra | C6: 33653 | D6: =DATEDIF(Table1[[#This Row],[Date_of_Birth]],TODAY(),"Y") -> 34 | E6: Male | F6: 9364371717 | G6: 9142672287 | H6: 958, Chorhata, Rewa | I6: Rewa | J6: 705 | K6: 486002 | L6: XXXX-XXXX-6331 | M6: IGDQL2188A | N6: Pending | O6: Business | P6: 100000 | Q6: Maruti | R6: Dzire | S6: Sedan | T6: CG37EC6718 | U6: 659602 | V6: BR005 | W6: Rewa | X6: Anita Dubey | Y6: 494849 | Z6: 12 | AA6: 11.05 | AB6: =-PMT((Table1[[#This Row],[Interest_Rate_%]]/100)/12,Table1[[#This Row],[Tenure_Months]],Table1[[#This Row],[Amount_Disbursed]]) -> 43747.117 | AC6: 45794 | AD6: =EDATE(Table1[[#This Row],[Disbursement_Date]],Table1[[#This Row],[Tenure_Months]]) -> 46159 | AE6: ECS
A7: CUST0006 | B7: Deepak Malviya | C7: 34578 | D7: =DATEDIF(Table1[[#This Row],[Date_of_Birth]],TODAY(),"Y") -> 31 | E7: Male | F7: 9220123666 | H7: 855, Adhartal, Jabalpur | I7: Jabalpur | J7: 793 | K7: 482005 | L7: XXXX-XXXX-7170 | M7: LBJYZ1653L | N7: Complete | O7: Business | P7: 30000 | Q7: Honda | R7: Activa | S7: Two-Wheeler | T7: MH81GC4878 | U7: 50000 | V7: BR003 | W7: Jabalpur | X7: Vikas Singh | Y7: 38984 | Z7: 24 | AA7: 15.69 | AB7: =-PMT((Table1[[#This Row],[Interest_Rate_%]]/100)/12,Table1[[#This Row],[Tenure_Months]],Table1[[#This Row],[Amount_Disbursed]]) -> 1903.0086 | AC7: 45498 | AD7: =EDATE(Table1[[#This Row],[Disbursement_Date]],Table1[[#This Row],[Tenure_Months]]) -> 46228 | AE7: ECS
A8: CUST0008 | B8: Dinesh Sharma | C8: 25309 | D8: =DATEDIF(Table1[[#This Row],[Date_of_Birth]],TODAY(),"Y") -> 57 | E8: Male | F8: 9756350429 | G8: 9178198716 | H8: 736, TT Nagar, Bhopal | I8: Bhopal | J8: 718 | K8: 462004 | L8: XXXX-XXXX-8323 | M8: DRXWX7965H | N8: Complete | O8: Business | P8: 75000 | Q8: Honda | R8: City | S8: Sedan | T8: CG41BH3184 | U8: 1156582 | V8: BR002 | W8: Bhopal | X8: Rohit Gupta | Y8: 872459 | Z8: 24 | AA8: 15.86 | AB8: =-PMT((Table1[[#This Row],[Interest_Rate_%]]/100)/12,Table1[[#This Row],[Tenure_Months]],Table1[[#This Row],[Amount_Disbursed]]) -> 42659.968 | AC8: 45092 | AD8: =EDATE(Table1[[#This Row],[Disbursement_Date]],Table1[[#This Row],[Tenure_Months]]) -> 45823 | AE8: NACH
A9: CUST0009 | B9: Meena Gupta | C9: 34161 | D9: =DATEDIF(Table1[[#This Row],[Date_of_Birth]],TODAY(),"Y") -> 32 | E9: Female | F9: 9682624278 | G9: 9166857303 | H9: 927, Habibganj, Bhopal | I9: Bhopal | J9: 786 | K9: 462006 | L9: XXXX-XXXX-4309 | M9: OMYHK7865R | N9: Expired | O9: Business | P9: 30000 | Q9: Honda | R9: City | S9: Sedan | T9: MH65HA7371 | U9: 1178760 | V9: BR002 | W9: Bhopal | X9: Rohit Gupta | Y9: 936007 | Z9: 60 | AA9: 13.74 | AB9: =-PMT((Table1[[#This Row],[Interest_Rate_%]]/100)/12,Table1[[#This Row],[Tenure_Months]],Table1[[#This Row],[Amount_Disbursed]]) -> 21653.284 | AC9: 45643 | AD9: =EDATE(Table1[[#This Row],[Disbursement_Date]],Table1[[#This Row],[Tenure_Months]]) -> 47469 | AE9: NACH
A10: CUST0011 | B10: Naresh Dwivedi | C10: 33390 | D10: =DATEDIF(Table1[[#This Row],[Date_of_Birth]],TODAY(),"Y") -> 35 | E10: Male | F10: 9630757561 | G10: 9295249057 | H10: 349, Kolar Road, Bhopal | I10: Bhopal | J10: 690 | K10: 462005 | L10: XXXX-XXXX-0529 | M10: AYCSM4937W | N10: Pending | O10: Business | P10: 60000 | Q10: Honda | R10: City | S10: Sedan | T10: MP47DG4986 | U10: 1152260 | V10: BR002 | W10: Bhopal | X10: Rohit Gupta | Y10: 874852 | Z10: 24 | AA10: 11.58 | AB10: =-PMT((Table1[[#This Row],[Interest_Rate_%]]/100)/12,Table1[[#This Row],[Tenure_Months]],Table1[[#This Row],[Amount_Disbursed]]) -> 41010.94 | AC10: 44955 | AD10: =EDATE(Table1[[#This Row],[Disbursement_Date]],Table1[[#This Row],[Tenure_Months]]) -> 45686 | AE10: PDC
A11: CUST0012 | B11: Asha Singh | C11: 35854 | D11: =DATEDIF(Table1[[#This Row],[Date_of_Birth]],TODAY(),"Y") -> 28 | E11: Female | F11: 9113169872 | G11: 9604011128 | H11: 989, MG Road, Indore | I11: Indore | J11: 785 | K11: 452003 | L11: XXXX-XXXX-2836 | M11: VKBQB3444Z | N11: Expired | O11: Self-Employed | P11: 20000 | Q11: Hyundai | R11: i20 | S11: Hatchback | T11: CG63DJ7232 | U11: 715525 | V11: BR001 | W11: Indore | X11: Amit Sharma | Y11: 599235 | Z11: 24 | AA11: 15.23 | AB11: =-PMT((Table1[[#This Row],[Interest_Rate_%]]/100)/12,Table1[[#This Row],[Tenure_Months]],Table1[[#This Row],[Amount_Disbursed]]) -> 29120.422 | AC11: 45332 | AD11: =EDATE(Table1[[#This Row],[Disbursement_Date]],Table1[[#This Row],[Tenure_Months]]) -> 46063 | AE11: ECS
A12: CUST0013 | B12: Ramesh Verma | C12: 28265 | D12: =DATEDIF(Table1[[#This Row],[Date_of_Birth]],TODAY(),"Y") -> 49 | E12: Male | F12: 9904187231 | G12: 9409893263 | H12: 717, Gorakhpur, Jabalpur | I12: Jabalpur | J12: 672 | K12: 482003 | L12: XXXX-XXXX-8490 | M12: MCBLI5102A | N12: Complete | O12: Salaried | P12: 100000 | Q12: Maruti | R12: Swift | S12: Hatchback | T12: MH83AC8708 | U12: 688117 | V12: BR003 | W12: Jabalpur | X12: Kavita Yadav | Y12: 538554 | Z12: 18 | AA12: 13.61 | AB12: =-PMT((Table1[[#This Row],[Interest_Rate_%]]/100)/12,Table1[[#This Row],[Tenure_Months]],Table1[[#This Row],[Amount_Disbursed]]) -> 33246.325 | AC12: 45947 | AD12: =EDATE(Table1[[#This Row],[Disbursement_Date]],Table1[[#This Row],[Tenure_Months]]) -> 46494 | AE12: PDC
A13: CUST0014 | B13: Ajay Chauhan | C13: 35827 | D13: =DATEDIF(Table1[[#This Row],[Date_of_Birth]],TODAY(),"Y") -> 28 | E13: Male | F13: 9776481264 | G13: 9356943695 | H13: 566, Purani Basti, Rewa | I13: Rewa | J13: 746 | K13: 486001 | L13: XXXX-XXXX-2733 | M13: YQEYH5479N | N13: Pending | O13: Self-Employed | P13: 30000 | Q13: Honda | R13: City | S13: Sedan | T13: UP59DJ3236 | U13: 1222255 | V13: BR005 | W13: Rewa | X13: Anita Dubey | Y13: 866248 | Z13: 60 | AA13: 13.34 | AB13: =-PMT((Table1[[#This Row],[Interest_Rate_%]]/100)/12,Table1[[#This Row],[Tenure_Months]],Table1[[#This Row],[Amount_Disbursed]]) -> 19860.902 | AC13: 45707 | AD13: =EDATE(Table1[[#This Row],[Disbursement_Date]],Table1[[#This Row],[Tenure_Months]]) -> 47533 | AE13: ECS
A14: CUST0015 | B14: Seema Joshi | C14: 26880 | D14: =DATEDIF(Table1[[#This Row],[Date_of_Birth]],TODAY(),"Y") -> 52 | E14: Female | F14: 9664735673 | G14: 9116479358 | H14: 77, TT Nagar, Bhopal | I14: Bhopal | J14: 638 | K14: 462003 | L14: XXXX-XXXX-9489 | M14: SQWWW7226K | N14: Pending | O14: Business | P14: 15000 | Q14: Renault | R14: Kwid | S14: Hatchback | T14: UP90ED2480 | U14: 458968 | V14: BR002 | W14: Bhopal | X14: Sunita Patel | Y14: 363463 | Z14: 60 | AA14: 10.56 | AB14: =-PMT((Table1[[#This Row],[Interest_Rate_%]]/100)/12,Table1[[#This Row],[Tenure_Months]],Table1[[#This Row],[Amount_Disbursed]]) -> 7823.045 | AC14: 45879 | AD14: =EDATE(Table1[[#This Row],[Disbursement_Date]],Table1[[#This Row],[Tenure_Months]]) -> 47705 | AE14: ECS
A15: CUST0016 | B15: Asha Jain | C15: 30556 | D15: =DATEDIF(Table1[[#This Row],[Date_of_Birth]],TODAY(),"Y") -> 42 | E15: Female | F15: 9424400672 | H15: 243, Gorakhpur, Jabalpur | I15: Jabalpur | J15: 656 | K15: 482005 | L15: XXXX-XXXX-0353 | M15: HSAVK1132S | N15: Complete | O15: Business | P15: 60000 | Q15: Hero | R15: Splendor | S15: Two-Wheeler | T15: UP87FD4115 | U15: 62512 | V15: BR003 | W15: Jabalpur | X15: Kavita Yadav | Y15: 55853 | Z15: 24 | AA15: 14.98 | AB15: =-PMT((Table1[[#This Row],[Interest_Rate_%]]/100)/12,Table1[[#This Row],[Tenure_Months]],Table1[[#This Row],[Amount_Disbursed]]) -> 2707.5941 | AC15: 45620 | AD15: =EDATE(Table1[[#This Row],[Disbursement_Date]],Table1[[#This Row],[Tenure_Months]]) -> 46350 | AE15: NACH
A16: CUST0017 | B16: Lata Gupta | C16: 33612 | D16: =DATEDIF(Table1[[#This Row],[Date_of_Birth]],TODAY(),"Y") -> 34 | E16: Female | F16: 9676140134 | H16: 599, Thatipur, Gwalior | I16: Gwalior | J16: 736 | K16: 474006 | L16: XXXX-XXXX-6063 | M16: CGAWO4626U | N16: Complete | O16: Business | P16: 60000 | Q16: TVS | R16: Jupiter | S16: Two-Wheeler | T16: RJ24CA1609 | U16: 79608 | V16: BR004 | W16: Gwalior | X16: Neha Mishra | Y16: 64394 | Z16: 60 | AA16: 12.65 | AB16: =-PMT((Table1[[#This Row],[Interest_Rate_%]]/100)/12,Table1[[#This Row],[Tenure_Months]],Table1[[#This Row],[Amount_Disbursed]]) -> 1453.6499 | AC16: 45742 | AD16: =EDATE(Table1[[#This Row],[Disbursement_Date]],Table1[[#This Row],[Tenure_Months]]) -> 47568 | AE16: ECS
A17: CUST0018 | B17: Kiran Sharma | C17: 25727 | D17: =DATEDIF(Table1[[#This Row],[Date_of_Birth]],TODAY(),"Y") -> 55 | E17: Female | F17: 9235209737 | G17: 9320337809 | H17: 784, Habibganj, Bhopal | I17: Bhopal | J17: 775 | K17: 462002 | L17: XXXX-XXXX-7466 | M17: VGUUP5542E | N17: Complete | O17: Business | P17: 35000 | Q17: Bajaj | R17: Pulsar | S17: Two-Wheeler | T17: MP94AC1243 | U17: 92871 | V17: BR002 | W17: Bhopal | X17: Sunita Patel | Y17: 77753 | Z17: 36 | AA17: 14.77 | AB17: =-PMT((Table1[[#This Row],[Interest_Rate_%]]/100)/12,Table1[[#This Row],[Tenure_Months]],Table1[[#This Row],[Amount_Disbursed]]) -> 2686.5841 | AC17: 45835 | AD17: =EDATE(Table1[[#This Row],[Disbursement_Date]],Table1[[#This Row],[Tenure_Months]]) -> 46931 | AE17: NACH
A18: CUST0020 | B18: Kiran Dwivedi | C18: 37276 | D18: =DATEDIF(Table1[[#This Row],[Date_of_Birth]],TODAY(),"Y") -> 24 | E18: Female | F18: 9806340901 | G18: 9387169808 | H18: 280, Morar, Gwalior | I18: Gwalior | J18: 756 | K18: 474003 | L18: XXXX-XXXX-1424 | M18: EDRBT1502C | N18: Expired | O18: Salaried | P18: 50000 | Q18: Honda | R18: City | S18: Sedan | T18: UP57EF2391 | U18: 1194681 | V18: BR004 | W18: Gwalior | X18: Neha Mishra | Y18: 905436 | Z18: 12 | AA18: 10.55 | AB18: =-PMT((Table1[[#This Row],[Interest_Rate_%]]/100)/12,Table1[[#This Row],[Tenure_Months]],Table1[[#This Row],[Amount_Disbursed]]) -> 79834.006 | AC18: 45808 | AD18: =EDATE(Table1[[#This Row],[Disbursement_Date]],Table1[[#This Row],[Tenure_Months]]) -> 46173 | AE18: NACH
A19: CUST0021 | B19: Renu Soni | C19: 26142 | D19: =DATEDIF(Table1[[#This Row],[Date_of_Birth]],TODAY(),"Y") -> 54 | E19: Female | F19: 9896760809 | H19: 944, MP Nagar, Bhopal | I19: Bhopal | J19: 732 | K19: 462003 | L19: XXXX-XXXX-2032 | M19: OSKCA6321F | N19: Expired | O19: Self-Employed | P19: 40000 | Q19: Maruti | R19: Dzire | S19: Sedan | T19: MP41GG9584 | U19: 707240 | V19: BR002 | W19: Bhopal | X19: Sunita Patel | Y19: 591412 | Z19: 48 | AA19: 14.36 | AB19: =-PMT((Table1[[#This Row],[Interest_Rate_%]]/100)/12,Table1[[#This Row],[Tenure_Months]],Table1[[#This Row],[Amount_Disbursed]]) -> 16268.21 | AC19: 45588 | AD19: =EDATE(Table1[[#This Row],[Disbursement_Date]],Table1[[#This Row],[Tenure_Months]]) -> 47049 | AE19: PDC
A20: CUST0022 | B20: Pradeep Pandey | C20: 30957 | D20: =DATEDIF(Table1[[#This Row],[Date_of_Birth]],TODAY(),"Y") -> 41 | E20: Male | F20: 9477895080 | G20: 9433297890 | H20: 378, Morar, Gwalior | I20: Gwalior | J20: 653 | K20: 474001 | L20: XXXX-XXXX-6009 | M20: PJPYT1672O | N20: Expired | O20: Business | P20: 30000 | Q20: Tata | R20: Nexon | S20: SUV | T20: RJ74CA8381 | U20: 1029299 | V20: BR004 | W20: Gwalior | X20: Neha Mishra | Y20: 737287 | Z20: 60 | AA20: 11.35 | AB20: =-PMT((Table1[[#This Row],[Interest_Rate_%]]/100)/12,Table1[[#This Row],[Tenure_Months]],Table1[[#This Row],[Amount_Disbursed]]) -> 16159.398 | AC20: 45643 | AD20: =EDATE(Table1[[#This Row],[Disbursement_Date]],Table1[[#This Row],[Tenure_Months]]) -> 47469 | AE20: ECS
A21: CUST0023 | B21: Mohit Agarwal | C21: 32224 | D21: =DATEDIF(Table1[[#This Row],[Date_of_Birth]],TODAY(),"Y") -> 38 | E21: Male | F21: 9854658900 | G21: 9893253262 | H21: 662, Malviya Nagar, Indore | I21: Indore | J21: 633 | K21: 452005 | L21: XXXX-XXXX-9032 | M21: JEFYM4711E | N21: Complete | O21: Salaried | P21: 20000 | Q21: Mahindra | R21: Bolero | S21: MUV | T21: CG14FC7172 | U21: 970748 | V21: BR001 | W21: Indore | X21: Priya Verma | Y21: 777162 | Z21: 36 | AA21: 16.3 | AB21: =-PMT((Table1[[#This Row],[Interest_Rate_%]]/100)/12,Table1[[#This Row],[Tenure_Months]],Table1[[#This Row],[Amount_Disbursed]]) -> 27437.956 | AC21: 45335 | AD21: =EDATE(Table1[[#This Row],[Disbursement_Date]],Table1[[#This Row],[Tenure_Months]]) -> 46431 | AE21: PDC
A22: CUST0024 | B22: Mohit Patel | C22: 36566 | D22: =DATEDIF(Table1[[#This Row],[Date_of_Birth]],TODAY(),"Y") -> 26 | E22: Male | F22: 9190060226 | G22: 9392907427 | H22: 851, Thatipur, Gwalior | I22: Gwalior | J22: 777 | K22: 474001 | L22: XXXX-XXXX-0842 | M22: LJABN4862M | N22: Complete | O22: Self-Employed | P22: 30000 | Q22: Maruti | R22: Swift | S22: Hatchback | T22: MP93FC3254 | U22: 641770 | V22: BR004 | W22: Gwalior | X22: Sanjay Tiwari | Y22: 530352 | Z22: 48 | AA22: 11.95 | AB22: =-PMT((Table1[[#This Row],[Interest_Rate_%]]/100)/12,Table1[[#This Row],[Tenure_Months]],Table1[[#This Row],[Amount_Disbursed]]) -> 13953.186 | AC22: 45221 | AD22: =EDATE(Table1[[#This Row],[Disbursement_Date]],Table1[[#This Row],[Tenure_Months]]) -> 46682 | AE22: ECS
A23: CUST0025 | B23: Pushpa Yadav | C23: 26554 | D23: =DATEDIF(Table1[[#This Row],[Date_of_Birth]],TODAY(),"Y") -> 53 | E23: Female | F23: 9172670118 | G23: 9684203557 | H23: 400, TT Nagar, Bhopal | I23: Bhopal | J23: 797 | K23: 462001 | L23: XXXX-XXXX-7563 | M23: ZGAUI2698Y | N23: Expired | O23: Business | P23: 40000 | Q23: Maruti | R23: Brezza | S23: SUV | T23: MH79FC8612 | U23: 1055811 | V23: BR002 | W23: Bhopal | X23: Sunita Patel | Y23: 926893 | Z23: 60 | AA23: 13.14 | AB23: =-PMT((Table1[[#This Row],[Interest_Rate_%]]/100)/12,Table1[[#This Row],[Tenure_Months]],Table1[[#This Row],[Amount_Disbursed]]) -> 21156.152 | AC23: 45718 | AD23: =EDATE(Table1[[#This Row],[Disbursement_Date]],Table1[[#This Row],[Tenure_Months]]) -> 47544 | AE23: ECS
A24: CUST0026 | B24: Neha Gupta | C24: 34379 | D24: =DATEDIF(Table1[[#This Row],[Date_of_Birth]],TODAY(),"Y") -> 32 | E24: Female | F24: 9746879296 | G24: 9293763673 | H24: 82, Adhartal, Jabalpur | I24: Jabalpur | J24: 651 | K24: 482006 | L24: XXXX-XXXX-3022 | M24: LSELL6776T | N24: Pending | O24: Self-Employed | P24: 15000 | Q24: Maruti | R24: Dzire | S24: Sedan | T24: RJ56CA3339 | U24: 737973 | V24: BR003 | W24: Jabalpur | X24: Kavita Yadav | Y24: 630961 | Z24: 60 | AA24: 13.18 | AB24: =-PMT((Table1[[#This Row],[Interest_Rate_%]]/100)/12,Table1[[#This Row],[Tenure_Months]],Table1[[#This Row],[Amount_Disbursed]]) -> 14414.508 | AC24: 45511 | AD24: =EDATE(Table1[[#This Row],[Disbursement_Date]],Table1[[#This Row],[Tenure_Months]]) -> 47337 | AE24: PDC
A25: CUST0027 | B25: Amit Chauhan | C25: 26631 | D25: =DATEDIF(Table1[[#This Row],[Date_of_Birth]],TODAY(),"Y") -> 53 | E25: Male | F25: 9443154754 | G25: 9861863296 | H25: 556, Palasia, Indore | I25: Indore | J25: 640 | K25: 452003 | L25: XXXX-XXXX-4013 | M25: SYQUN2988G | N25: Complete | O25: Salaried | P25: 15000 | Q25: Tata | R25: Nexon | S25: SUV | T25: CG57HJ3126 | U25: 1022616 | V25: BR001 | W25: Indore | X25: Amit Sharma | Y25: 778031 | Z25: 18 | AA25: 12.44 | AB25: =-PMT((Table1[[#This Row],[Interest_Rate_%]]/100)/12,Table1[[#This Row],[Tenure_Months]],Table1[[#This Row],[Amount_Disbursed]]) -> 47605.1 | AC25: 45388 | AD25: =EDATE(Table1[[#This Row],[Disbursement_Date]],Table1[[#This Row],[Tenure_Months]]) -> 45936 | AE25: ECS
A26: CUST0028 | B26: Renu Dubey | C26: 27708 | D26: =DATEDIF(Table1[[#This Row],[Date_of_Birth]],TODAY(),"Y") -> 50 | E26: Female | F26: 9759737342 | G26: 9639633807 | H26: 176, Habibganj, Bhopal | I26: Bhopal | J26: 668 | K26: 462006 | L26: XXXX-XXXX-7914 | M26: IYBWC5336U | N26: Complete | O26: Business | P26: 50000 | Q26: Renault | R26: Kwid | S26: Hatchback | T26: MP73EE8912 | U26: 533753 | V26: BR002 | W26: Bhopal | X26: Sunita Patel | Y26: 474547 | Z26: 48 | AA26: 13.01 | AB26: =-PMT((Table1[[#This Row],[Interest_Rate_%]]/100)/12,Table1[[#This Row],[Tenure_Months]],Table1[[#This Row],[Amount_Disbursed]]) -> 12733.263 | AC26: 45254 | AD26: =EDATE(Table1[[#This Row],[Disbursement_Date]],Table1[[#This Row],[Tenure_Months]]) -> 46715 | AE26: ECS
A27: CUST0029 | B27: Nisha Rajput | C27: 31625 | D27: =DATEDIF(Table1[[#This Row],[Date_of_Birth]],TODAY(),"Y") -> 39 | E27: Female | F27: 9196689473 | G27: 9642716859 | H27: 598, Morar, Gwalior | I27: Gwalior | J27: 771 | K27: 474001 | L27: XXXX-XXXX-4700 | M27: MWRMN2761N | N27: Complete | O27: Self-Employed | P27: 40000 | Q27: Bajaj | R27: Pulsar | S27: Two-Wheeler | T27: MH15GA4189 | U27: 122855 | V27: BR004 | W27: Gwalior | X27: Sanjay Tiwari | Y27: 94056 | Z27: 48 | AA27: 12.41 | AB27: =-PMT((Table1[[#This Row],[Interest_Rate_%]]/100)/12,Table1[[#This Row],[Tenure_Months]],Table1[[#This Row],[Amount_Disbursed]]) -> 2495.8315 | AC27: 45731 | AD27: =EDATE(Table1[[#This Row],[Disbursement_Date]],Table1[[#This Row],[Tenure_Months]]) -> 47192 | AE27: PDC
A28: CUST0030 | B28: Renu Rajput | C28: 37757 | D28: =DATEDIF(Table1[[#This Row],[Date_of_Birth]],TODAY(),"Y") -> 23 | E28: Female | F28: 9975903641 | H28: 598, Chorhata, Rewa | I28: Rewa | J28: 800 | K28: 486006 | L28: XXXX-XXXX-1269 | M28: QPGRZ4728X | N28: Complete | O28: Business | P28: 60000 | Q28: Maruti | R28: Brezza | S28: SUV | T28: CG58CD1517 | U28: 1118712 | V28: BR005 | W28: Rewa | X28: Anita Dubey | Y28: 826116 | Z28: 18 | AA28: 12.17 | AB28: =-PMT((Table1[[#This Row],[Interest_Rate_%]]/100)/12,Table1[[#This Row],[Tenure_Months]],Table1[[#This Row],[Amount_Disbursed]]) -> 50443.508 | AC28: 45538 | AD28: =EDATE(Table1[[#This Row],[Disbursement_Date]],Table1[[#This Row],[Tenure_Months]]) -> 46084 | AE28: NACH
A29: CUST0032 | B29: Rajesh Pandey | C29: 37898 | D29: =DATEDIF(Table1[[#This Row],[Date_of_Birth]],TODAY(),"Y") -> 22 | E29: Male | F29: 9459748735 | H29: 911, Civil Lines, Jabalpur | I29: Jabalpur | J29: 659 | K29: 482005 | L29: XXXX-XXXX-7342 | M29: FCELG4050A | N29: Complete | O29: Self-Employed | P29: 100000 | Q29: Honda | R29: Activa | S29: Two-Wheeler | T29: UP32GG9442 | U29: 134258 | V29: BR003 | W29: Jabalpur | X29: Vikas Singh | Y29: 111131 | Z29: 24 | AA29: 12.71 | AB29: =-PMT((Table1[[#This Row],[Interest_Rate_%]]/100)/12,Table1[[#This Row],[Tenure_Months]],Table1[[#This Row],[Amount_Disbursed]]) -> 5268.2453 | AC29: 45379 | AD29: =EDATE(Table1[[#This Row],[Disbursement_Date]],Table1[[#This Row],[Tenure_Months]]) -> 46109 | AE29: NACH
A30: CUST0033 | B30: Vikas Malviya | C30: 35699 | D30: =DATEDIF(Table1[[#This Row],[Date_of_Birth]],TODAY(),"Y") -> 28 | E30: Male | F30: 9813065972 | G30: 9918040539 | H30: 539, Purani Basti, Rewa | I30: Rewa | J30: 787 | K30: 486005 | L30: XXXX-XXXX-3734 | M30: COBON9792E | N30: Complete | O30: Self-Employed | P30: 75000 | Q30: Honda | R30: City | S30: Sedan | T30: UP84HB9361 | U30: 1165235 | V30: BR005 | W30: Rewa | X30: Anita Dubey | Y30: 902931 | Z30: 36 | AA30: 13.19 | AB30: =-PMT((Table1[[#This Row],[Interest_Rate_%]]/100)/12,Table1[[#This Row],[Tenure_Months]],Table1[[#This Row],[Amount_Disbursed]]) -> 30506.012 | AC30: 45700 | AD30: =EDATE(Table1[[#This Row],[Disbursement_Date]],Table1[[#This Row],[Tenure_Months]]) -> 46795 | AE30: ECS
A31: CUST0034 | B31: Mohit Agarwal | C31: 36609 | D31: =DATEDIF(Table1[[#This Row],[Date_of_Birth]],TODAY(),"Y") -> 26 | E31: Male | F31: 9339111798 | G31: 9911941471 | H31: 306, Malviya Nagar, Indore | I31: Indore | J31: 762 | K31: 452006 | L31: XXXX-XXXX-9243 | M31: LJFLE4088X | N31: Complete | O31: Salaried | P31: 100000 | Q31: Bajaj | R31: Pulsar | S31: Two-Wheeler | T31: UP36BB1550 | U31: 72050 | V31: BR001 | W31: Indore | X31: Amit Sharma | Y31: 58457 | Z31: 48 | AA31: 15.78 | AB31: =-PMT((Table1[[#This Row],[Interest_Rate_%]]/100)/12,Table1[[#This Row],[Tenure_Months]],Table1[[#This Row],[Amount_Disbursed]]) -> 1650.1086 | AC31: 45285 | AD31: =EDATE(Table1[[#This Row],[Disbursement_Date]],Table1[[#This Row],[Tenure_Months]]) -> 46746 | AE31: PDC
A32: CUST0035 | B32: Pradeep Agarwal | C32: 36700 | D32: =DATEDIF(Table1[[#This Row],[Date_of_Birth]],TODAY(),"Y") -> 25 | E32: Male | F32: 9547025173 | G32: 9422002819 | H32: 247, Vijay Nagar, Indore | I32: Indore | J32: 698 | K32: 452003 | L32: XXXX-XXXX-2156 | M32: DMBKK9683E | N32: Pending | O32: Salaried | P32: 30000 | Q32: Tata | R32: Nexon | S32: SUV | T32: MP67FB9775 | U32: 1034765 | V32: BR001 | W32: Indore | X32: Priya Verma | Y32: 913723 | Z32: 48 | AA32: 12.43 | AB32: =-PMT((Table1[[#This Row],[Interest_Rate_%]]/100)/12,Table1[[#This Row],[Tenure_Months]],Table1[[#This Row],[Amount_Disbursed]]) -> 24255.193 | AC32: 45506 | AD32: =EDATE(Table1[[#This Row],[Disbursement_Date]],Table1[[#This Row],[Tenure_Months]]) -> 46967 | AE32: ECS
A33: CUST0036 | B33: Savita Chauhan | C33: 27014 | D33: =DATEDIF(Table1[[#This Row],[Date_of_Birth]],TODAY(),"Y") -> 52 | E33: Female | F33: 9917792874 | G33: 9318106480 | H33: 577, Civil Lines, Jabalpur | I33: Jabalpur | J33: 757 | K33: 482006 | L33: XXXX-XXXX-2466 | M33: GYPKD6404H | N33: Pending | O33: Business | P33: 30000 | Q33: Honda | R33: City | S33: Sedan | T33: MH42HH8550 | U33: 1222173 | V33: BR003 | W33: Jabalpur | X33: Kavita Yadav | Y33: 859366 | Z33: 48 | AA33: 13.81 | AB33: =-PMT((Table1[[#This Row],[Interest_Rate_%]]/100)/12,Table1[[#This Row],[Tenure_Months]],Table1[[#This Row],[Amount_Disbursed]]) -> 23401.621 | AC33: 44951 | AD33: =EDATE(Table1[[#This Row],[Disbursement_Date]],Table1[[#This Row],[Tenure_Months]]) -> 46412 | AE33: NACH
A34: CUST0037 | B34: Pushpa Yadav | C34: 26712 | D34: =DATEDIF(Table1[[#This Row],[Date_of_Birth]],TODAY(),"Y") -> 53 | E34: Female | F34: 9259877461 | H34: 274, Malviya Nagar, Indore | I34: Indore | J34: 718 | K34: 452001 | L34: XXXX-XXXX-8076 | M34: OZFRW1519C | N34: Pending | O34: Self-Employed | P34: 50000 | Q34: Mahindra | R34: Bolero | S34: MUV | T34: MP91AC2354 | U34: 962390 | V34: BR001 | W34: Indore | X34: Amit Sharma | Y34: 731277 | Z34: 48 | AA34: 11.94 | AB34: =-PMT((Table1[[#This Row],[Interest_Rate_%]]/100)/12,Table1[[#This Row],[Tenure_Months]],Table1[[#This Row],[Amount_Disbursed]]) -> 19235.792 | AC34: 45723 | AD34: =EDATE(Table1[[#This Row],[Disbursement_Date]],Table1[[#This Row],[Tenure_Months]]) -> 47184 | AE34: PDC
A35: CUST0038 | B35: Kavita Thakur | C35: 32512 | D35: =DATEDIF(Table1[[#This Row],[Date_of_Birth]],TODAY(),"Y") -> 37 | E35: Female | F35: 9569319938 | H35: 620, Habibganj, Bhopal | I35: Bhopal | J35: 795 | K35: 462005 | L35: XXXX-XXXX-8633 | M35: AHZMJ7150N | N35: Complete | O35: Business | P35: 100000 | Q35: Honda | R35: Activa | S35: Two-Wheeler | T35: MP89ED2204 | U35: 84816 | V35: BR002 | W35: Bhopal | X35: Sunita Patel | Y35: 65949 | Z35: 12 | AA35: 14.85 | AB35: =-PMT((Table1[[#This Row],[Interest_Rate_%]]/100)/12,Table1[[#This Row],[Tenure_Months]],Table1[[#This Row],[Amount_Disbursed]]) -> 5947.7785 | AC35: 45424 | AD35: =EDATE(Table1[[#This Row],[Disbursement_Date]],Table1[[#This Row],[Tenure_Months]]) -> 45789 | AE35: PDC
A36: CUST0039 | B36: Vijay Pandey | C36: 30899 | D36: =DATEDIF(Table1[[#This Row],[Date_of_Birth]],TODAY(),"Y") -> 41 | E36: Male | F36: 9167932588 | H36: 802, MP Nagar, Bhopal | I36: Bhopal | J36: 782 | K36: 462003 | L36: XXXX-XXXX-8722 | M36: QPFCH7483K | N36: Expired | O36: Self-Employed | P36: 40000 | Q36: Honda | R36: City | S36: Sedan | T36: RJ93CE6253 | U36: 1193874 | V36: BR002 | W36: Bhopal | X36: Sunita Patel | Y36: 1026179 | Z36: 60 | AA36: 10.91 | AB36: =-PMT((Table1[[#This Row],[Interest_Rate_%]]/100)/12,Table1[[#This Row],[Tenure_Months]],Table1[[#This Row],[Amount_Disbursed]]) -> 22265.587 | AC36: 45764 | AD36: =EDATE(Table1[[#This Row],[Disbursement_Date]],Table1[[#This Row],[Tenure_Months]]) -> 47590 | AE36: PDC
A37: CUST0041 | B37: Rekha Mishra | C37: 36603 | D37: =DATEDIF(Table1[[#This Row],[Date_of_Birth]],TODAY(),"Y") -> 26 | E37: Female | F37: 9271944408 | G37: 9557810637 | H37: 645, Vijay Nagar, Indore | I37: Indore | J37: 693 | K37: 452002 | L37: XXXX-XXXX-1537 | M37: LAPFP7370A | N37: Complete | O37: Salaried | P37: 20000 | Q37: Renault | R37: Kwid | S37: Hatchback | T37: CG33FF4228 | U37: 463336 | V37: BR001 | W37: Indore | X37: Amit Sharma | Y37: 377600 | Z37: 36 | AA37: 11.61 | AB37: =-PMT((Table1[[#This Row],[Interest_Rate_%]]/100)/12,Table1[[#This Row],[Tenure_Months]],Table1[[#This Row],[Amount_Disbursed]]) -> 12471.504 | AC37: 45281 | AD37: =EDATE(Table1[[#This Row],[Disbursement_Date]],Table1[[#This Row],[Tenure_Months]]) -> 46377 | AE37: PDC
A38: CUST0042 | B38: Deepak Dwivedi | C38: 25720 | D38: =DATEDIF(Table1[[#This Row],[Date_of_Birth]],TODAY(),"Y") -> 56 | E38: Male | F38: 9620344871 | H38: 419, TT Nagar, Bhopal | I38: Bhopal | J38: 756 | K38: 462004 | L38: XXXX-XXXX-0733 | M38: EOUFA4683R | N38: Complete | O38: Salaried | P38: 100000 | Q38: TVS | R38: Jupiter | S38: Two-Wheeler | T38: CG75BB5389 | U38: 104921 | V38: BR002 | W38: Bhopal | X38: Sunita Patel | Y38: 76927 | Z38: 18 | AA38: 15.21 | AB38: =-PMT((Table1[[#This Row],[Interest_Rate_%]]/100)/12,Table1[[#This Row],[Tenure_Months]],Table1[[#This Row],[Amount_Disbursed]]) -> 4806.6808 | AC38: 45350 | AD38: =EDATE(Table1[[#This Row],[Disbursement_Date]],Table1[[#This Row],[Tenure_Months]]) -> 45897 | AE38: NACH
A39: CUST0043 | B39: Rekha Joshi | C39: 31186 | D39: =DATEDIF(Table1[[#This Row],[Date_of_Birth]],TODAY(),"Y") -> 41 | E39: Female | F39: 9387057426 | G39: 9652348887 | H39: 139, Purani Basti, Rewa | I39: Rewa | J39: 631 | K39: 486001 | L39: XXXX-XXXX-6605 | M39: WDWGS5055Y | N39: Pending | O39: Self-Employed | P39: 25000 | Q39: Renault | R39: Kwid | S39: Hatchback | T39: MH90GG8405 | U39: 532890 | V39: BR005 | W39: Rewa | X39: Anita Dubey | Y39: 409020 | Z39: 48 | AA39: 11.28 | AB39: =-PMT((Table1[[#This Row],[Interest_Rate_%]]/100)/12,Table1[[#This Row],[Tenure_Months]],Table1[[#This Row],[Amount_Disbursed]]) -> 10627.039 | AC39: 45920 | AD39: =EDATE(Table1[[#This Row],[Disbursement_Date]],Table1[[#This Row],[Tenure_Months]]) -> 47381 | AE39: ECS
A40: CUST0044 | B40: Mahesh Yadav | C40: 34912 | D40: =DATEDIF(Table1[[#This Row],[Date_of_Birth]],TODAY(),"Y") -> 30 | E40: Male | F40: 9559346003 | H40: 163, Morar, Gwalior | I40: Gwalior | J40: 675 | K40: 474001 | L40: XXXX-XXXX-5144 | M40: GJXEK6005X | N40: Complete | O40: Self-Employed | P40: 20000 | Q40: TVS | R40: Jupiter | S40: Two-Wheeler | T40: MP37HB3174 | U40: 52475 | V40: BR004 | W40: Gwalior | X40: Neha Mishra | Y40: 40418 | Z40: 18 | AA40: 14.27 | AB40: =-PMT((Table1[[#This Row],[Interest_Rate_%]]/100)/12,Table1[[#This Row],[Tenure_Months]],Table1[[#This Row],[Amount_Disbursed]]) -> 2507.6042 | AC40: 45237 | AD40: =EDATE(Table1[[#This Row],[Disbursement_Date]],Table1[[#This Row],[Tenure_Months]]) -> 45784 | AE40: ECS
A41: CUST0045 | B41: Mahesh Shukla | C41: 33403 | D41: =DATEDIF(Table1[[#This Row],[Date_of_Birth]],TODAY(),"Y") -> 34 | E41: Male | F41: 9437695739 | G41: 9366058599 | H41: 567, AB Road, Indore | I41: Indore | J41: 640 | K41: 452005 | L41: XXXX-XXXX-3842 | M41: HYAWW4366Q | N41: Expired | O41: Business | P41: 30000 | Q41: TVS | R41: Jupiter | S41: Two-Wheeler | T41: MH92AD9108 | U41: 91347 | V41: BR001 | W41: Indore | X41: Priya Verma | Y41: 71681 | Z41: 36 | AA41: 10.99 | AB41: =-PMT((Table1[[#This Row],[Interest_Rate_%]]/100)/12,Table1[[#This Row],[Tenure_Months]],Table1[[#This Row],[Amount_Disbursed]]) -> 2346.4045 | AC41: 45239 | AD41: =EDATE(Table1[[#This Row],[Disbursement_Date]],Table1[[#This Row],[Tenure_Months]]) -> 46335 | AE41: ECS
A42: CUST0046 | B42: Mohit Joshi | C42: 33898 | D42: =DATEDIF(Table1[[#This Row],[Date_of_Birth]],TODAY(),"Y") -> 33 | E42: Male | F42: 9919505668 | G42: 9831277972 | H42: 748, Arera Colony, Bhopal | I42: Bhopal | J42: 713 | K42: 462001 | L42: XXXX-XXXX-3082 | M42: YDPBR3877D | N42: Complete | O42: Business | P42: 25000 | Q42: TVS | R42: Jupiter | S42: Two-Wheeler | T42: UP73FJ9474 | U42: 50000 | V42: BR002 | W42: Bhopal | X42: Rohit Gupta | Y42: 42407 | Z42: 12 | AA42: 10.76 | AB42: =-PMT((Table1[[#This Row],[Interest_Rate_%]]/100)/12,Table1[[#This Row],[Tenure_Months]],Table1[[#This Row],[Amount_Disbursed]]) -> 3743.2553 | AC42: 44952 | AD42: =EDATE(Table1[[#This Row],[Disbursement_Date]],Table1[[#This Row],[Tenure_Months]]) -> 45317 | AE42: NACH
A43: CUST0047 | B43: Suresh Malviya | C43: 34070 | D43: =DATEDIF(Table1[[#This Row],[Date_of_Birth]],TODAY(),"Y") -> 33 | E43: Male | F43: 9366570563 | G43: 9873403266 | H43: 123, Habibganj, Bhopal | I43: Bhopal | J43: 631 | K43: 462006 | L43: XXXX-XXXX-2002 | M43: EUZYB8620J | N43: Complete | O43: Self-Employed | P43: 20000 | Q43: Mahindra | R43: Bolero | S43: MUV | T43: MP57DE5979 | U43: 959866 | V43: BR002 | W43: Bhopal | X43: Sunita Patel | Y43: 766362 | Z43: 12 | AA43: 16.34 | AB43: =-PMT((Table1[[#This Row],[Interest_Rate_%]]/100)/12,Table1[[#This Row],[Tenure_Months]],Table1[[#This Row],[Amount_Disbursed]]) -> 69656.045 | AC43: 45218 | AD43: =EDATE(Table1[[#This Row],[Disbursement_Date]],Table1[[#This Row],[Tenure_Months]]) -> 45584 | AE43: PDC
A44: CUST0048 | B44: Anil Chauhan | C44: 26576 | D44: =DATEDIF(Table1[[#This Row],[Date_of_Birth]],TODAY(),"Y") -> 53 | E44: Male | F44: 9642698931 | H44: 446, Indira Nagar, Rewa | I44: Rewa | J44: 655 | K44: 486002 | L44: XXXX-XXXX-0530 | M44: WYKVI8417I | N44: Complete | O44: Salaried | P44: 25000 | Q44: Bajaj | R44: Pulsar | S44: Two-Wheeler | T44: MP29BC8365 | U44: 146638 | V44: BR005 | W44: Rewa | X44: Anita Dubey | Y44: 127710 | Z44: 48 | AA44: 14.99 | AB44: =-PMT((Table1[[#This Row],[Interest_Rate_%]]/100)/12,Table1[[#This Row],[Tenure_Months]],Table1[[#This Row],[Amount_Disbursed]]) -> 3553.6175 | AC44: 45438 | AD44: =EDATE(Table1[[#This Row],[Disbursement_Date]],Table1[[#This Row],[Tenure_Months]]) -> 46899 | AE44: NACH
A45: CUST0049 | B45: Sanjay Singh | C45: 29048 | D45: =DATEDIF(Table1[[#This Row],[Date_of_Birth]],TODAY(),"Y") -> 46 | E45: Male | F45: 9836893185 | G45: 9792225271 | H45: 601, Palasia, Indore | I45: Indore | J45: 666 | K45: 452001 | L45: XXXX-XXXX-0085 | M45: XLDXV6432D | N45: Complete | O45: Self-Employed | P45: 15000 | Q45: Maruti | R45: Brezza | S45: SUV | T45: RJ60HA7270 | U45: 1125220 | V45: BR001 | W45: Indore | X45: Priya Verma | Y45: 910194 | Z45: 36 | AA45: 12.56 | AB45: =-PMT((Table1[[#This Row],[Interest_Rate_%]]/100)/12,Table1[[#This Row],[Tenure_Months]],Table1[[#This Row],[Amount_Disbursed]]) -> 30475.49 | AC45: 45955 | AD45: =EDATE(Table1[[#This Row],[Disbursement_Date]],Table1[[#This Row],[Tenure_Months]]) -> 47051 | AE45: ECS
A46: CUST0050 | B46: Pooja Sharma | C46: 30707 | D46: =DATEDIF(Table1[[#This Row],[Date_of_Birth]],TODAY(),"Y") -> 42 | E46: Female | F46: 9606467254 | G46: 9923390510 | H46: 103, Civil Lines, Jabalpur | I46: Jabalpur | J46: 697 | K46: 482006 | L46: XXXX-XXXX-9507 | M46: NUTTY7363L | N46: Complete | O46: Salaried | P46: 100000 | Q46: Tata | R46: Nexon | S46: SUV | T46: MH85AF3328 | U46: 1046744 | V46: BR003 | W46: Jabalpur | X46: Kavita Yadav | Y46: 933812 | Z46: 24 | AA46: 14.73 | AB46: =-PMT((Table1[[#This Row],[Interest_Rate_%]]/100)/12,Table1[[#This Row],[Tenure_Months]],Table1[[#This Row],[Amount_Disbursed]]) -> 45157.715 | AC46: 45737 | AD46: =EDATE(Table1[[#This Row],[Disbursement_Date]],Table1[[#This Row],[Tenure_Months]]) -> 46467 | AE46: PDC
A47: CUST0051 | B47: Vikas Rajput | C47: 31859 | D47: =DATEDIF(Table1[[#This Row],[Date_of_Birth]],TODAY(),"Y") -> 39 | E47: Male | F47: 9703418543 | G47: 9758965006 | H47: 388, Kolar Road, Bhopal | I47: Bhopal | J47: 628 | K47: 462006 | L47: XXXX-XXXX-5497 | M47: DSYYK1530F | N47: Expired | O47: Self-Employed | P47: 100000 | Q47: Hyundai | R47: i20 | S47: Hatchback | T47: CG23HC6425 | U47: 783839 | V47: BR002 | W47: Bhopal | X47: Rohit Gupta | Y47: 678617 | Z47: 48 | AA47: 14.41 | AB47: =-PMT((Table1[[#This Row],[Interest_Rate_%]]/100)/12,Table1[[#This Row],[Tenure_Months]],Table1[[#This Row],[Amount_Disbursed]]) -> 18684.083 | AC47: 45388 | AD47: =EDATE(Table1[[#This Row],[Disbursement_Date]],Table1[[#This Row],[Tenure_Months]]) -> 46849 | AE47: NACH
A48: CUST0052 | B48: Vijay Patel | C48: 26090 | D48: =DATEDIF(Table1[[#This Row],[Date_of_Birth]],TODAY(),"Y") -> 55 | E48: Male | F48: 9503144836 | H48: 965, MG Road, Indore | I48: Indore | J48: 688 | K48: 452003 | L48: XXXX-XXXX-1981 | M48: AYEXE2659K | N48: Complete | O48: Salaried | P48: 75000 | Q48: TVS | R48: Jupiter | S48: Two-Wheeler | T48: CG43EE4891 | U48: 135679 | V48: BR001 | W48: Indore | X48: Priya Verma | Y48: 104999 | Z48: 36 | AA48: 10.77 | AB48: =-PMT((Table1[[#This Row],[Interest_Rate_%]]/100)/12,Table1[[#This Row],[Tenure_Months]],Table1[[#This Row],[Amount_Disbursed]]) -> 3426.1074 | AC48: 45827 | AD48: =EDATE(Table1[[#This Row],[Disbursement_Date]],Table1[[#This Row],[Tenure_Months]]) -> 46923 | AE48: ECS
A49: CUST0053 | B49: Santosh Patel | C49: 26615 | D49: =DATEDIF(Table1[[#This Row],[Date_of_Birth]],TODAY(),"Y") -> 53 | E49: Male | F49: 9967776836 | G49: 9912239392 | H49: 861, Malviya Nagar, Indore | I49: Indore | J49: 693 | K49: 452005 | L49: XXXX-XXXX-3672 | M49: WMWMC1568Q | N49: Expired | O49: Business | P49: 100000 | Q49: Honda | R49: Activa | S49: Two-Wheeler | T49: UP25HC3738 | U49: 116300 | V49: BR001 | W49: Indore | X49: Amit Sharma | Y49: 91049 | Z49: 18 | AA49: 13.9 | AB49: =-PMT((Table1[[#This Row],[Interest_Rate_%]]/100)/12,Table1[[#This Row],[Tenure_Months]],Table1[[#This Row],[Amount_Disbursed]]) -> 5633.0491 | AC49: 45132 | AD49: =EDATE(Table1[[#This Row],[Disbursement_Date]],Table1[[#This Row],[Tenure_Months]]) -> 45682 | AE49: NACH
A50: CUST0054 | B50: Vijay Agarwal | C50: 36088 | D50: =DATEDIF(Table1[[#This Row],[Date_of_Birth]],TODAY(),"Y") -> 27 | E50: Male | F50: 9607929943 | H50: 40, Gorakhpur, Jabalpur | I50: Jabalpur | J50: 794 | K50: 482003 | L50: XXXX-XXXX-1768 | M50: BMGJI5965J | N50: Complete | O50: Self-Employed | P50: 20000 | Q50: Hero | R50: Splendor | S50: Two-Wheeler | T50: UP48HF5414 | U50: 54878 | V50: BR003 | W50: Jabalpur | X50: Kavita Yadav | Y50: 46148 | Z50: 24 | AA50: 12.71 | AB50: =-PMT((Table1[[#This Row],[Interest_Rate_%]]/100)/12,Table1[[#This Row],[Tenure_Months]],Table1[[#This Row],[Amount_Disbursed]]) -> 2187.6792 | AC50: 45877 | AD50: =EDATE(Table1[[#This Row],[Disbursement_Date]],Table1[[#This Row],[Tenure_Months]]) -> 46607 | AE50: PDC
A51: CUST0055 | B51: Lalit Dwivedi | C51: 34786 | D51: =DATEDIF(Table1[[#This Row],[Date_of_Birth]],TODAY(),"Y") -> 31 | E51: Male | F51: 9609578849 | G51: 9475551835 | H51: 292, MP Nagar, Bhopal | I51: Bhopal | J51: 668 | K51: 462004 | L51: XXXX-XXXX-8764 | M51: WUFFF4387I | N51: Pending | O51: Business | P51: 15000 | Q51: Hero | R51: Splendor | S51: Two-Wheeler | T51: MP70CC1138 | U51: 114417 | V51: BR002 | W51: Bhopal | X51: Rohit Gupta | Y51: 87787 | Z51: 24 | AA51: 14.34 | AB51: =-PMT((Table1[[#This Row],[Interest_Rate_%]]/100)/12,Table1[[#This Row],[Tenure_Months]],Table1[[#This Row],[Amount_Disbursed]]) -> 4229.0211 | AC51: 45494 | AD51: =EDATE(Table1[[#This Row],[Disbursement_Date]],Table1[[#This Row],[Tenure_Months]]) -> 46224 | AE51: ECS
A52: CUST0056 | B52: Suresh Dwivedi | C52: 33919 | D52: =DATEDIF(Table1[[#This Row],[Date_of_Birth]],TODAY(),"Y") -> 33 | E52: Male | F52: 9830955923 | H52: 510, Chorhata, Rewa | I52: Rewa | J52: 655 | K52: 486003 | L52: XXXX-XXXX-6182 | M52: KTPZV6622X | N52: Complete | O52: Business | P52: 75000 | Q52: Honda | R52: Activa | S52: Two-Wheeler | T52: MH74EC3967 | U52: 97355 | V52: BR005 | W52: Rewa | X52: Manoj Joshi | Y52: 77893 | Z52: 60 | AA52: 12.79 | AB52: =-PMT((Table1[[#This Row],[Interest_Rate_%]]/100)/12,Table1[[#This Row],[Tenure_Months]],Table1[[#This Row],[Amount_Disbursed]]) -> 1763.9428 | AC52: 45538 | AD52: =EDATE(Table1[[#This Row],[Disbursement_Date]],Table1[[#This Row],[Tenure_Months]]) -> 47364 | AE52: ECS
A53: CUST0058 | B53: Geeta Tiwari | C53: 25128 | D53: =DATEDIF(Table1[[#This Row],[Date_of_Birth]],TODAY(),"Y") -> 57 | E53: Female | F53: 9281445989 | H53: 898, Kolar Road, Bhopal | I53: Bhopal | J53: 658 | K53: 462005 | L53: XXXX-XXXX-1069 | M53: PBCVB2897N | N53: Pending | O53: Self-Employed | P53: 20000 | Q53: Mahindra | R53: Bolero | S53: MUV | T53: RJ99CD1152 | U53: 933126 | V53: BR002 | W53: Bhopal | X53: Sunita Patel | Y53: 696952 | Z53: 12 | AA53: 14.53 | AB53: =-PMT((Table1[[#This Row],[Interest_Rate_%]]/100)/12,Table1[[#This Row],[Tenure_Months]],Table1[[#This Row],[Amount_Disbursed]]) -> 62751.246 | AC53: 45153 | AD53: =EDATE(Table1[[#This Row],[Disbursement_Date]],Table1[[#This Row],[Tenure_Months]]) -> 45519 | AE53: PDC
A54: CUST0059 | B54: Mahesh Dubey | C54: 29808 | D54: =DATEDIF(Table1[[#This Row],[Date_of_Birth]],TODAY(),"Y") -> 44 | E54: Male | F54: 9383602087 | G54: 9207169001 | H54: 369, Chorhata, Rewa | I54: Rewa | J54: 787 | K54: 486004 | L54: XXXX-XXXX-7596 | M54: CTBWR3793K | N54: Complete | O54: Self-Employed | P54: 100000 | Q54: Hyundai | R54: Creta | S54: SUV | T54: MP57FC2865 | U54: 1446084 | V54: BR005 | W54: Rewa | X54: Anita Dubey | Y54: 1278453 | Z54: 12 | AA54: 15.83 | AB54: =-PMT((Table1[[#This Row],[Interest_Rate_%]]/100)/12,Table1[[#This Row],[Tenure_Months]],Table1[[#This Row],[Amount_Disbursed]]) -> 115892.31 | AC54: 45829 | AD54: =EDATE(Table1[[#This Row],[Disbursement_Date]],Table1[[#This Row],[Tenure_Months]]) -> 46194 | AE54: NACH
A55: CUST0060 | B55: Mamta Shukla | C55: 37733 | D55: =DATEDIF(Table1[[#This Row],[Date_of_Birth]],TODAY(),"Y") -> 23 | E55: Female | F55: 9463247548 | G55: 9838993835 | H55: 678, Vijay Nagar, Indore | I55: Indore | J55: 788 | K55: 452004 | L55: XXXX-XXXX-5774 | M55: RKVOZ1894A | N55: Complete | O55: Business | P55: 60000 | Q55: Hero | R55: Splendor | S55: Two-Wheeler | T55: UP19HF4946 | U55: 89990 | V55: BR001 | W55: Indore | X55: Priya Verma | Y55: 80097 | Z55: 24 | AA55: 15.45 | AB55: =-PMT((Table1[[#This Row],[Interest_Rate_%]]/100)/12,Table1[[#This Row],[Tenure_Months]],Table1[[#This Row],[Amount_Disbursed]]) -> 3900.7818 | AC55: 45383 | AD55: =EDATE(Table1[[#This Row],[Disbursement_Date]],Table1[[#This Row],[Tenure_Months]]) -> 46113 | AE55: ECS
A56: CUST0061 | B56: Mahesh Mishra | C56: 24635 | D56: =DATEDIF(Table1[[#This Row],[Date_of_Birth]],TODAY(),"Y") -> 58 | E56: Male | F56: 9991081037 | G56: 9958899743 | H56: 719, Lashkar, Gwalior | I56: Gwalior | J56: 774 | K56: 474001 | L56: XXXX-XXXX-4348 | M56: MVTKG4209G | N56: Complete | O56: Self-Employed | P56: 30000 | Q56: Honda | R56: City | S56: Sedan | T56: MH23GA3018 | U56: 1174979 | V56: BR004 | W56: Gwalior | X56: Neha Mishra | Y56: 915983 | Z56: 24 | AA56: 16.32 | AB56: =-PMT((Table1[[#This Row],[Interest_Rate_%]]/100)/12,Table1[[#This Row],[Tenure_Months]],Table1[[#This Row],[Amount_Disbursed]]) -> 44989.556 | AC56: 45854 | AD56: =EDATE(Table1[[#This Row],[Disbursement_Date]],Table1[[#This Row],[Tenure_Months]]) -> 46584 | AE56: NACH
A57: CUST0062 | B57: Mohit Joshi | C57: 37567 | D57: =DATEDIF(Table1[[#This Row],[Date_of_Birth]],TODAY(),"Y") -> 23 | E57: Male | F57: 9315703009 | H57: 944, Indira Nagar, Rewa | I57: Rewa | J57: 684 | K57: 486006 | L57: XXXX-XXXX-9112 | M57: NSIDJ8870S | N57: Expired | O57: Business | P57: 50000 | Q57: Honda | R57: Activa | S57: Two-Wheeler | T57: CG46GA9564 | U57: 133024 | V57: BR005 | W57: Rewa | X57: Manoj Joshi | Y57: 117765 | Z57: 36 | AA57: 13 | AB57: =-PMT((Table1[[#This Row],[Interest_Rate_%]]/100)/12,Table1[[#This Row],[Tenure_Months]],Table1[[#This Row],[Amount_Disbursed]]) -> 3967.9683 | AC57: 45567 | AD57: =EDATE(Table1[[#This Row],[Disbursement_Date]],Table1[[#This Row],[Tenure_Months]]) -> 46662 | AE57: PDC
A58: CUST0063 | B58: Sanjay Soni | C58: 38254 | D58: =DATEDIF(Table1[[#This Row],[Date_of_Birth]],TODAY(),"Y") -> 21 | E58: Male | F58: 9747881832 | H58: 460, Indira Nagar, Rewa | I58: Rewa | J58: 717 | K58: 486006 | L58: XXXX-XXXX-4805 | M58: ZTDBH5329E | N58: Complete | O58: Business | P58: 35000 | Q58: Maruti | R58: Swift | S58: Hatchback | T58: RJ29AC6285 | U58: 643327 | V58: BR005 | W58: Rewa | X58: Manoj Joshi | Y58: 465089 | Z58: 24 | AA58: 13.17 | AB58: =-PMT((Table1[[#This Row],[Interest_Rate_%]]/100)/12,Table1[[#This Row],[Tenure_Months]],Table1[[#This Row],[Amount_Disbursed]]) -> 22148.334 | AC58: 45426 | AD58: =EDATE(Table1[[#This Row],[Disbursement_Date]],Table1[[#This Row],[Tenure_Months]]) -> 46156 | AE58: NACH
A59: CUST0064 | B59: Mohit Pandey | C59: 25108 | D59: =DATEDIF(Table1[[#This Row],[Date_of_Birth]],TODAY(),"Y") -> 57 | E59: Male | F59: 9927311980 | G59: 9962017907 | H59: 304, City Centre, Gwalior | I59: Gwalior | J59: 789 | K59: 474003 | L59: XXXX-XXXX-4145 | M59: YEYNA2072G | N59: Complete | O59: Business | P59: 50000 | Q59: Hero | R59: Splendor | S59: Two-Wheeler | T59: UP78GB3519 | U59: 50000 | V59: BR004 | W59: Gwalior | X59: Neha Mishra | Y59: 42868 | Z59: 24 | AA59: 14.14 | AB59: =-PMT((Table1[[#This Row],[Interest_Rate_%]]/100)/12,Table1[[#This Row],[Tenure_Months]],Table1[[#This Row],[Amount_Disbursed]]) -> 2061.0526 | AC59: 45503 | AD59: =EDATE(Table1[[#This Row],[Disbursement_Date]],Table1[[#This Row],[Tenure_Months]]) -> 46233 | AE59: ECS
A60: CUST0065 | B60: Mohit Mishra | C60: 27741 | D60: =DATEDIF(Table1[[#This Row],[Date_of_Birth]],TODAY(),"Y") -> 50 | E60: Male | F60: 9955525741 | G60: 9685967190 | H60: 306, Morar, Gwalior | I60: Gwalior | J60: 683 | K60: 474001 | L60: XXXX-XXXX-9063 | M60: DAPNY5992G | N60: Complete | O60: Salaried | P60: 75000 | Q60: Maruti | R60: Brezza | S60: SUV | T60: UP38ED2877 | U60: 1071096 | V60: BR004 | W60: Gwalior | X60: Sanjay Tiwari | Y60: 870919 | Z60: 24 | AA60: 15.35 | AB60: =-PMT((Table1[[#This Row],[Interest_Rate_%]]/100)/12,Table1[[#This Row],[Tenure_Months]],Table1[[#This Row],[Amount_Disbursed]]) -> 42372.912 | AC60: 45804 | AD60: =EDATE(Table1[[#This Row],[Disbursement_Date]],Table1[[#This Row],[Tenure_Months]]) -> 46534 | AE60: NACH
A61: CUST0066 | B61: Anil Singh | C61: 32370 | D61: =DATEDIF(Table1[[#This Row],[Date_of_Birth]],TODAY(),"Y") -> 37 | E61: Male | F61: 9578199481 | G61: 9427997841 | H61: 662, Maharajpura, Gwalior | I61: Gwalior | J61: 714 | K61: 474001 | L61: XXXX-XXXX-1403 | M61: WDOGX2252X | N61: Complete | O61: Salaried | P61: 15000 | Q61: Hero | R61: Splendor | S61: Two-Wheeler | T61: CG61DA5269 | U61: 101269 | V61: BR004 | W61: Gwalior | X61: Neha Mishra | Y61: 89910 | Z61: 12 | AA61: 11.81 | AB61: =-PMT((Table1[[#This Row],[Interest_Rate_%]]/100)/12,Table1[[#This Row],[Tenure_Months]],Table1[[#This Row],[Amount_Disbursed]]) -> 7980.4053 | AC61: 45925 | AD61: =EDATE(Table1[[#This Row],[Disbursement_Date]],Table1[[#This Row],[Tenure_Months]]) -> 46290 | AE61: NACH
A62: CUST0067 | B62: Meena Thakur | C62: 33070 | D62: =DATEDIF(Table1[[#This Row],[Date_of_Birth]],TODAY(),"Y") -> 35 | E62: Female | F62: 9588169687 | G62: 9142847338 | H62: 721, AB Road, Indore | I62: Indore | J62: 666 | K62: 452006 | L62: XXXX-XXXX-8115 | M62: VGOEQ6985S | N62: Complete | O62: Business | P62: 35000 | Q62: Tata | R62: Tiago | S62: Hatchback | T62: CG61FF8976 | U62: 579215 | V62: BR001 | W62: Indore | X62: Amit Sharma | Y62: 421057 | Z62: 48 | AA62: 10.74 | AB62: =-PMT((Table1[[#This Row],[Interest_Rate_%]]/100)/12,Table1[[#This Row],[Tenure_Months]],Table1[[#This Row],[Amount_Disbursed]]) -> 10829.35 | AC62: 45227 | AD62: =EDATE(Table1[[#This Row],[Disbursement_Date]],Table1[[#This Row],[Tenure_Months]]) -> 46688 | AE62: NACH
A63: CUST0068 | B63: Seema Sharma | C63: 31085 | D63: =DATEDIF(Table1[[#This Row],[Date_of_Birth]],TODAY(),"Y") -> 41 | E63: Female | F63: 9582328432 | G63: 9606176343 | H63: 851, Thatipur, Gwalior | I63: Gwalior | J63: 728 | K63: 474005 | L63: XXXX-XXXX-5037 | M63: PTQNE6614O | N63: Expired | O63: Business | P63: 20000 | Q63: Hyundai | R63: i20 | S63: Hatchback | T63: RJ26BA4315 | U63: 749572 | V63: BR004 | W63: Gwalior | X63: Sanjay Tiwari | Y63: 665383 | Z63: 36 | AA63: 15.24 | AB63: =-PMT((Table1[[#This Row],[Interest_Rate_%]]/100)/12,Table1[[#This Row],[Tenure_Months]],Table1[[#This Row],[Amount_Disbursed]]) -> 23143.999 | AC63: 45707 | AD63: =EDATE(Table1[[#This Row],[Disbursement_Date]],Table1[[#This Row],[Tenure_Months]]) -> 46802 | AE63: ECS
A64: CUST0069 | B64: Sanjay Gupta | C64: 31338 | D64: =DATEDIF(Table1[[#This Row],[Date_of_Birth]],TODAY(),"Y") -> 40 | E64: Male | F64: 9538781057 | H64: 762, Napier Town, Jabalpur | I64: Jabalpur | J64: 642 | K64: 482005 | L64: XXXX-XXXX-3808 | M64: NJFUK2746E | N64: Pending | O64: Business | P64: 100000 | Q64: Hyundai | R64: Creta | S64: SUV | T64: CG64FE7511 | U64: 1384249 | V64: BR003 | W64: Jabalpur | X64: Vikas Singh | Y64: 1076697 | Z64: 60 | AA64: 10.53 | AB64: =-PMT((Table1[[#This Row],[Interest_Rate_%]]/100)/12,Table1[[#This Row],[Tenure_Months]],Table1[[#This Row],[Amount_Disbursed]]) -> 23158.423 | AC64: 45113 | AD64: =EDATE(Table1[[#This Row],[Disbursement_Date]],Table1[[#This Row],[Tenure_Months]]) -> 46940 | AE64: NACH
A65: CUST0071 | B65: Savita Mishra | C65: 32377 | D65: =DATEDIF(Table1[[#This Row],[Date_of_Birth]],TODAY(),"Y") -> 37 | E65: Female | F65: 9594694805 | G65: 9129367590 | H65: 392, City Centre, Gwalior | I65: Gwalior | J65: 721 | K65: 474006 | L65: XXXX-XXXX-1599 | M65: UKJNS5314H | N65: Complete | O65: Salaried | P65: 40000 | Q65: Maruti | R65: Dzire | S65: Sedan | T65: UP70FF4580 | U65: 722686 | V65: BR004 | W65: Gwalior | X65: Neha Mishra | Y65: 595589 | Z65: 36 | AA65: 15.89 | AB65: =-PMT((Table1[[#This Row],[Interest_Rate_%]]/100)/12,Table1[[#This Row],[Tenure_Months]],Table1[[#This Row],[Amount_Disbursed]]) -> 20906.812 | AC65: 45489 | AD65: =EDATE(Table1[[#This Row],[Disbursement_Date]],Table1[[#This Row],[Tenure_Months]]) -> 46584 | AE65: ECS
A66: CUST0072 | B66: Suresh Thakur | C66: 34564 | D66: =DATEDIF(Table1[[#This Row],[Date_of_Birth]],TODAY(),"Y") -> 31 | E66: Male | F66: 9134963873 | G66: 9522750321 | H66: 124, Station Road, Rewa | I66: Rewa | J66: 635 | K66: 486004 | L66: XXXX-XXXX-5967 | M66: ARJCJ5254F | N66: Expired | O66: Self-Employed | P66: 30000 | Q66: Hyundai | R66: Creta | S66: SUV | T66: CG53FC9171 | U66: 1411780 | V66: BR005 | W66: Rewa | X66: Anita Dubey | Y66: 1072962 | Z66: 48 | AA66: 15.65 | AB66: =-PMT((Table1[[#This Row],[Interest_Rate_%]]/100)/12,Table1[[#This Row],[Tenure_Months]],Table1[[#This Row],[Amount_Disbursed]]) -> 30216.056 | AC66: 45024 | AD66: =EDATE(Table1[[#This Row],[Disbursement_Date]],Table1[[#This Row],[Tenure_Months]]) -> 46485 | AE66: ECS
A67: CUST0073 | B67: Pradeep Patel | C67: 35044 | D67: =DATEDIF(Table1[[#This Row],[Date_of_Birth]],TODAY(),"Y") -> 30 | E67: Male | F67: 9378924968 | G67: 9701671267 | H67: 21, Gorakhpur, Jabalpur | I67: Jabalpur | J67: 644 | K67: 482001 | L67: XXXX-XXXX-4053 | M67: OQNZH6326V | N67: Expired | O67: Self-Employed | P67: 60000 | Q67: Maruti | R67: Dzire | S67: Sedan | T67: CG46HC3745 | U67: 699947 | V67: BR003 | W67: Jabalpur | X67: Kavita Yadav | Y67: 621614 | Z67: 60 | AA67: 15 | AB67: =-PMT((Table1[[#This Row],[Interest_Rate_%]]/100)/12,Table1[[#This Row],[Tenure_Months]],Table1[[#This Row],[Amount_Disbursed]]) -> 14788.154 | AC67: 45358 | AD67: =EDATE(Table1[[#This Row],[Disbursement_Date]],Table1[[#This Row],[Tenure_Months]]) -> 47184 | AE67: NACH
A68: CUST0074 | B68: Sunita Sharma | C68: 33872 | D68: =DATEDIF(Table1[[#This Row],[Date_of_Birth]],TODAY(),"Y") -> 33 | E68: Female | F68: 9189390303 | H68: 317, City Centre, Gwalior | I68: Gwalior | J68: 785 | K68: 474002 | L68: XXXX-XXXX-4107 | M68: LDNEA6846K | N68: Pending | O68: Self-Employed | P68: 75000 | Q68: Hyundai | R68: Creta | S68: SUV | T68: RJ27CH8126 | U68: 1421898 | V68: BR004 | W68: Gwalior | X68: Sanjay Tiwari | Y68: 1151228 | Z68: 18 | AA68: 12.97 | AB68: =-PMT((Table1[[#This Row],[Interest_Rate_%]]/100)/12,Table1[[#This Row],[Tenure_Months]],Table1[[#This Row],[Amount_Disbursed]]) -> 70724.077 | AC68: 45822 | AD68: =EDATE(Table1[[#This Row],[Disbursement_Date]],Table1[[#This Row],[Tenure_Months]]) -> 46370 | AE68: ECS
A69: CUST0075 | B69: Vijay Gupta | C69: 34646 | D69: =DATEDIF(Table1[[#This Row],[Date_of_Birth]],TODAY(),"Y") -> 31 | E69: Male | F69: 9654705830 | G69: 9758435897 | H69: 292, Maharajpura, Gwalior | I69: Gwalior | J69: 670 | K69: 474003 | L69: XXXX-XXXX-8868 | M69: WEHQQ5458W | N69: Expired | O69: Self-Employed | P69: 30000 | Q69: Tata | R69: Nexon | S69: SUV | T69: UP16AC2675 | U69: 952542 | V69: BR004 | W69: Gwalior | X69: Sanjay Tiwari | Y69: 690014 | Z69: 60 | AA69: 11.99 | AB69: =-PMT((Table1[[#This Row],[Interest_Rate_%]]/100)/12,Table1[[#This Row],[Tenure_Months]],Table1[[#This Row],[Amount_Disbursed]]) -> 15345.494 | AC69: 45834 | AD69: =EDATE(Table1[[#This Row],[Disbursement_Date]],Table1[[#This Row],[Tenure_Months]]) -> 47660 | AE69: NACH
A70: CUST0076 | B70: Meena Rajput | C70: 33552 | D70: =DATEDIF(Table1[[#This Row],[Date_of_Birth]],TODAY(),"Y") -> 34 | E70: Female | F70: 9446886458 | H70: 260, Malviya Nagar, Indore | I70: Indore | J70: 668 | K70: 452006 | L70: XXXX-XXXX-7243 | M70: JBRZG8113K | N70: Complete | O70: Salaried | P70: 100000 | Q70: Maruti | R70: Dzire | S70: Sedan | T70: UP11AH3539 | U70: 701879 | V70: BR001 | W70: Indore | X70: Priya Verma | Y70: 617465 | Z70: 36 | AA70: 14.74 | AB70: =-PMT((Table1[[#This Row],[Interest_Rate_%]]/100)/12,Table1[[#This Row],[Tenure_Months]],Table1[[#This Row],[Amount_Disbursed]]) -> 21326.093 | AC70: 45530 | AD70: =EDATE(Table1[[#This Row],[Disbursement_Date]],Table1[[#This Row],[Tenure_Months]]) -> 46625 | AE70: PDC
A71: CUST0078 | B71: Suresh Dwivedi | C71: 30927 | D71: =DATEDIF(Table1[[#This Row],[Date_of_Birth]],TODAY(),"Y") -> 41 | E71: Male | F71: 9888448988 | H71: 104, City Centre, Gwalior | I71: Gwalior | J71: 696 | K71: 474005 | L71: XXXX-XXXX-4636 | M71: FROYO7802X | N71: Complete | O71: Business | P71: 100000 | Q71: Tata | R71: Nexon | S71: SUV | T71: RJ99GB3733 | U71: 1038407 | V71: BR004 | W71: Gwalior | X71: Sanjay Tiwari | Y71: 877726 | Z71: 24 | AA71: 14.07 | AB71: =-PMT((Table1[[#This Row],[Interest_Rate_%]]/100)/12,Table1[[#This Row],[Tenure_Months]],Table1[[#This Row],[Amount_Disbursed]]) -> 42171.187 | AC71: 45987 | AD71: =EDATE(Table1[[#This Row],[Disbursement_Date]],Table1[[#This Row],[Tenure_Months]]) -> 46717 | AE71: NACH
A72: CUST0079 | B72: Rajesh Dubey | C72: 37517 | D72: =DATEDIF(Table1[[#This Row],[Date_of_Birth]],TODAY(),"Y") -> 23 | E72: Male | F72: 9712750316 | G72: 9266123743 | H72: 472, Kolar Road, Bhopal | I72: Bhopal | J72: 694 | K72: 462002 | L72: XXXX-XXXX-7506 | M72: JPGVC7550S | N72: Complete | O72: Business | P72: 20000 | Q72: TVS | R72: Jupiter | S72: Two-Wheeler | T72: RJ32HB5921 | U72: 82558 | V72: BR002 | W72: Bhopal | X72: Rohit Gupta | Y72: 68913 | Z72: 36 | AA72: 16.33 | AB72: =-PMT((Table1[[#This Row],[Interest_Rate_%]]/100)/12,Table1[[#This Row],[Tenure_Months]],Table1[[#This Row],[Amount_Disbursed]]) -> 2434.019 | AC72: 45960 | AD72: =EDATE(Table1[[#This Row],[Disbursement_Date]],Table1[[#This Row],[Tenure_Months]]) -> 47056 | AE72: NACH
A73: CUST0080 | B73: Manoj Gupta | C73: 35727 | D73: =DATEDIF(Table1[[#This Row],[Date_of_Birth]],TODAY(),"Y") -> 28 | E73: Male | F73: 9152947385 | G73: 9381919481 | H73: 514, TT Nagar, Bhopal | I73: Bhopal | J73: 757 | K73: 462006 | L73: XXXX-XXXX-9822 | M73: DOMQF9589H | N73: Complete | O73: Salaried | P73: 50000 | Q73: Tata | R73: Nexon | S73: SUV | T73: CG21BG7939 | U73: 1039749 | V73: BR002 | W73: Bhopal | X73: Rohit Gupta | Y73: 799207 | Z73: 12 | AA73: 12.33 | AB73: =-PMT((Table1[[#This Row],[Interest_Rate_%]]/100)/12,Table1[[#This Row],[Tenure_Months]],Table1[[#This Row],[Amount_Disbursed]]) -> 71132.012 | AC73: 45891 | AD73: =EDATE(Table1[[#This Row],[Disbursement_Date]],Table1[[#This Row],[Tenure_Months]]) -> 46256 | AE73: NACH
A74: CUST0081 | B74: Mamta Dubey | C74: 37488 | D74: =DATEDIF(Table1[[#This Row],[Date_of_Birth]],TODAY(),"Y") -> 23 | E74: Female | F74: 9883749478 | G74: 9846326954 | H74: 597, Habibganj, Bhopal | I74: Bhopal | J74: 658 | K74: 462001 | L74: XXXX-XXXX-0380 | M74: BFSHM1136C | N74: Pending | O74: Business | P74: 35000 | Q74: Honda | R74: Activa | S74: Two-Wheeler | T74: MH23AE7332 | U74: 121520 | V74: BR002 | W74: Bhopal | X74: Rohit Gupta | Y74: 100273 | Z74: 36 | AA74: 15.84 | AB74: =-PMT((Table1[[#This Row],[Interest_Rate_%]]/100)/12,Table1[[#This Row],[Tenure_Months]],Table1[[#This Row],[Amount_Disbursed]]) -> 3517.3855 | AC74: 44987 | AD74: =EDATE(Table1[[#This Row],[Disbursement_Date]],Table1[[#This Row],[Tenure_Months]]) -> 46083 | AE74: PDC
A75: CUST0082 | B75: Geeta Gupta | C75: 33503 | D75: =DATEDIF(Table1[[#This Row],[Date_of_Birth]],TODAY(),"Y") -> 34 | E75: Female | F75: 9757611451 | G75: 9837148793 | H75: 437, Morar, Gwalior | I75: Gwalior | J75: 786 | K75: 474005 | L75: XXXX-XXXX-8930 | M75: OFDOU3262J | N75: Expired | O75: Salaried | P75: 25000 | Q75: Honda | R75: Activa | S75: Two-Wheeler | T75: UP50BJ9732 | U75: 109035 | V75: BR004 | W75: Gwalior | X75: Sanjay Tiwari | Y75: 91314 | Z75: 24 | AA75: 10.98 | AB75: =-PMT((Table1[[#This Row],[Interest_Rate_%]]/100)/12,Table1[[#This Row],[Tenure_Months]],Table1[[#This Row],[Amount_Disbursed]]) -> 4255.1003 | AC75: 45903 | AD75: =EDATE(Table1[[#This Row],[Disbursement_Date]],Table1[[#This Row],[Tenure_Months]]) -> 46633 | AE75: NACH
A76: CUST0083 | B76: Lalit Rajput | C76: 27460 | D76: =DATEDIF(Table1[[#This Row],[Date_of_Birth]],TODAY(),"Y") -> 51 | E76: Male | F76: 9342958848 | H76: 974, TT Nagar, Bhopal | I76: Bhopal | J76: 643 | K76: 462002 | L76: XXXX-XXXX-8157 | M76: ZTBYZ9027W | N76: Complete | O76: Self-Employed | P76: 30000 | Q76: Tata | R76: Tiago | S76: Hatchback | T76: MP87GF7457 | U76: 603066 | V76: BR002 | W76: Bhopal | X76: Rohit Gupta | Y76: 473100 | Z76: 48 | AA76: 16.01 | AB76: =-PMT((Table1[[#This Row],[Interest_Rate_%]]/100)/12,Table1[[#This Row],[Tenure_Months]],Table1[[#This Row],[Amount_Disbursed]]) -> 13410.21 | AC76: 45985 | AD76: =EDATE(Table1[[#This Row],[Disbursement_Date]],Table1[[#This Row],[Tenure_Months]]) -> 47446 | AE76: NACH
A77: CUST0084 | B77: Amit Shukla | C77: 36963 | D77: =DATEDIF(Table1[[#This Row],[Date_of_Birth]],TODAY(),"Y") -> 25 | E77: Male | F77: 9544055921 | G77: 9126749178 | H77: 605, Indira Nagar, Rewa | I77: Rewa | J77: 682 | K77: 486004 | L77: XXXX-XXXX-5649 | M77: IQSET2494D | N77: Pending | O77: Business | P77: 40000 | Q77: Maruti | R77: Dzire | S77: Sedan | T77: RJ75CG7235 | U77: 718657 | V77: BR005 | W77: Rewa | X77: Manoj Joshi | Y77: 534231 | Z77: 60 | AA77: 13.35 | AB77: =-PMT((Table1[[#This Row],[Interest_Rate_%]]/100)/12,Table1[[#This Row],[Tenure_Months]],Table1[[#This Row],[Amount_Disbursed]]) -> 12251.329 | AC77: 45766 | AD77: =EDATE(Table1[[#This Row],[Disbursement_Date]],Table1[[#This Row],[Tenure_Months]]) -> 47592 | AE77: ECS
A78: CUST0086 | B78: Rajesh Patel | C78: 25071 | D78: =DATEDIF(Table1[[#This Row],[Date_of_Birth]],TODAY(),"Y") -> 57 | E78: Male | F78: 9955485064 | H78: 424, Napier Town, Jabalpur | I78: Jabalpur | J78: 627 | K78: 482003 | L78: XXXX-XXXX-8820 | M78: UFQRG2111J | N78: Complete | O78: Business | P78: 75000 | Q78: Tata | R78: Nexon | S78: SUV | T78: MP97FF7488 | U78: 950803 | V78: BR003 | W78: Jabalpur | X78: Vikas Singh | Y78: 775360 | Z78: 24 | AA78: 15.3 | AB78: =-PMT((Table1[[#This Row],[Interest_Rate_%]]/100)/12,Table1[[#This Row],[Tenure_Months]],Table1[[#This Row],[Amount_Disbursed]]) -> 37705.217 | AC78: 45651 | AD78: =EDATE(Table1[[#This Row],[Disbursement_Date]],Table1[[#This Row],[Tenure_Months]]) -> 46381 | AE78: NACH
A79: CUST0087 | B79: Renu Yadav | C79: 37907 | D79: =DATEDIF(Table1[[#This Row],[Date_of_Birth]],TODAY(),"Y") -> 22 | E79: Female | F79: 9301196574 | G79: 9940035404 | H79: 727, Lashkar, Gwalior | I79: Gwalior | J79: 693 | K79: 474003 | L79: XXXX-XXXX-6781 | M79: MGLYF5953F | N79: Complete | O79: Self-Employed | P79: 15000 | Q79: Bajaj | R79: Pulsar | S79: Two-Wheeler | T79: MP66AH9192 | U79: 96489 | V79: BR004 | W79: Gwalior | X79: Neha Mishra | Y79: 67976 | Z79: 24 | AA79: 14.33 | AB79: =-PMT((Table1[[#This Row],[Interest_Rate_%]]/100)/12,Table1[[#This Row],[Tenure_Months]],Table1[[#This Row],[Amount_Disbursed]]) -> 3274.331 | AC79: 45356 | AD79: =EDATE(Table1[[#This Row],[Disbursement_Date]],Table1[[#This Row],[Tenure_Months]]) -> 46086 | AE79: ECS
A80: CUST0088 | B80: Deepak Patel | C80: 30747 | D80: =DATEDIF(Table1[[#This Row],[Date_of_Birth]],TODAY(),"Y") -> 42 | E80: Male | F80: 9393815375 | H80: 212, Station Road, Rewa | I80: Rewa | J80: 799 | K80: 486003 | L80: XXXX-XXXX-8516 | M80: HYUOE6101T | N80: Complete | O80: Business | P80: 60000 | Q80: Maruti | R80: Swift | S80: Hatchback | T80: MP70AB7284 | U80: 617049 | V80: BR005 | W80: Rewa | X80: Anita Dubey | Y80: 460527 | Z80: 18 | AA80: 11.36 | AB80: =-PMT((Table1[[#This Row],[Interest_Rate_%]]/100)/12,Table1[[#This Row],[Tenure_Months]],Table1[[#This Row],[Amount_Disbursed]]) -> 27947.159 | AC80: 45455 | AD80: =EDATE(Table1[[#This Row],[Disbursement_Date]],Table1[[#This Row],[Tenure_Months]]) -> 46003 | AE80: ECS
A81: CUST0089 | B81: Deepak Rajput | C81: 24884 | D81: =DATEDIF(Table1[[#This Row],[Date_of_Birth]],TODAY(),"Y") -> 58 | E81: Male | F81: 9221211559 | G81: 9595254481 | H81: 619, Wright Town, Jabalpur | I81: Jabalpur | J81: 657 | K81: 482002 | L81: XXXX-XXXX-6898 | M81: KSCOB5949R | N81: Pending | O81: Self-Employed | P81: 100000 | Q81: Tata | R81: Tiago | S81: Hatchback | T81: CG41CH7288 | U81: 581270 | V81: BR003 | W81: Jabalpur | X81: Kavita Yadav | Y81: 464352 | Z81: 60 | AA81: 10.87 | AB81: =-PMT((Table1[[#This Row],[Interest_Rate_%]]/100)/12,Table1[[#This Row],[Tenure_Months]],Table1[[#This Row],[Amount_Disbursed]]) -> 10066.059 | AC81: 45372 | AD81: =EDATE(Table1[[#This Row],[Disbursement_Date]],Table1[[#This Row],[Tenure_Months]]) -> 47198 | AE81: NACH
A82: CUST0090 | B82: Mohit Pandey | C82: 33530 | D82: =DATEDIF(Table1[[#This Row],[Date_of_Birth]],TODAY(),"Y") -> 34 | E82: Male | F82: 9580134151 | H82: 584, Kolar Road, Bhopal | I82: Bhopal | J82: 750 | K82: 462004 | L82: XXXX-XXXX-3581 | M82: ZPPNW5819B | N82: Complete | O82: Business | P82: 15000 | Q82: Maruti | R82: Swift | S82: Hatchback | T82: CG55BE1510 | U82: 692190 | V82: BR002 | W82: Bhopal | X82: Rohit Gupta | Y82: 503529 | Z82: 36 | AA82: 15.66 | AB82: =-PMT((Table1[[#This Row],[Interest_Rate_%]]/100)/12,Table1[[#This Row],[Tenure_Months]],Table1[[#This Row],[Amount_Disbursed]]) -> 17618.18 | AC82: 45798 | AD82: =EDATE(Table1[[#This Row],[Disbursement_Date]],Table1[[#This Row],[Tenure_Months]]) -> 46894 | AE82: PDC
A83: CUST0091 | B83: Pankaj Soni | C83: 29659 | D83: =DATEDIF(Table1[[#This Row],[Date_of_Birth]],TODAY(),"Y") -> 45 | E83: Male | F83: 9749155592 | H83: 730, Station Road, Rewa | I83: Rewa | J83: 693 | K83: 486003 | L83: XXXX-XXXX-8731 | M83: JZOSC8889W | N83: Complete | O83: Salaried | P83: 35000 | Q83: Honda | R83: City | S83: Sedan | T83: MP76BD8740 | U83: 1217757 | V83: BR005 | W83: Rewa | X83: Manoj Joshi | Y83: 1005696 | Z83: 48 | AA83: 11.51 | AB83: =-PMT((Table1[[#This Row],[Interest_Rate_%]]/100)/12,Table1[[#This Row],[Tenure_Months]],Table1[[#This Row],[Amount_Disbursed]]) -> 26242.523 | AC83: 45032 | AD83: =EDATE(Table1[[#This Row],[Disbursement_Date]],Table1[[#This Row],[Tenure_Months]]) -> 46493 | AE83: PDC
A84: CUST0092 | B84: Sumit Gupta | C84: 30807 | D84: =DATEDIF(Table1[[#This Row],[Date_of_Birth]],TODAY(),"Y") -> 42 | E84: Male | F84: 9761207811 | H84: 619, Vijay Nagar, Indore | I84: Indore | J84: 730 | K84: 452005 | L84: XXXX-XXXX-7355 | M84: RJEUG3962Z | N84: Expired | O84: Salaried | P84: 20000 | Q84: Maruti | R84: Brezza | S84: SUV | T84: UP73GG4898 | U84: 1128059 | V84: BR001 | W84: Indore | X84: Priya Verma | Y84: 1006626 | Z84: 60 | AA84: 16.24 | AB84: =-PMT((Table1[[#This Row],[Interest_Rate_%]]/100)/12,Table1[[#This Row],[Tenure_Months]],Table1[[#This Row],[Amount_Disbursed]]) -> 24607.738 | AC84: 45126 | AD84: =EDATE(Table1[[#This Row],[Disbursement_Date]],Table1[[#This Row],[Tenure_Months]]) -> 46953 | AE84: PDC
A85: CUST0093 | B85: Vijay Dubey | C85: 26805 | D85: =DATEDIF(Table1[[#This Row],[Date_of_Birth]],TODAY(),"Y") -> 53 | E85: Male | F85: 9727255103 | G85: 9930164576 | H85: 533, Adhartal, Jabalpur | I85: Jabalpur | J85: 635 | K85: 482006 | L85: XXXX-XXXX-9812 | M85: ORVAC2702V | N85: Pending | O85: Self-Employed | P85: 30000 | Q85: TVS | R85: Jupiter | S85: Two-Wheeler | T85: MH34AA2506 | U85: 77132 | V85: BR003 | W85: Jabalpur | X85: Kavita Yadav | Y85: 56490 | Z85: 12 | AA85: 12.16 | AB85: =-PMT((Table1[[#This Row],[Interest_Rate_%]]/100)/12,Table1[[#This Row],[Tenure_Months]],Table1[[#This Row],[Amount_Disbursed]]) -> 5023.2973 | AC85: 45054 | AD85: =EDATE(Table1[[#This Row],[Disbursement_Date]],Table1[[#This Row],[Tenure_Months]]) -> 45420 | AE85: ECS
A86: CUST0094 | B86: Deepak Gupta | C86: 35905 | D86: =DATEDIF(Table1[[#This Row],[Date_of_Birth]],TODAY(),"Y") -> 28 | E86: Male | F86: 9521588025 | H86: 224, Wright Town, Jabalpur | I86: Jabalpur | J86: 789 | K86: 482006 | L86: XXXX-XXXX-4153 | M86: GABSU1307P | N86: Complete | O86: Business | P86: Business | Q86: Maruti | R86: Swift | S86: Hatchback | T86: RJ44CF7411 | U86: 687111 | V86: BR003 | W86: Jabalpur | X86: Vikas Singh | Y86: 596574 | Z86: 24 | AA86: 14.39 | AB86: =-PMT((Table1[[#This Row],[Interest_Rate_%]]/100)/12,Table1[[#This Row],[Tenure_Months]],Table1[[#This Row],[Amount_Disbursed]]) -> 28753.274 | AC86: 45288 | AD86: =EDATE(Table1[[#This Row],[Disbursement_Date]],Table1[[#This Row],[Tenure_Months]]) -> 46019 | AE86: PDC
A87: CUST0095 | B87: Shanta Patel | C87: 32723 | D87: =DATEDIF(Table1[[#This Row],[Date_of_Birth]],TODAY(),"Y") -> 36 | E87: Female | F87: 9779454449 | G87: 9303435957 | H87: 198, Napier Town, Jabalpur | I87: Jabalpur | J87: 703 | K87: 482006 | L87: XXXX-XXXX-6488 | M87: GKUQM8361A | N87: Complete | O87: Self-Employed | P87: 15000 | Q87: Tata | R87: Nexon | S87: SUV | T87: MP61BD9570 | U87: 1044504 | V87: BR003 | W87: Jabalpur | X87: Vikas Singh | Y87: 835006 | Z87: 48 | AA87: 11.82 | AB87: =-PMT((Table1[[#This Row],[Interest_Rate_%]]/100)/12,Table1[[#This Row],[Tenure_Months]],Table1[[#This Row],[Amount_Disbursed]]) -> 21915.186 | AC87: 45342 | AD87: =EDATE(Table1[[#This Row],[Disbursement_Date]],Table1[[#This Row],[Tenure_Months]]) -> 46803 | AE87: ECS
A88: CUST0096 | B88: Geeta Joshi | C88: 29239 | D88: =DATEDIF(Table1[[#This Row],[Date_of_Birth]],TODAY(),"Y") -> 46 | E88: Female | F88: 9286237999 | G88: 9229649486 | H88: 173, Chorhata, Rewa | I88: Rewa | J88: 795 | K88: 486005 | L88: XXXX-XXXX-3065 | M88: GPDUQ7162Y | N88: Complete | O88: Salaried | P88: 20000 | Q88: Maruti | R88: Swift | S88: Hatchback | T88: UP21EG8798 | U88: 600946 | V88: BR005 | W88: Rewa | X88: Anita Dubey | Y88: 513247 | Z88: 60 | AA88: 11.75 | AB88: =-PMT((Table1[[#This Row],[Interest_Rate_%]]/100)/12,Table1[[#This Row],[Tenure_Months]],Table1[[#This Row],[Amount_Disbursed]]) -> 11352.162 | AC88: 45035 | AD88: =EDATE(Table1[[#This Row],[Disbursement_Date]],Table1[[#This Row],[Tenure_Months]]) -> 46862 | AE88: NACH
A89: CUST0097 | B89: Amit Verma | C89: 25884 | D89: =DATEDIF(Table1[[#This Row],[Date_of_Birth]],TODAY(),"Y") -> 55 | E89: Male | F89: 9406085699 | H89: 45, Lashkar, Gwalior | I89: Gwalior | J89: 767 | K89: 474006 | L89: XXXX-XXXX-4716 | M89: EANBG8287S | N89: Expired | O89: Self-Employed | P89: 50000 | Q89: Hyundai | R89: i20 | S89: Hatchback | T89: MH39BF4731 | U89: 797922 | V89: BR004 | W89: Gwalior | X89: Neha Mishra | Y89: 585866 | Z89: 24 | AA89: 11.82 | AB89: =-PMT((Table1[[#This Row],[Interest_Rate_%]]/100)/12,Table1[[#This Row],[Tenure_Months]],Table1[[#This Row],[Amount_Disbursed]]) -> 27529.525 | AC89: 45531 | AD89: =EDATE(Table1[[#This Row],[Disbursement_Date]],Table1[[#This Row],[Tenure_Months]]) -> 46261 | AE89: PDC
A90: CUST0098 | B90: Vikas Thakur | C90: 35904 | D90: =DATEDIF(Table1[[#This Row],[Date_of_Birth]],TODAY(),"Y") -> 28 | E90: Male | F90: 9608404935 | G90: 9399757448 | H90: 439, Arera Colony, Bhopal | I90: Bhopal | J90: 798 | K90: 462002 | L90: XXXX-XXXX-5243 | M90: PXPDO1083N | N90: Complete | O90: Salaried | P90: 75000 | Q90: Maruti | R90: Swift | S90: Hatchback | T90: CG60HB8412 | U90: 655797 | V90: BR002 | W90: Bhopal | X90: Rohit Gupta | Y90: 509538 | Z90: 60 | AA90: 12.5 | AB90: =-PMT((Table1[[#This Row],[Interest_Rate_%]]/100)/12,Table1[[#This Row],[Tenure_Months]],Table1[[#This Row],[Amount_Disbursed]]) -> 11463.554 | AC90: 44993 | AD90: =EDATE(Table1[[#This Row],[Disbursement_Date]],Table1[[#This Row],[Tenure_Months]]) -> 46820 | AE90: ECS
A91: CUST0099 | B91: Meena Gupta | C91: 32479 | D91: =DATEDIF(Table1[[#This Row],[Date_of_Birth]],TODAY(),"Y") -> 37 | E91: Female | F91: 9652694084 | G91: 9824403104 | H91: 393, Chorhata, Rewa | I91: Rewa | J91: 747 | K91: 486004 | L91: XXXX-XXXX-0887 | M91: JEOBS4354E | N91: Complete | O91: Salaried | P91: 20000 | Q91: Honda | R91: Activa | S91: Two-Wheeler | T91: CG99DD6250 | U91: 97717 | V91: BR005 | W91: Rewa | X91: Anita Dubey | Y91: 87129 | Z91: 12 | AA91: 11.16 | AB91: =-PMT((Table1[[#This Row],[Interest_Rate_%]]/100)/12,Table1[[#This Row],[Tenure_Months]],Table1[[#This Row],[Amount_Disbursed]]) -> 7707.1097 | AC91: 45492 | AD91: =EDATE(Table1[[#This Row],[Disbursement_Date]],Table1[[#This Row],[Tenure_Months]]) -> 45857 | AE91: NACH
A92: CUST0100 | B92: Priya Pandey | C92: 34291 | D92: =DATEDIF(Table1[[#This Row],[Date_of_Birth]],TODAY(),"Y") -> 32 | E92: Female | F92: 9241763305 | G92: 9551111120 | H92: 299, Arera Colony, Bhopal | I92: Bhopal | J92: 758 | K92: 462001 | L92: XXXX-XXXX-7445 | M92: VNIPR6346P | N92: Expired | O92: Business | P92: 75000 | Q92: Hero | R92: Splendor | S92: Two-Wheeler | T92: RJ68EC6021 | U92: 96888 | V92: BR002 | W92: Bhopal | X92: Rohit Gupta | Y92: 78721 | Z92: 12 | AA92: 14.49 | AB92: =-PMT((Table1[[#This Row],[Interest_Rate_%]]/100)/12,Table1[[#This Row],[Tenure_Months]],Table1[[#This Row],[Amount_Disbursed]]) -> 7086.2939 | AC92: 45631 | AD92: =EDATE(Table1[[#This Row],[Disbursement_Date]],Table1[[#This Row],[Tenure_Months]]) -> 45996 | AE92: NACH
A93: CUST0101 | B93: Mahesh Sharma | C93: 33841 | D93: =DATEDIF(Table1[[#This Row],[Date_of_Birth]],TODAY(),"Y") -> 33 | E93: Male | F93: 9256104757 | G93: 9443831389 | H93: 994, Station Road, Rewa | I93: Rewa | J93: 709 | K93: 486005 | L93: XXXX-XXXX-3367 | M93: SMHYZ3409Z | N93: Expired | O93: Business | P93: 60000 | Q93: Tata | R93: Nexon | S93: SUV | T93: MP71AC2914 | U93: 1040327 | V93: BR005 | W93: Rewa | X93: Anita Dubey | Y93: 759011 | Z93: 36 | AA93: 12.72 | AB93: =-PMT((Table1[[#This Row],[Interest_Rate_%]]/100)/12,Table1[[#This Row],[Tenure_Months]],Table1[[#This Row],[Amount_Disbursed]]) -> 25471.836 | AC93: 45690 | AD93: =EDATE(Table1[[#This Row],[Disbursement_Date]],Table1[[#This Row],[Tenure_Months]]) -> 46785 | AE93: NACH
A94: CUST0102 | B94: Kavita Tiwari | C94: 35047 | D94: =DATEDIF(Table1[[#This Row],[Date_of_Birth]],TODAY(),"Y") -> 30 | E94: Female | F94: 9962950738 | G94: 9275868541 | H94: 143, Maharajpura, Gwalior | I94: Gwalior | J94: 797 | K94: 474005 | L94: XXXX-XXXX-4753 | M94: FMWZB7156C | N94: Complete | O94: Self-Employed | P94: 35000 | Q94: Tata | R94: Tiago | S94: Hatchback | T94: CG69CD4047 | U94: 572923 | V94: BR004 | W94: Gwalior | X94: Sanjay Tiwari | Y94: 469669 | Z94: 24 | AA94: 13.99 | AB94: =-PMT((Table1[[#This Row],[Interest_Rate_%]]/100)/12,Table1[[#This Row],[Tenure_Months]],Table1[[#This Row],[Amount_Disbursed]]) -> 22547.944 | AC94: 45820 | AD94: =EDATE(Table1[[#This Row],[Disbursement_Date]],Table1[[#This Row],[Tenure_Months]]) -> 46550 | AE94: ECS
A95: CUST0103 | B95: Seema Sharma | C95: 30394 | D95: =DATEDIF(Table1[[#This Row],[Date_of_Birth]],TODAY(),"Y") -> 43 | E95: Female | F95: 9162825060 | H95: 366, Civil Lines, Jabalpur | I95: Jabalpur | J95: 699 | K95: 482001 | L95: XXXX-XXXX-1483 | M95: KXJHN2258Q | N95: Complete | O95: Business | P95: 25000 | Q95: Bajaj | R95: Pulsar | S95: Two-Wheeler | T95: CG31FF5932 | U95: 82387 | V95: BR003 | W95: Jabalpur | X95: Kavita Yadav | Y95: 65258 | Z95: 12 | AA95: 11.2 | AB95: =-PMT((Table1[[#This Row],[Interest_Rate_%]]/100)/12,Table1[[#This Row],[Tenure_Months]],Table1[[#This Row],[Amount_Disbursed]]) -> 5773.7 | AC95: 45195 | AD95: =EDATE(Table1[[#This Row],[Disbursement_Date]],Table1[[#This Row],[Tenure_Months]]) -> 45561 | AE95: NACH
A96: CUST0104 | B96: Deepak Dwivedi | C96: 36683 | D96: =DATEDIF(Table1[[#This Row],[Date_of_Birth]],TODAY(),"Y") -> 26 | E96: Male | F96: 9862243827 | G96: 9899358066 | H96: 878, Civil Lines, Jabalpur | I96: Jabalpur | J96: 749 | K96: 482006 | L96: XXXX-XXXX-8878 | M96: DDCRU2273A | N96: Pending | O96: Self-Employed | P96: 15000 | Q96: Hyundai | R96: i20 | S96: Hatchback | T96: MP94AH2948 | U96: 714131 | V96: BR003 | W96: Jabalpur | X96: Vikas Singh | Y96: 602128 | Z96: 24 | AA96: 11.53 | AB96: =-PMT((Table1[[#This Row],[Interest_Rate_%]]/100)/12,Table1[[#This Row],[Tenure_Months]],Table1[[#This Row],[Amount_Disbursed]]) -> 28212.277 | AC96: 44935 | AD96: =EDATE(Table1[[#This Row],[Disbursement_Date]],Table1[[#This Row],[Tenure_Months]]) -> 45666 | AE96: PDC
A97: CUST0105 | B97: Naresh Yadav | C97: 35007 | D97: =DATEDIF(Table1[[#This Row],[Date_of_Birth]],TODAY(),"Y") -> 30 | E97: Male | F97: 9294184632 | G97: 9507608561 | H97: 418, Lashkar, Gwalior | I97: Gwalior | J97: 768 | K97: 474003 | L97: XXXX-XXXX-2337 | M97: CDTSO1665C | N97: Complete | O97: Self-Employed | P97: 20000 | Q97: Tata | R97: Tiago | S97: Hatchback | T97: RJ86EH4700 | U97: 587173 | V97: BR004 | W97: Gwalior | X97: Neha Mishra | Y97: 434538 | Z97: 36 | AA97: 11.24 | AB97: =-PMT((Table1[[#This Row],[Interest_Rate_%]]/100)/12,Table1[[#This Row],[Tenure_Months]],Table1[[#This Row],[Amount_Disbursed]]) -> 14275.655 | AC97: 45796 | AD97: =EDATE(Table1[[#This Row],[Disbursement_Date]],Table1[[#This Row],[Tenure_Months]]) -> 46892 | AE97: PDC
A98: CUST0106 | B98: Shanta Soni | C98: 35754 | D98: =DATEDIF(Table1[[#This Row],[Date_of_Birth]],TODAY(),"Y") -> 28 | E98: Female | F98: 9534268004 | G98: 9649127152 | H98: 111, Napier Town, Jabalpur | I98: Jabalpur | J98: 788 | K98: 482003 | L98: XXXX-XXXX-1817 | M98: GYATV9161V | N98: Complete | O98: Salaried | P98: 100000 | Q98: Honda | R98: Activa | S98: Two-Wheeler | T98: UP48BB9518 | U98: 77854 | V98: BR003 | W98: Jabalpur | X98: Kavita Yadav | Y98: 56591 | Z98: 60 | AA98: 12.83 | AB98: =-PMT((Table1[[#This Row],[Interest_Rate_%]]/100)/12,Table1[[#This Row],[Tenure_Months]],Table1[[#This Row],[Amount_Disbursed]]) -> 1282.6997 | AC98: 45151 | AD98: =EDATE(Table1[[#This Row],[Disbursement_Date]],Table1[[#This Row],[Tenure_Months]]) -> 46978 | AE98: PDC
A99: CUST0107 | B99: Savita Rajput | C99: 37332 | D99: =DATEDIF(Table1[[#This Row],[Date_of_Birth]],TODAY(),"Y") -> 24 | E99: Female | F99: 9159847287 | G99: 9631170553 | H99: 785, Chorhata, Rewa | I99: Rewa | J99: 747 | K99: 486003 | L99: XXXX-XXXX-5053 | M99: PDJVP6591M | N99: Complete | O99: Self-Employed | P99: 40000 | Q99: Tata | R99: Nexon | S99: SUV | T99: MH17DD4844 | U99: 1003992 | V99: BR005 | W99: Rewa | X99: Anita Dubey | Y99: 803749 | Z99: 60 | AA99: 12.54 | AB99: =-PMT((Table1[[#This Row],[Interest_Rate_%]]/100)/12,Table1[[#This Row],[Tenure_Months]],Table1[[#This Row],[Amount_Disbursed]]) -> 18099.052 | AC99: 45540 | AD99: =EDATE(Table1[[#This Row],[Disbursement_Date]],Table1[[#This Row],[Tenure_Months]]) -> 47366 | AE99: ECS
A100: CUST0109 | B100: Kiran Mishra | C100: 33698 | D100: =DATEDIF(Table1[[#This Row],[Date_of_Birth]],TODAY(),"Y") -> 34 | E100: Female | F100: 9261020740 | H100: 498, Wright Town, Jabalpur | I100: Jabalpur | J100: 724 | K100: 482004 | L100: XXXX-XXXX-2180 | M100: XFHAU5551V | N100: Expired | O100: Salaried | P100: 60000 | Q100: Bajaj | R100: Pulsar | S100: Two-Wheeler | T100: MP20FE2041 | U100: 72609 | V100: BR003 | W100: Jabalpur | X100: Vikas Singh | Y100: 64411 | Z100: 18 | AA100: 11.37 | AB100: =-PMT((Table1[[#This Row],[Interest_Rate_%]]/100)/12,Table1[[#This Row],[Tenure_Months]],Table1[[#This Row],[Amount_Disbursed]]) -> 3909.0908 | AC100: 45285 | AD100: =EDATE(Table1[[#This Row],[Disbursement_Date]],Table1[[#This Row],[Tenure_Months]]) -> 45833 | AE100: NACH
...

Sheet agent_master
A1: ABC Finance | Agent Master | May 2026
A2: Agent_Code | B2: Agent_Name | C2: Channel | D2: Branch_Code | E2: Branch_Name | F2: Team_Leader | G2: Joining_Date | H2: Status
A3: AG001 | B3: Mohit Mishra | C3: Field | D3: BR001 | E3: =_xlfn.XLOOKUP(Table4[[#This Row],[Branch_Code]],Table1[Branch_Code],Table1[Branch_Name],,0) -> Indore | F3: Rahul Sharma | G3: 45659 | H3: Active
A4: AG002 | B4: Sunita Patel | C4: Tele-Calling | D4: BR002 | E4: =_xlfn.XLOOKUP(Table4[[#This Row],[Branch_Code]],Table1[Branch_Code],Table1[Branch_Name],,0) -> Bhopal | F4: Priya Verma | G4: 45660 | H4: Active
A5: AG003 | B5: Pushpa Gupta | C5: Field | D5: BR003 | E5: =_xlfn.XLOOKUP(Table4[[#This Row],[Branch_Code]],Table1[Branch_Code],Table1[Branch_Name],,0) -> Jabalpur | F5: Sanjay Patel | G5: 45661 | H5: On Leave
A6: AG004 | B6: Pankaj Verma | C6: Tele-Calling | D6: BR004 | E6: =_xlfn.XLOOKUP(Table4[[#This Row],[Branch_Code]],Table1[Branch_Code],Table1[Branch_Name],,0) -> Gwalior | F6: Ankit Jain | G6: 45662 | H6: Active
A7: AG005 | B7: Amit Thakur | C7: Field | D7: BR005 | E7: =_xlfn.XLOOKUP(Table4[[#This Row],[Branch_Code]],Table1[Branch_Code],Table1[Branch_Name],,0) -> Rewa | F7: Rohit Gupta | G7: 45663 | H7: Active
A8: AG006 | B8: Suresh Malviya | C8: Field | D8: BR001 | E8: =_xlfn.XLOOKUP(Table4[[#This Row],[Branch_Code]],Table1[Branch_Code],Table1[Branch_Name],,0) -> Indore | F8: Rahul Sharma | G8: 45664 | H8: Active
A9: AG007 | B9: Pushpa Jain | C9: Tele-Calling | D9: BR002 | E9: =_xlfn.XLOOKUP(Table4[[#This Row],[Branch_Code]],Table1[Branch_Code],Table1[Branch_Name],,0) -> Bhopal | F9: Priya Verma | G9: 45665 | H9: Active
A10: AG008 | B10: Pooja Shukla | C10: Field | D10: BR003 | E10: =_xlfn.XLOOKUP(Table4[[#This Row],[Branch_Code]],Table1[Branch_Code],Table1[Branch_Name],,0) -> Jabalpur | F10: Sanjay Patel | G10: 45666 | H10: Active
A11: AG009 | B11: Pankaj Joshi | C11: Field | D11: BR004 | E11: =_xlfn.XLOOKUP(Table4[[#This Row],[Branch_Code]],Table1[Branch_Code],Table1[Branch_Name],,0) -> Gwalior | F11: Ankit Jain | G11: 45667 | H11: Active
A12: AG010 | B12: Kavita Tiwari | C12: Tele-Calling | D12: BR005 | E12: =_xlfn.XLOOKUP(Table4[[#This Row],[Branch_Code]],Table1[Branch_Code],Table1[Branch_Name],,0) -> Rewa | F12: Rohit Gupta | G12: 45668 | H12: Active
A13: AG011 | B13: Umesh Gupta | C13: Field | D13: BR001 | E13: =_xlfn.XLOOKUP(Table4[[#This Row],[Branch_Code]],Table1[Branch_Code],Table1[Branch_Name],,0) -> Indore | F13: Rahul Sharma | G13: 45669 | H13: Inactive
A14: AG012 | B14: Umesh Soni | C14: Tele-Calling | D14: BR002 | E14: =_xlfn.XLOOKUP(Table4[[#This Row],[Branch_Code]],Table1[Branch_Code],Table1[Branch_Name],,0) -> Bhopal | F14: Priya Verma | G14: 45670 | H14: Active
... A22: AG020 | B22: Vijay Tiwari | C22: Field | D22: BR005 | E22: =_xlfn.XLOOKUP(Table4[[#This Row],[Branch_Code]],Table1[Branch_Code],Table1[Branch_Name],,0) -> Rewa | F22: Rohit Gupta | G22: 45678 | H22: Active

Sheet loan_status_tracker
A1: ABC Finance | Loan Status Tracker | May 2026
A2: Customer_ID | B2: Customer_Name | C2: Branch_Name | D2: Vehicle_Make | E2: Vehicle_Model | F2: Loan_Amount | G2: EMI_Amount | H2: EMI_Due_May26 | I2: Amount_Received_May26 | J2: Overdue_Amount | K2: EMI_Due_Date | L2: Days_Past_Due | M2: DPD_Bucket | N2: Loan_Status
A3: CUST0001 | B3: =_xlfn.XLOOKUP(Table2[[#This Row],[Customer_ID]],Table1[Customer_ID],Table1[Customer_Name],,0,) -> Vijay Mishra | C3: =_xlfn.XLOOKUP(Table2[[#This Row],[Customer_ID]],Table1[Customer_ID],Table1[Branch_Name],,) -> Indore | D3: =_xlfn.XLOOKUP(Table2[[#This Row],[Customer_ID]],Table1[Customer_ID],Table1[Vehicle_Make],,0) -> Bajaj | E3: =_xlfn.XLOOKUP(Table2[[#This Row],[Customer_ID]],Table1[Customer_ID],Table1[Vehicle_Model],,) -> Pulsar | F3: =_xlfn.XLOOKUP(Table2[[#This Row],[Customer_ID]],Table1[Customer_ID],Table1[Amount_Disbursed],,) -> 54982 | G3: =_xlfn.XLOOKUP(Table2[[#This Row],[Customer_ID]],Table1[Customer_ID],Table1[EMI_Amount],,0) -> 1887.4434 | H3: =Table2[[#This Row],[EMI_Amount]] -> 1887.4434 | I3: 167 | J3: =Table2[[#This Row],[EMI_Due_May26]]-Table2[[#This Row],[Amount_Received_May26]] -> 1720.4434 | K3: =DATE(2026,5,DAY(Table1[[#This Row],[Maturity_Date]])) -> 46159 | L3: =IF(Table2[[#This Row],[Overdue_Amount]]<1,"",MAX(0,TODAY()-Table2[[#This Row],[EMI_Due_Date]])) -> 21 | M3: =IF(LEN(Table2[[#This Row],[Days_Past_Due]])=0,"Current", IF(Table2[[#This Row],[Days_Past_Due]]<=30,"1-30", IF(Table2[[#This Row],[Days_Past_Due]]<=60,"31-60", IF(Table2[[#This Row],[Days_Past_Due]]<=90,"61-90","90+")))) -> 1-30 | N3: {=_xlfn.IFS(Table2[[#This Row],[DPD_Bucket]]="1-30","Overdue",Table2[[#This Row],[DPD_Bucket]]="90+","NPA",Table2[[#This Row],[DPD_Bucket]]="Current","Active",Table2[[#This Row],[DPD_Bucket]]="31-60","Overdue")} -> Overdue
A4: CUST0003 | B4: =_xlfn.XLOOKUP(Table2[[#This Row],[Customer_ID]],Table1[Customer_ID],Table1[Customer_Name],,0,) -> Mamta Dwivedi | C4: =_xlfn.XLOOKUP(Table2[[#This Row],[Customer_ID]],Table1[Customer_ID],Table1[Branch_Name],,) -> Jabalpur | D4: =_xlfn.XLOOKUP(Table2[[#This Row],[Customer_ID]],Table1[Customer_ID],Table1[Vehicle_Make],,0) -> Maruti | E4: =_xlfn.XLOOKUP(Table2[[#This Row],[Customer_ID]],Table1[Customer_ID],Table1[Vehicle_Model],,) -> Brezza | F4: =_xlfn.XLOOKUP(Table2[[#This Row],[Customer_ID]],Table1[Customer_ID],Table1[Amount_Disbursed],,) -> 858828 | G4: =_xlfn.XLOOKUP(Table2[[#This Row],[Customer_ID]],Table1[Customer_ID],Table1[EMI_Amount],,0) -> 28439.315 | H4: =Table2[[#This Row],[EMI_Amount]] -> 28439.315 | I4: 28439 | J4: =Table2[[#This Row],[EMI_Due_May26]]-Table2[[#This Row],[Amount_Received_May26]] -> 0.31540488 | K4: =DATE(2026,5,DAY(Table1[[#This Row],[Maturity_Date]])) -> 46170 | L4: =IF(Table2[[#This Row],[Overdue_Amount]]<1,"",MAX(0,TODAY()-Table2[[#This Row],[EMI_Due_Date]])) | M4: =IF(LEN(Table2[[#This Row],[Days_Past_Due]])=0,"Current", IF(Table2[[#This Row],[Days_Past_Due]]<=30,"1-30", IF(Table2[[#This Row],[Days_Past_Due]]<=60,"31-60", IF(Table2[[#This Row],[Days_Past_Due]]<=90,"61-90","90+")))) -> Current | N4: {=_xlfn.IFS(Table2[[#This Row],[DPD_Bucket]]="1-30","Overdue",Table2[[#This Row],[DPD_Bucket]]="90+","NPA",Table2[[#This Row],[DPD_Bucket]]="Current","Active",Table2[[#This Row],[DPD_Bucket]]="31-60","Overdue")} -> Active
A5: CUST0004 | B5: =_xlfn.XLOOKUP(Table2[[#This Row],[Customer_ID]],Table1[Customer_ID],Table1[Customer_Name],,0,) -> Mahesh Patel | C5: =_xlfn.XLOOKUP(Table2[[#This Row],[Customer_ID]],Table1[Customer_ID],Table1[Branch_Name],,) -> Gwalior | D5: =_xlfn.XLOOKUP(Table2[[#This Row],[Customer_ID]],Table1[Customer_ID],Table1[Vehicle_Make],,0) -> Hero | E5: =_xlfn.XLOOKUP(Table2[[#This Row],[Customer_ID]],Table1[Customer_ID],Table1[Vehicle_Model],,) -> Splendor | F5: =_xlfn.XLOOKUP(Table2[[#This Row],[Customer_ID]],Table1[Customer_ID],Table1[Amount_Disbursed],,) -> 35571 | G5: =_xlfn.XLOOKUP(Table2[[#This Row],[Customer_ID]],Table1[Customer_ID],Table1[EMI_Amount],,0) -> 960.64883 | H5: =Table2[[#This Row],[EMI_Amount]] -> 960.64883 | I5: 194 | J5: =Table2[[#This Row],[EMI_Due_May26]]-Table2[[#This Row],[Amount_Received_May26]] -> 766.64883 | K5: =DATE(2026,5,DAY(Table1[[#This Row],[Maturity_Date]])) -> 46165 | L5: =IF(Table2[[#This Row],[Overdue_Amount]]<1,"",MAX(0,TODAY()-Table2[[#This Row],[EMI_Due_Date]])) -> 15 | M5: =IF(LEN(Table2[[#This Row],[Days_Past_Due]])=0,"Current", IF(Table2[[#This Row],[Days_Past_Due]]<=30,"1-30", IF(Table2[[#This Row],[Days_Past_Due]]<=60,"31-60", IF(Table2[[#This Row],[Days_Past_Due]]<=90,"61-90","90+")))) -> 1-30 | N5: {=_xlfn.IFS(Table2[[#This Row],[DPD_Bucket]]="1-30","Overdue",Table2[[#This Row],[DPD_Bucket]]="90+","NPA",Table2[[#This Row],[DPD_Bucket]]="Current","Active",Table2[[#This Row],[DPD_Bucket]]="31-60","Overdue")} -> Overdue
A6: CUST0005 | B6: =_xlfn.XLOOKUP(Table2[[#This Row],[Customer_ID]],Table1[Customer_ID],Table1[Customer_Name],,0,) -> Santosh Mishra | C6: =_xlfn.XLOOKUP(Table2[[#This Row],[Customer_ID]],Table1[Customer_ID],Table1[Branch_Name],,) -> Rewa | D6: =_xlfn.XLOOKUP(Table2[[#This Row],[Customer_ID]],Table1[Customer_ID],Table1[Vehicle_Make],,0) -> Maruti | E6: =_xlfn.XLOOKUP(Table2[[#This Row],[Customer_ID]],Table1[Customer_ID],Table1[Vehicle_Model],,) -> Dzire | F6: =_xlfn.XLOOKUP(Table2[[#This Row],[Customer_ID]],Table1[Customer_ID],Table1[Amount_Disbursed],,) -> 494849 | G6: =_xlfn.XLOOKUP(Table2[[#This Row],[Customer_ID]],Table1[Customer_ID],Table1[EMI_Amount],,0) -> 43747.117 | H6: =Table2[[#This Row],[EMI_Amount]] -> 43747.117 | I6: 43747 | J6: =Table2[[#This Row],[EMI_Due_May26]]-Table2[[#This Row],[Amount_Received_May26]] -> 0.11732015 | K6: =DATE(2026,5,DAY(Table1[[#This Row],[Maturity_Date]])) -> 46159 | L6: =IF(Table2[[#This Row],[Overdue_Amount]]<1,"",MAX(0,TODAY()-Table2[[#This Row],[EMI_Due_Date]])) | M6: =IF(LEN(Table2[[#This Row],[Days_Past_Due]])=0,"Current", IF(Table2[[#This Row],[Days_Past_Due]]<=30,"1-30", IF(Table2[[#This Row],[Days_Past_Due]]<=60,"31-60", IF(Table2[[#This Row],[Days_Past_Due]]<=90,"61-90","90+")))) -> Current | N6: {=_xlfn.IFS(Table2[[#This Row],[DPD_Bucket]]="1-30","Overdue",Table2[[#This Row],[DPD_Bucket]]="90+","NPA",Table2[[#This Row],[DPD_Bucket]]="Current","Active",Table2[[#This Row],[DPD_Bucket]]="31-60","Overdue")} -> Active
A7: CUST0006 | B7: =_xlfn.XLOOKUP(Table2[[#This Row],[Customer_ID]],Table1[Customer_ID],Table1[Customer_Name],,0,) -> Deepak Malviya | C7: =_xlfn.XLOOKUP(Table2[[#This Row],[Customer_ID]],Table1[Customer_ID],Table1[Branch_Name],,) -> Jabalpur | D7: =_xlfn.XLOOKUP(Table2[[#This Row],[Customer_ID]],Table1[Customer_ID],Table1[Vehicle_Make],,0) -> Honda | E7: =_xlfn.XLOOKUP(Table2[[#This Row],[Customer_ID]],Table1[Customer_ID],Table1[Vehicle_Model],,) -> Activa | F7: =_xlfn.XLOOKUP(Table2[[#This Row],[Customer_ID]],Table1[Customer_ID],Table1[Amount_Disbursed],,) -> 38984 | G7: =_xlfn.XLOOKUP(Table2[[#This Row],[Customer_ID]],Table1[Customer_ID],Table1[EMI_Amount],,0) -> 1903.0086 | H7: =Table2[[#This Row],[EMI_Amount]] -> 1903.0086 | I7: 1903 | J7: =Table2[[#This Row],[EMI_Due_May26]]-Table2[[#This Row],[Amount_Received_May26]] -> 0.0086001553 | K7: =DATE(2026,5,DAY(Table1[[#This Row],[Maturity_Date]])) -> 46167 | L7: =IF(Table2[[#This Row],[Overdue_Amount]]<1,"",MAX(0,TODAY()-Table2[[#This Row],[EMI_Due_Date]])) | M7: =IF(LEN(Table2[[#This Row],[Days_Past_Due]])=0,"Current", IF(Table2[[#This Row],[Days_Past_Due]]<=30,"1-30", IF(Table2[[#This Row],[Days_Past_Due]]<=60,"31-60", IF(Table2[[#This Row],[Days_Past_Due]]<=90,"61-90","90+")))) -> Current | N7: {=_xlfn.IFS(Table2[[#This Row],[DPD_Bucket]]="1-30","Overdue",Table2[[#This Row],[DPD_Bucket]]="90+","NPA",Table2[[#This Row],[DPD_Bucket]]="Current","Active",Table2[[#This Row],[DPD_Bucket]]="31-60","Overdue")} -> Active
A8: CUST0008 | B8: =_xlfn.XLOOKUP(Table2[[#This Row],[Customer_ID]],Table1[Customer_ID],Table1[Customer_Name],,0,) -> Dinesh Sharma | C8: =_xlfn.XLOOKUP(Table2[[#This Row],[Customer_ID]],Table1[Customer_ID],Table1[Branch_Name],,) -> Bhopal | D8: =_xlfn.XLOOKUP(Table2[[#This Row],[Customer_ID]],Table1[Customer_ID],Table1[Vehicle_Make],,0) -> Honda | E8: =_xlfn.XLOOKUP(Table2[[#This Row],[Customer_ID]],Table1[Customer_ID],Table1[Vehicle_Model],,) -> City | F8: =_xlfn.XLOOKUP(Table2[[#This Row],[Customer_ID]],Table1[Customer_ID],Table1[Amount_Disbursed],,) -> 872459 | G8: =_xlfn.XLOOKUP(Table2[[#This Row],[Customer_ID]],Table1[Customer_ID],Table1[EMI_Amount],,0) -> 42659.968 | H8: =Table2[[#This Row],[EMI_Amount]] -> 42659.968 | I8: 0 | J8: =Table2[[#This Row],[EMI_Due_May26]]-Table2[[#This Row],[Amount_Received_May26]] -> 42659.968 | K8: =DATE(2026,5,DAY(Table1[[#This Row],[Maturity_Date]])) -> 46157 | L8: =IF(Table2[[#This Row],[Overdue_Amount]]<1,"",MAX(0,TODAY()-Table2[[#This Row],[EMI_Due_Date]])) -> 23 | M8: =IF(LEN(Table2[[#This Row],[Days_Past_Due]])=0,"Current", IF(Table2[[#This Row],[Days_Past_Due]]<=30,"1-30", IF(Table2[[#This Row],[Days_Past_Due]]<=60,"31-60", IF(Table2[[#This Row],[Days_Past_Due]]<=90,"61-90","90+")))) -> 1-30 | N8: {=_xlfn.IFS(Table2[[#This Row],[DPD_Bucket]]="1-30","Overdue",Table2[[#This Row],[DPD_Bucket]]="90+","NPA",Table2[[#This Row],[DPD_Bucket]]="Current","Active",Table2[[#This Row],[DPD_Bucket]]="31-60","Overdue")} -> Overdue
A9: CUST0009 | B9: =_xlfn.XLOOKUP(Table2[[#This Row],[Customer_ID]],Table1[Customer_ID],Table1[Customer_Name],,0,) -> Meena Gupta | C9: =_xlfn.XLOOKUP(Table2[[#This Row],[Customer_ID]],Table1[Customer_ID],Table1[Branch_Name],,) -> Bhopal | D9: =_xlfn.XLOOKUP(Table2[[#This Row],[Customer_ID]],Table1[Customer_ID],Table1[Vehicle_Make],,0) -> Honda | E9: =_xlfn.XLOOKUP(Table2[[#This Row],[Customer_ID]],Table1[Customer_ID],Table1[Vehicle_Model],,) -> City | F9: =_xlfn.XLOOKUP(Table2[[#This Row],[Customer_ID]],Table1[Customer_ID],Table1[Amount_Disbursed],,) -> 936007 | G9: =_xlfn.XLOOKUP(Table2[[#This Row],[Customer_ID]],Table1[Customer_ID],Table1[EMI_Amount],,0) -> 21653.284 | H9: =Table2[[#This Row],[EMI_Amount]] -> 21653.284 | I9: 5106 | J9: =Table2[[#This Row],[EMI_Due_May26]]-Table2[[#This Row],[Amount_Received_May26]] -> 16547.284 | K9: =DATE(2026,5,DAY(Table1[[#This Row],[Maturity_Date]])) -> 46159 | L9: =IF(Table2[[#This Row],[Overdue_Amount]]<1,"",MAX(0,TODAY()-Table2[[#This Row],[EMI_Due_Date]])) -> 21 | M9: =IF(LEN(Table2[[#This Row],[Days_Past_Due]])=0,"Current", IF(Table2[[#This Row],[Days_Past_Due]]<=30,"1-30", IF(Table2[[#This Row],[Days_Past_Due]]<=60,"31-60", IF(Table2[[#This Row],[Days_Past_Due]]<=90,"61-90","90+")))) -> 1-30 | N9: {=_xlfn.IFS(Table2[[#This Row],[DPD_Bucket]]="1-30","Overdue",Table2[[#This Row],[DPD_Bucket]]="90+","NPA",Table2[[#This Row],[DPD_Bucket]]="Current","Active",Table2[[#This Row],[DPD_Bucket]]="31-60","Overdue")} -> Overdue
A10: CUST0011 | B10: =_xlfn.XLOOKUP(Table2[[#This Row],[Customer_ID]],Table1[Customer_ID],Table1[Customer_Name],,0,) -> Naresh Dwivedi | C10: =_xlfn.XLOOKUP(Table2[[#This Row],[Customer_ID]],Table1[Customer_ID],Table1[Branch_Name],,) -> Bhopal | D10: =_xlfn.XLOOKUP(Table2[[#This Row],[Customer_ID]],Table1[Customer_ID],Table1[Vehicle_Make],,0) -> Honda | E10: =_xlfn.XLOOKUP(Table2[[#This Row],[Customer_ID]],Table1[Customer_ID],Table1[Vehicle_Model],,) -> City | F10: =_xlfn.XLOOKUP(Table2[[#This Row],[Customer_ID]],Table1[Customer_ID],Table1[Amount_Disbursed],,) -> 874852 | G10: =_xlfn.XLOOKUP(Table2[[#This Row],[Customer_ID]],Table1[Customer_ID],Table1[EMI_Amount],,0) -> 41010.94 | H10: =Table2[[#This Row],[EMI_Amount]] -> 41010.94 | I10: 25092 | J10: =Table2[[#This Row],[EMI_Due_May26]]-Table2[[#This Row],[Amount_Received_May26]] -> 15918.94 | K10: =DATE(2026,5,DAY(Table1[[#This Row],[Maturity_Date]])) -> 46171 | L10: =IF(Table2[[#This Row],[Overdue_Amount]]<1,"",MAX(0,TODAY()-Table2[[#This Row],[EMI_Due_Date]])) -> 9 | M10: =IF(LEN(Table2[[#This Row],[Days_Past_Due]])=0,"Current", IF(Table2[[#This Row],[Days_Past_Due]]<=30,"1-30", IF(Table2[[#This Row],[Days_Past_Due]]<=60,"31-60", IF(Table2[[#This Row],[Days_Past_Due]]<=90,"61-90","90+")))) -> 1-30 | N10: {=_xlfn.IFS(Table2[[#This Row],[DPD_Bucket]]="1-30","Overdue",Table2[[#This Row],[DPD_Bucket]]="90+","NPA",Table2[[#This Row],[DPD_Bucket]]="Current","Active",Table2[[#This Row],[DPD_Bucket]]="31-60","Overdue")} -> Overdue | LW10: 90+
A11: CUST0012 | B11: =_xlfn.XLOOKUP(Table2[[#This Row],[Customer_ID]],Table1[Customer_ID],Table1[Customer_Name],,0,) -> Asha Singh | C11: =_xlfn.XLOOKUP(Table2[[#This Row],[Customer_ID]],Table1[Customer_ID],Table1[Branch_Name],,) -> Indore | D11: =_xlfn.XLOOKUP(Table2[[#This Row],[Customer_ID]],Table1[Customer_ID],Table1[Vehicle_Make],,0) -> Hyundai | E11: =_xlfn.XLOOKUP(Table2[[#This Row],[Customer_ID]],Table1[Customer_ID],Table1[Vehicle_Model],,) -> i20 | F11: =_xlfn.XLOOKUP(Table2[[#This Row],[Customer_ID]],Table1[Customer_ID],Table1[Amount_Disbursed],,) -> 599235 | G11: =_xlfn.XLOOKUP(Table2[[#This Row],[Customer_ID]],Table1[Customer_ID],Table1[EMI_Amount],,0) -> 29120.422 | H11: =Table2[[#This Row],[EMI_Amount]] -> 29120.422 | I11: 29120 | J11: =Table2[[#This Row],[EMI_Due_May26]]-Table2[[#This Row],[Amount_Received_May26]] -> 0.42152583 | K11: =DATE(2026,5,DAY(Table1[[#This Row],[Maturity_Date]])) -> 46152 | L11: =IF(Table2[[#This Row],[Overdue_Amount]]<1,"",MAX(0,TODAY()-Table2[[#This Row],[EMI_Due_Date]])) | M11: =IF(LEN(Table2[[#This Row],[Days_Past_Due]])=0,"Current", IF(Table2[[#This Row],[Days_Past_Due]]<=30,"1-30", IF(Table2[[#This Row],[Days_Past_Due]]<=60,"31-60", IF(Table2[[#This Row],[Days_Past_Due]]<=90,"61-90","90+")))) -> Current | N11: {=_xlfn.IFS(Table2[[#This Row],[DPD_Bucket]]="1-30","Overdue",Table2[[#This Row],[DPD_Bucket]]="90+","NPA",Table2[[#This Row],[DPD_Bucket]]="Current","Active",Table2[[#This Row],[DPD_Bucket]]="31-60","Overdue")} -> Active
A12: CUST0013 | B12: =_xlfn.XLOOKUP(Table2[[#This Row],[Customer_ID]],Table1[Customer_ID],Table1[Customer_Name],,0,) -> Ramesh Verma | C12: =_xlfn.XLOOKUP(Table2[[#This Row],[Customer_ID]],Table1[Customer_ID],Table1[Branch_Name],,) -> Jabalpur | D12: =_xlfn.XLOOKUP(Table2[[#This Row],[Customer_ID]],Table1[Customer_ID],Table1[Vehicle_Make],,0) -> Maruti | E12: =_xlfn.XLOOKUP(Table2[[#This Row],[Customer_ID]],Table1[Customer_ID],Table1[Vehicle_Model],,) -> Swift | F12: =_xlfn.XLOOKUP(Table2[[#This Row],[Customer_ID]],Table1[Customer_ID],Table1[Amount_Disbursed],,) -> 538554 | G12: =_xlfn.XLOOKUP(Table2[[#This Row],[Customer_ID]],Table1[Customer_ID],Table1[EMI_Amount],,0) -> 33246.325 | H12: =Table2[[#This Row],[EMI_Amount]] -> 33246.325 | I12: 33246 | J12: =Table2[[#This Row],[EMI_Due_May26]]-Table2[[#This Row],[Amount_Received_May26]] -> 0.325458 | K12: =DATE(2026,5,DAY(Table1[[#This Row],[Maturity_Date]])) -> 46159 | L12: =IF(Table2[[#This Row],[Overdue_Amount]]<1,"",MAX(0,TODAY()-Table2[[#This Row],[EMI_Due_Date]])) | M12: =IF(LEN(Table2[[#This Row],[Days_Past_Due]])=0,"Current", IF(Table2[[#This Row],[Days_Past_Due]]<=30,"1-30", IF(Table2[[#This Row],[Days_Past_Due]]<=60,"31-60", IF(Table2[[#This Row],[Days_Past_Due]]<=90,"61-90","90+")))) -> Current | N12: {=_xlfn.IFS(Table2[[#This Row],[DPD_Bucket]]="1-30","Overdue",Table2[[#This Row],[DPD_Bucket]]="90+","NPA",Table2[[#This Row],[DPD_Bucket]]="Current","Active",Table2[[#This Row],[DPD_Bucket]]="31-60","Overdue")} -> Active
A13: CUST0014 | B13: =_xlfn.XLOOKUP(Table2[[#This Row],[Customer_ID]],Table1[Customer_ID],Table1[Customer_Name],,0,) -> Ajay Chauhan | C13: =_xlfn.XLOOKUP(Table2[[#This Row],[Customer_ID]],Table1[Customer_ID],Table1[Branch_Name],,) -> Rewa | D13: =_xlfn.XLOOKUP(Table2[[#This Row],[Customer_ID]],Table1[Customer_ID],Table1[Vehicle_Make],,0) -> Honda | E13: =_xlfn.XLOOKUP(Table2[[#This Row],[Customer_ID]],Table1[Customer_ID],Table1[Vehicle_Model],,) -> City | F13: =_xlfn.XLOOKUP(Table2[[#This Row],[Customer_ID]],Table1[Customer_ID],Table1[Amount_Disbursed],,) -> 866248 | G13: =_xlfn.XLOOKUP(Table2[[#This Row],[Customer_ID]],Table1[Customer_ID],Table1[EMI_Amount],,0) -> 19860.902 | H13: =Table2[[#This Row],[EMI_Amount]] -> 19860.902 | I13: 19861 | J13: =Table2[[#This Row],[EMI_Due_May26]]-Table2[[#This Row],[Amount_Received_May26]] -> -0.098274357 | K13: =DATE(2026,5,DAY(Table1[[#This Row],[Maturity_Date]])) -> 46161 | L13: =IF(Table2[[#This Row],[Overdue_Amount]]<1,"",MAX(0,TODAY()-Table2[[#This Row],[EMI_Due_Date]])) | M13: =IF(LEN(Table2[[#This Row],[Days_Past_Due]])=0,"Current", IF(Table2[[#This Row],[Days_Past_Due]]<=30,"1-30", IF(Table2[[#This Row],[Days_Past_Due]]<=60,"31-60", IF(Table2[[#This Row],[Days_Past_Due]]<=90,"61-90","90+")))) -> Current | N13: {=_xlfn.IFS(Table2[[#This Row],[DPD_Bucket]]="1-30","Overdue",Table2[[#This Row],[DPD_Bucket]]="90+","NPA",Table2[[#This Row],[DPD_Bucket]]="Current","Active",Table2[[#This Row],[DPD_Bucket]]="31-60","Overdue")} -> Active
A14: CUST0015 | B14: =_xlfn.XLOOKUP(Table2[[#This Row],[Customer_ID]],Table1[Customer_ID],Table1[Customer_Name],,0,) -> Seema Joshi | C14: =_xlfn.XLOOKUP(Table2[[#This Row],[Customer_ID]],Table1[Customer_ID],Table1[Branch_Name],,) -> Bhopal | D14: =_xlfn.XLOOKUP(Table2[[#This Row],[Customer_ID]],Table1[Customer_ID],Table1[Vehicle_Make],,0) -> Renault | E14: =_xlfn.XLOOKUP(Table2[[#This Row],[Customer_ID]],Table1[Customer_ID],Table1[Vehicle_Model],,) -> Kwid | F14: =_xlfn.XLOOKUP(Table2[[#This Row],[Customer_ID]],Table1[Customer_ID],Table1[Amount_Disbursed],,) -> 363463 | G14: =_xlfn.XLOOKUP(Table2[[#This Row],[Customer_ID]],Table1[Customer_ID],Table1[EMI_Amount],,0) -> 7823.045 | H14: =Table2[[#This Row],[EMI_Amount]] -> 7823.045 | I14: 5486 | J14: =Table2[[#This Row],[EMI_Due_May26]]-Table2[[#This Row],[Amount_Received_May26]] -> 2337.045 | K14: =DATE(2026,5,DAY(Table1[[#This Row],[Maturity_Date]])) -> 46152 | L14: =IF(Table2[[#This Row],[Overdue_Amount]]<1,"",MAX(0,TODAY()-Table2[[#This Row],[EMI_Due_Date]])) -> 28 | M14: =IF(LEN(Table2[[#This Row],[Days_Past_Due]])=0,"Current", IF(Table2[[#This Row],[Days_Past_Due]]<=30,"1-30", IF(Table2[[#This Row],[Days_Past_Due]]<=60,"31-60", IF(Table2[[#This Row],[Days_Past_Due]]<=90,"61-90","90+")))) -> 1-30 | N14: {=_xlfn.IFS(Table2[[#This Row],[DPD_Bucket]]="1-30","Overdue",Table2[[#This Row],[DPD_Bucket]]="90+","NPA",Table2[[#This Row],[DPD_Bucket]]="Current","Active",Table2[[#This Row],[DPD_Bucket]]="31-60","Overdue")} -> Overdue
A15: CUST0016 | B15: =_xlfn.XLOOKUP(Table2[[#This Row],[Customer_ID]],Table1[Customer_ID],Table1[Customer_Name],,0,) -> Asha Jain | C15: =_xlfn.XLOOKUP(Table2[[#This Row],[Customer_ID]],Table1[Customer_ID],Table1[Branch_Name],,) -> Jabalpur | D15: =_xlfn.XLOOKUP(Table2[[#This Row],[Customer_ID]],Table1[Customer_ID],Table1[Vehicle_Make],,0) -> Hero | E15: =_xlfn.XLOOKUP(Table2[[#This Row],[Customer_ID]],Table1[Customer_ID],Table1[Vehicle_Model],,) -> Splendor | F15: =_xlfn.XLOOKUP(Table2[[#This Row],[Customer_ID]],Table1[Customer_ID],Table1[Amount_Disbursed],,) -> 55853 | G15: =_xlfn.XLOOKUP(Table2[[#This Row],[Customer_ID]],Table1[Customer_ID],Table1[EMI_Amount],,0) -> 2707.5941 | H15: =Table2[[#This Row],[EMI_Amount]] -> 2707.5941 | I15: 2708 | J15: =Table2[[#This Row],[EMI_Due_May26]]-Table2[[#This Row],[Amount_Received_May26]] -> -0.40594813 | K15: =DATE(2026,5,DAY(Table1[[#This Row],[Maturity_Date]])) -> 46166 | L15: =IF(Table2[[#This Row],[Overdue_Amount]]<1,"",MAX(0,TODAY()-Table2[[#This Row],[EMI_Due_Date]])) | M15: =IF(LEN(Table2[[#This Row],[Days_Past_Due]])=0,"Current", IF(Table2[[#This Row],[Days_Past_Due]]<=30,"1-30", IF(Table2[[#This Row],[Days_Past_Due]]<=60,"31-60", IF(Table2[[#This Row],[Days_Past_Due]]<=90,"61-90","90+")))) -> Current | N15: {=_xlfn.IFS(Table2[[#This Row],[DPD_Bucket]]="1-30","Overdue",Table2[[#This Row],[DPD_Bucket]]="90+","NPA",Table2[[#This Row],[DPD_Bucket]]="Current","Active",Table2[[#This Row],[DPD_Bucket]]="31-60","Overdue")} -> Active
A16: CUST0017 | B16: =_xlfn.XLOOKUP(Table2[[#This Row],[Customer_ID]],Table1[Customer_ID],Table1[Customer_Name],,0,) -> Lata Gupta | C16: =_xlfn.XLOOKUP(Table2[[#This Row],[Customer_ID]],Table1[Customer_ID],Table1[Branch_Name],,) -> Gwalior | D16: =_xlfn.XLOOKUP(Table2[[#This Row],[Customer_ID]],Table1[Customer_ID],Table1[Vehicle_Make],,0) -> TVS | E16: =_xlfn.XLOOKUP(Table2[[#This Row],[Customer_ID]],Table1[Customer_ID],Table1[Vehicle_Model],,) -> Jupiter | F16: =_xlfn.XLOOKUP(Table2[[#This Row],[Customer_ID]],Table1[Customer_ID],Table1[Amount_Disbursed],,) -> 64394 | G16: =_xlfn.XLOOKUP(Table2[[#This Row],[Customer_ID]],Table1[Customer_ID],Table1[EMI_Amount],,0) -> 1453.6499 | H16: =Table2[[#This Row],[EMI_Amount]] -> 1453.6499 | I16: 1048 | J16: =Table2[[#This Row],[EMI_Due_May26]]-Table2[[#This Row],[Amount_Received_May26]] -> 405.64988 | K16: =DATE(2026,5,DAY(Table1[[#This Row],[Maturity_Date]])) -> 46168 | L16: =IF(Table2[[#This Row],[Overdue_Amount]]<1,"",MAX(0,TODAY()-Table2[[#This Row],[EMI_Due_Date]])) -> 12 | M16: =IF(LEN(Table2[[#This Row],[Days_Past_Due]])=0,"Current", IF(Table2[[#This Row],[Days_Past_Due]]<=30,"1-30", IF(Table2[[#This Row],[Days_Past_Due]]<=60,"31-60", IF(Table2[[#This Row],[Days_Past_Due]]<=90,"61-90","90+")))) -> 1-30 | N16: {=_xlfn.IFS(Table2[[#This Row],[DPD_Bucket]]="1-30","Overdue",Table2[[#This Row],[DPD_Bucket]]="90+","NPA",Table2[[#This Row],[DPD_Bucket]]="Current","Active",Table2[[#This Row],[DPD_Bucket]]="31-60","Overdue")} -> Overdue
A17: CUST0018 | B17: =_xlfn.XLOOKUP(Table2[[#This Row],[Customer_ID]],Table1[Customer_ID],Table1[Customer_Name],,0,) -> Kiran Sharma | C17: =_xlfn.XLOOKUP(Table2[[#This Row],[Customer_ID]],Table1[Customer_ID],Table1[Branch_Name],,) -> Bhopal | D17: =_xlfn.XLOOKUP(Table2[[#This Row],[Customer_ID]],Table1[Customer_ID],Table1[Vehicle_Make],,0) -> Bajaj | E17: =_xlfn.XLOOKUP(Table2[[#This Row],[Customer_ID]],Table1[Customer_ID],Table1[Vehicle_Model],,) -> Pulsar | F17: =_xlfn.XLOOKUP(Table2[[#This Row],[Customer_ID]],Table1[Customer_ID],Table1[Amount_Disbursed],,) -> 77753 | G17: =_xlfn.XLOOKUP(Table2[[#This Row],[Customer_ID]],Table1[Customer_ID],Table1[EMI_Amount],,0) -> 2686.5841 | H17: =Table2[[#This Row],[EMI_Amount]] -> 2686.5841 | I17: 2687 | J17: =Table2[[#This Row],[EMI_Due_May26]]-Table2[[#This Row],[Amount_Received_May26]] -> -0.41594581 | K17: =DATE(2026,5,DAY(Table1[[#This Row],[Maturity_Date]])) -> 46169 | L17: =IF(Table2[[#This Row],[Overdue_Amount]]<1,"",MAX(0,TODAY()-Table2[[#This Row],[EMI_Due_Date]])) | M17: =IF(LEN(Table2[[#This Row],[Days_Past_Due]])=0,"Current", IF(Table2[[#This Row],[Days_Past_Due]]<=30,"1-30", IF(Table2[[#This Row],[Days_Past_Due]]<=60,"31-60", IF(Table2[[#This Row],[Days_Past_Due]]<=90,"61-90","90+")))) -> Current | N17: {=_xlfn.IFS(Table2[[#This Row],[DPD_Bucket]]="1-30","Overdue",Table2[[#This Row],[DPD_Bucket]]="90+","NPA",Table2[[#This Row],[DPD_Bucket]]="Current","Active",Table2[[#This Row],[DPD_Bucket]]="31-60","Overdue")} -> Active
A18: CUST0020 | B18: =_xlfn.XLOOKUP(Table2[[#This Row],[Customer_ID]],Table1[Customer_ID],Table1[Customer_Name],,0,) -> Kiran Dwivedi | C18: =_xlfn.XLOOKUP(Table2[[#This Row],[Customer_ID]],Table1[Customer_ID],Table1[Branch_Name],,) -> Gwalior | D18: =_xlfn.XLOOKUP(Table2[[#This Row],[Customer_ID]],Table1[Customer_ID],Table1[Vehicle_Make],,0) -> Honda | E18: =_xlfn.XLOOKUP(Table2[[#This Row],[Customer_ID]],Table1[Customer_ID],Table1[Vehicle_Model],,) -> City | F18: =_xlfn.XLOOKUP(Table2[[#This Row],[Customer_ID]],Table1[Customer_ID],Table1[Amount_Disbursed],,) -> 905436 | G18: =_xlfn.XLOOKUP(Table2[[#This Row],[Customer_ID]],Table1[Customer_ID],Table1[EMI_Amount],,0) -> 79834.006 | H18: =Table2[[#This Row],[EMI_Amount]] -> 79834.006 | I18: 79834 | J18: =Table2[[#This Row],[EMI_Due_May26]]-Table2[[#This Row],[Amount_Received_May26]] -> 0.0062576602 | K18: =DATE(2026,5,DAY(Table1[[#This Row],[Maturity_Date]])) -> 46173 | L18: =IF(Table2[[#This Row],[Overdue_Amount]]<1,"",MAX(0,TODAY()-Table2[[#This Row],[EMI_Due_Date]])) | M18: =IF(LEN(Table2[[#This Row],[Days_Past_Due]])=0,"Current", IF(Table2[[#This Row],[Days_Past_Due]]<=30,"1-30", IF(Table2[[#This Row],[Days_Past_Due]]<=60,"31-60", IF(Table2[[#This Row],[Days_Past_Due]]<=90,"61-90","90+")))) -> Current | N18: {=_xlfn.IFS(Table2[[#This Row],[DPD_Bucket]]="1-30","Overdue",Table2[[#This Row],[DPD_Bucket]]="90+","NPA",Table2[[#This Row],[DPD_Bucket]]="Current","Active",Table2[[#This Row],[DPD_Bucket]]="31-60","Overdue")} -> Active
A19: CUST0021 | B19: =_xlfn.XLOOKUP(Table2[[#This Row],[Customer_ID]],Table1[Customer_ID],Table1[Customer_Name],,0,) -> Renu Soni | C19: =_xlfn.XLOOKUP(Table2[[#This Row],[Customer_ID]],Table1[Customer_ID],Table1[Branch_Name],,) -> Bhopal | D19: =_xlfn.XLOOKUP(Table2[[#This Row],[Customer_ID]],Table1[Customer_ID],Table1[Vehicle_Make],,0) -> Maruti | E19: =_xlfn.XLOOKUP(Table2[[#This Row],[Customer_ID]],Table1[Customer_ID],Table1[Vehicle_Model],,) -> Dzire | F19: =_xlfn.XLOOKUP(Table2[[#This Row],[Customer_ID]],Table1[Customer_ID],Table1[Amount_Disbursed],,) -> 591412 | G19: =_xlfn.XLOOKUP(Table2[[#This Row],[Customer_ID]],Table1[Customer_ID],Table1[EMI_Amount],,0) -> 16268.21 | H19: =Table2[[#This Row],[EMI_Amount]] -> 16268.21 | I19: 16268 | J19: =Table2[[#This Row],[EMI_Due_May26]]-Table2[[#This Row],[Amount_Received_May26]] -> 0.21020272 | K19: =DATE(2026,5,DAY(Table1[[#This Row],[Maturity_Date]])) -> 46165 | L19: =IF(Table2[[#This Row],[Overdue_Amount]]<1,"",MAX(0,TODAY()-Table2[[#This Row],[EMI_Due_Date]])) | M19: =IF(LEN(Table2[[#This Row],[Days_Past_Due]])=0,"Current", IF(Table2[[#This Row],[Days_Past_Due]]<=30,"1-30", IF(Table2[[#This Row],[Days_Past_Due]]<=60,"31-60", IF(Table2[[#This Row],[Days_Past_Due]]<=90,"61-90","90+")))) -> Current | N19: {=_xlfn.IFS(Table2[[#This Row],[DPD_Bucket]]="1-30","Overdue",Table2[[#This Row],[DPD_Bucket]]="90+","NPA",Table2[[#This Row],[DPD_Bucket]]="Current","Active",Table2[[#This Row],[DPD_Bucket]]="31-60","Overdue")} -> Active
A20: CUST0022 | B20: =_xlfn.XLOOKUP(Table2[[#This Row],[Customer_ID]],Table1[Customer_ID],Table1[Customer_Name],,0,) -> Pradeep Pandey | C20: =_xlfn.XLOOKUP(Table2[[#This Row],[Customer_ID]],Table1[Customer_ID],Table1[Branch_Name],,) -> Gwalior | D20: =_xlfn.XLOOKUP(Table2[[#This Row],[Customer_ID]],Table1[Customer_ID],Table1[Vehicle_Make],,0) -> Tata | E20: =_xlfn.XLOOKUP(Table2[[#This Row],[Customer_ID]],Table1[Customer_ID],Table1[Vehicle_Model],,) -> Nexon | F20: =_xlfn.XLOOKUP(Table2[[#This Row],[Customer_ID]],Table1[Customer_ID],Table1[Amount_Disbursed],,) -> 737287 | G20: =_xlfn.XLOOKUP(Table2[[#This Row],[Customer_ID]],Table1[Customer_ID],Table1[EMI_Amount],,0) -> 16159.398 | H20: =Table2[[#This Row],[EMI_Amount]] -> 16159.398 | I20: 16159 | J20: =Table2[[#This Row],[EMI_Due_May26]]-Table2[[#This Row],[Amount_Received_May26]] -> 0.39783303 | K20: =DATE(2026,5,DAY(Table1[[#This Row],[Maturity_Date]])) -> 46159 | L20: =IF(Table2[[#This Row],[Overdue_Amount]]<1,"",MAX(0,TODAY()-Table2[[#This Row],[EMI_Due_Date]])) | M20: =IF(LEN(Table2[[#This Row],[Days_Past_Due]])=0,"Current", IF(Table2[[#This Row],[Days_Past_Due]]<=30,"1-30", IF(Table2[[#This Row],[Days_Past_Due]]<=60,"31-60", IF(Table2[[#This Row],[Days_Past_Due]]<=90,"61-90","90+")))) -> Current | N20: {=_xlfn.IFS(Table2[[#This Row],[DPD_Bucket]]="1-30","Overdue",Table2[[#This Row],[DPD_Bucket]]="90+","NPA",Table2[[#This Row],[DPD_Bucket]]="Current","Active",Table2[[#This Row],[DPD_Bucket]]="31-60","Overdue")} -> Active
A21: CUST0023 | B21: =_xlfn.XLOOKUP(Table2[[#This Row],[Customer_ID]],Table1[Customer_ID],Table1[Customer_Name],,0,) -> Mohit Agarwal | C21: =_xlfn.XLOOKUP(Table2[[#This Row],[Customer_ID]],Table1[Customer_ID],Table1[Branch_Name],,) -> Indore | D21: =_xlfn.XLOOKUP(Table2[[#This Row],[Customer_ID]],Table1[Customer_ID],Table1[Vehicle_Make],,0) -> Mahindra | E21: =_xlfn.XLOOKUP(Table2[[#This Row],[Customer_ID]],Table1[Customer_ID],Table1[Vehicle_Model],,) -> Bolero | F21: =_xlfn.XLOOKUP(Table2[[#This Row],[Customer_ID]],Table1[Customer_ID],Table1[Amount_Disbursed],,) -> 777162 | G21: =_xlfn.XLOOKUP(Table2[[#This Row],[Customer_ID]],Table1[Customer_ID],Table1[EMI_Amount],,0) -> 27437.956 | H21: =Table2[[#This Row],[EMI_Amount]] -> 27437.956 | I21: 21611 | J21: =Table2[[#This Row],[EMI_Due_May26]]-Table2[[#This Row],[Amount_Received_May26]] -> 5826.9556 | K21: =DATE(2026,5,DAY(Table1[[#This Row],[Maturity_Date]])) -> 46155 | L21: =IF(Table2[[#This Row],[Overdue_Amount]]<1,"",MAX(0,TODAY()-Table2[[#This Row],[EMI_Due_Date]])) -> 25 | M21: =IF(LEN(Table2[[#This Row],[Days_Past_Due]])=0,"Current", IF(Table2[[#This Row],[Days_Past_Due]]<=30,"1-30", IF(Table2[[#This Row],[Days_Past_Due]]<=60,"31-60", IF(Table2[[#This Row],[Days_Past_Due]]<=90,"61-90","90+")))) -> 1-30 | N21: {=_xlfn.IFS(Table2[[#This Row],[DPD_Bucket]]="1-30","Overdue",Table2[[#This Row],[DPD_Bucket]]="90+","NPA",Table2[[#This Row],[DPD_Bucket]]="Current","Active",Table2[[#This Row],[DPD_Bucket]]="31-60","Overdue")} -> Overdue
A22: CUST0024 | B22: =_xlfn.XLOOKUP(Table2[[#This Row],[Customer_ID]],Table1[Customer_ID],Table1[Customer_Name],,0,) -> Mohit Patel | C22: =_xlfn.XLOOKUP(Table2[[#This Row],[Customer_ID]],Table1[Customer_ID],Table1[Branch_Name],,) -> Gwalior | D22: =_xlfn.XLOOKUP(Table2[[#This Row],[Customer_ID]],Table1[Customer_ID],Table1[Vehicle_Make],,0) -> Maruti | E22: =_xlfn.XLOOKUP(Table2[[#This Row],[Customer_ID]],Table1[Customer_ID],Table1[Vehicle_Model],,) -> Swift | F22: =_xlfn.XLOOKUP(Table2[[#This Row],[Customer_ID]],Table1[Customer_ID],Table1[Amount_Disbursed],,) -> 530352 | G22: =_xlfn.XLOOKUP(Table2[[#This Row],[Customer_ID]],Table1[Customer_ID],Table1[EMI_Amount],,0) -> 13953.186 | H22: =Table2[[#This Row],[EMI_Amount]] -> 13953.186 | I22: 13953 | J22: =Table2[[#This Row],[EMI_Due_May26]]-Table2[[#This Row],[Amount_Received_May26]] -> 0.18592892 | K22: =DATE(2026,5,DAY(Table1[[#This Row],[Maturity_Date]])) -> 46164 | L22: =IF(Table2[[#This Row],[Overdue_Amount]]<1,"",MAX(0,TODAY()-Table2[[#This Row],[EMI_Due_Date]])) | M22: =IF(LEN(Table2[[#This Row],[Days_Past_Due]])=0,"Current", IF(Table2[[#This Row],[Days_Past_Due]]<=30,"1-30", IF(Table2[[#This Row],[Days_Past_Due]]<=60,"31-60", IF(Table2[[#This Row],[Days_Past_Due]]<=90,"61-90","90+")))) -> Current | N22: {=_xlfn.IFS(Table2[[#This Row],[DPD_Bucket]]="1-30","Overdue",Table2[[#This Row],[DPD_Bucket]]="90+","NPA",Table2[[#This Row],[DPD_Bucket]]="Current","Active",Table2[[#This Row],[DPD_Bucket]]="31-60","Overdue")} -> Active
... A394: CUST0464 | B394: =_xlfn.XLOOKUP(Table2[[#This Row],[Customer_ID]],Table1[Customer_ID],Table1[Customer_Name],,0,) -> Ajay Thakur | C394: =_xlfn.XLOOKUP(Table2[[#This Row],[Customer_ID]],Table1[Customer_ID],Table1[Branch_Name],,) -> Gwalior | D394: =_xlfn.XLOOKUP(Table2[[#This Row],[Customer_ID]],Table1[Customer_ID],Table1[Vehicle_Make],,0) -> Maruti | E394: =_xlfn.XLOOKUP(Table2[[#This Row],[Customer_ID]],Table1[Customer_ID],Table1[Vehicle_Model],,) -> Swift | F394: =_xlfn.XLOOKUP(Table2[[#This Row],[Customer_ID]],Table1[Customer_ID],Table1[Amount_Disbursed],,) -> 451434 | G394: =_xlfn.XLOOKUP(Table2[[#This Row],[Customer_ID]],Table1[Customer_ID],Table1[EMI_Amount],,0) -> 39896.38 | H394: =Table2[[#This Row],[EMI_Amount]] -> 39896.38 | I394: 39896 | J394: =Table2[[#This Row],[EMI_Due_May26]]-Table2[[#This Row],[Amount_Received_May26]] -> 0.37994506 | K394: =DATE(2026,5,DAY(Table1[[#This Row],[Maturity_Date]])) -> 46171 | L394: =IF(Table2[[#This Row],[Overdue_Amount]]<1,"",MAX(0,TODAY()-Table2[[#This Row],[EMI_Due_Date]])) | M394: =IF(LEN(Table2[[#This Row],[Days_Past_Due]])=0,"Current", IF(Table2[[#This Row],[Days_Past_Due]]<=30,"1-30", IF(Table2[[#This Row],[Days_Past_Due]]<=60,"31-60", IF(Table2[[#This Row],[Days_Past_Due]]<=90,"61-90","90+")))) -> Current | N394: {=_xlfn.IFS(Table2[[#This Row],[DPD_Bucket]]="1-30","Overdue",Table2[[#This Row],[DPD_Bucket]]="90+","NPA",Table2[[#This Row],[DPD_Bucket]]="Current","Active",Table2[[#This Row],[DPD_Bucket]]="31-60","Overdue")} -> Active
A395: CUST0465 | B395: =_xlfn.XLOOKUP(Table2[[#This Row],[Customer_ID]],Table1[Customer_ID],Table1[Customer_Name],,0,) -> Manoj Mishra | C395: =_xlfn.XLOOKUP(Table2[[#This Row],[Customer_ID]],Table1[Customer_ID],Table1[Branch_Name],,) -> Indore | D395: =_xlfn.XLOOKUP(Table2[[#This Row],[Customer_ID]],Table1[Customer_ID],Table1[Vehicle_Make],,0) -> Honda | E395: =_xlfn.XLOOKUP(Table2[[#This Row],[Customer_ID]],Table1[Customer_ID],Table1[Vehicle_Model],,) -> Activa | F395: =_xlfn.XLOOKUP(Table2[[#This Row],[Customer_ID]],Table1[Customer_ID],Table1[Amount_Disbursed],,) -> 59521 | G395: =_xlfn.XLOOKUP(Table2[[#This Row],[Customer_ID]],Table1[Customer_ID],Table1[EMI_Amount],,0) -> 2807.9792 | H395: =Table2[[#This Row],[EMI_Amount]] -> 2807.9792 | I395: 2808 | J395: =Table2[[#This Row],[EMI_Due_May26]]-Table2[[#This Row],[Amount_Received_May26]] -> -0.020849483 | K395: =DATE(2026,5,DAY(Table1[[#This Row],[Maturity_Date]])) -> 46168 | L395: =IF(Table2[[#This Row],[Overdue_Amount]]<1,"",MAX(0,TODAY()-Table2[[#This Row],[EMI_Due_Date]])) | M395: =IF(LEN(Table2[[#This Row],[Days_Past_Due]])=0,"Current", IF(Table2[[#This Row],[Days_Past_Due]]<=30,"1-30", IF(Table2[[#This Row],[Days_Past_Due]]<=60,"31-60", IF(Table2[[#This Row],[Days_Past_Due]]<=90,"61-90","90+")))) -> Current | N395: {=_xlfn.IFS(Table2[[#This Row],[DPD_Bucket]]="1-30","Overdue",Table2[[#This Row],[DPD_Bucket]]="90+","NPA",Table2[[#This Row],[DPD_Bucket]]="Current","Active",Table2[[#This Row],[DPD_Bucket]]="31-60","Overdue")} -> Active | KX395: 90+
A396: CUST0466 | B396: =_xlfn.XLOOKUP(Table2[[#This Row],[Customer_ID]],Table1[Customer_ID],Table1[Customer_Name],,0,) -> Sanjay Thakur | C396: =_xlfn.XLOOKUP(Table2[[#This Row],[Customer_ID]],Table1[Customer_ID],Table1[Branch_Name],,) -> Bhopal | D396: =_xlfn.XLOOKUP(Table2[[#This Row],[Customer_ID]],Table1[Customer_ID],Table1[Vehicle_Make],,0) -> Renault | E396: =_xlfn.XLOOKUP(Table2[[#This Row],[Customer_ID]],Table1[Customer_ID],Table1[Vehicle_Model],,) -> Kwid | F396: =_xlfn.XLOOKUP(Table2[[#This Row],[Customer_ID]],Table1[Customer_ID],Table1[Amount_Disbursed],,) -> 410673 | G396: =_xlfn.XLOOKUP(Table2[[#This Row],[Customer_ID]],Table1[Customer_ID],Table1[EMI_Amount],,0) -> 25753.305 | H396: =Table2[[#This Row],[EMI_Amount]] -> 25753.305 | I396: 25753 | J396: =Table2[[#This Row],[EMI_Due_May26]]-Table2[[#This Row],[Amount_Received_May26]] -> 0.30518157 | K396: =DATE(2026,5,DAY(Table1[[#This Row],[Maturity_Date]])) -> 46147 | L396: =IF(Table2[[#This Row],[Overdue_Amount]]<1,"",MAX(0,TODAY()-Table2[[#This Row],[EMI_Due_Date]])) | M396: =IF(LEN(Table2[[#This Row],[Days_Past_Due]])=0,"Current", IF(Table2[[#This Row],[Days_Past_Due]]<=30,"1-30", IF(Table2[[#This Row],[Days_Past_Due]]<=60,"31-60", IF(Table2[[#This Row],[Days_Past_Due]]<=90,"61-90","90+")))) -> Current | N396: {=_xlfn.IFS(Table2[[#This Row],[DPD_Bucket]]="1-30","Overdue",Table2[[#This Row],[DPD_Bucket]]="90+","NPA",Table2[[#This Row],[DPD_Bucket]]="Current","Active",Table2[[#This Row],[DPD_Bucket]]="31-60","Overdue")} -> Active
A397: CUST0467 | B397: =_xlfn.XLOOKUP(Table2[[#This Row],[Customer_ID]],Table1[Customer_ID],Table1[Customer_Name],,0,) -> Vijay Shukla | C397: =_xlfn.XLOOKUP(Table2[[#This Row],[Customer_ID]],Table1[Customer_ID],Table1[Branch_Name],,) -> Indore | D397: =_xlfn.XLOOKUP(Table2[[#This Row],[Customer_ID]],Table1[Customer_ID],Table1[Vehicle_Make],,0) -> Tata | E397: =_xlfn.XLOOKUP(Table2[[#This Row],[Customer_ID]],Table1[Customer_ID],Table1[Vehicle_Model],,) -> Tiago | F397: =_xlfn.XLOOKUP(Table2[[#This Row],[Customer_ID]],Table1[Customer_ID],Table1[Amount_Disbursed],,) -> 490321 | G397: =_xlfn.XLOOKUP(Table2[[#This Row],[Customer_ID]],Table1[Customer_ID],Table1[EMI_Amount],,0) -> 13770.596 | H397: =Table2[[#This Row],[EMI_Amount]] -> 13770.596 | I397: 13771 | J397: =Table2[[#This Row],[EMI_Due_May26]]-Table2[[#This Row],[Amount_Received_May26]] -> -0.40390172 | K397: =DATE(2026,5,DAY(Table1[[#This Row],[Maturity_Date]])) -> 46165 | L397: =IF(Table2[[#This Row],[Overdue_Amount]]<1,"",MAX(0,TODAY()-Table2[[#This Row],[EMI_Due_Date]])) | M397: =IF(LEN(Table2[[#This Row],[Days_Past_Due]])=0,"Current", IF(Table2[[#This Row],[Days_Past_Due]]<=30,"1-30", IF(Table2[[#This Row],[Days_Past_Due]]<=60,"31-60", IF(Table2[[#This Row],[Days_Past_Due]]<=90,"61-90","90+")))) -> Current | N397: {=_xlfn.IFS(Table2[[#This Row],[DPD_Bucket]]="1-30","Overdue",Table2[[#This Row],[DPD_Bucket]]="90+","NPA",Table2[[#This Row],[DPD_Bucket]]="Current","Active",Table2[[#This Row],[DPD_Bucket]]="31-60","Overdue")} -> Active
A398: CUST0468 | B398: =_xlfn.XLOOKUP(Table2[[#This Row],[Customer_ID]],Table1[Customer_ID],Table1[Customer_Name],,0,) -> Santosh Gupta | C398: =_xlfn.XLOOKUP(Table2[[#This Row],[Customer_ID]],Table1[Customer_ID],Table1[Branch_Name],,) -> Indore | D398: =_xlfn.XLOOKUP(Table2[[#This Row],[Customer_ID]],Table1[Customer_ID],Table1[Vehicle_Make],,0) -> Honda | E398: =_xlfn.XLOOKUP(Table2[[#This Row],[Customer_ID]],Table1[Customer_ID],Table1[Vehicle_Model],,) -> Activa | F398: =_xlfn.XLOOKUP(Table2[[#This Row],[Customer_ID]],Table1[Customer_ID],Table1[Amount_Disbursed],,) -> 117970 | G398: =_xlfn.XLOOKUP(Table2[[#This Row],[Customer_ID]],Table1[Customer_ID],Table1[EMI_Amount],,0) -> 2684.784 | H398: =Table2[[#This Row],[EMI_Amount]] -> 2684.784 | I398: 2685 | J398: =Table2[[#This Row],[EMI_Due_May26]]-Table2[[#This Row],[Amount_Received_May26]] -> -0.21603426 | K398: =DATE(2026,5,DAY(Table1[[#This Row],[Maturity_Date]])) -> 46153 | L398: =IF(Table2[[#This Row],[Overdue_Amount]]<1,"",MAX(0,TODAY()-Table2[[#This Row],[EMI_Due_Date]])) | M398: =IF(LEN(Table2[[#This Row],[Days_Past_Due]])=0,"Current", IF(Table2[[#This Row],[Days_Past_Due]]<=30,"1-30", IF(Table2[[#This Row],[Days_Past_Due]]<=60,"31-60", IF(Table2[[#This Row],[Days_Past_Due]]<=90,"61-90","90+")))) -> Current | N398: {=_xlfn.IFS(Table2[[#This Row],[DPD_Bucket]]="1-30","Overdue",Table2[[#This Row],[DPD_Bucket]]="90+","NPA",Table2[[#This Row],[DPD_Bucket]]="Current","Active",Table2[[#This Row],[DPD_Bucket]]="31-60","Overdue")} -> Active
A399: CUST0469 | B399: =_xlfn.XLOOKUP(Table2[[#This Row],[Customer_ID]],Table1[Customer_ID],Table1[Customer_Name],,0,) -> Ramesh Thakur | C399: =_xlfn.XLOOKUP(Table2[[#This Row],[Customer_ID]],Table1[Customer_ID],Table1[Branch_Name],,) -> Gwalior | D399: =_xlfn.XLOOKUP(Table2[[#This Row],[Customer_ID]],Table1[Customer_ID],Table1[Vehicle_Make],,0) -> Tata | E399: =_xlfn.XLOOKUP(Table2[[#This Row],[Customer_ID]],Table1[Customer_ID],Table1[Vehicle_Model],,) -> Tiago | F399: =_xlfn.XLOOKUP(Table2[[#This Row],[Customer_ID]],Table1[Customer_ID],Table1[Amount_Disbursed],,) -> 450022 | G399: =_xlfn.XLOOKUP(Table2[[#This Row],[Customer_ID]],Table1[Customer_ID],Table1[EMI_Amount],,0) -> 12070.73 | H399: =Table2[[#This Row],[EMI_Amount]] -> 12070.73 | I399: 7012 | J399: =Table2[[#This Row],[EMI_Due_May26]]-Table2[[#This Row],[Amount_Received_May26]] -> 5058.7299 | K399: =DATE(2026,5,DAY(Table1[[#This Row],[Maturity_Date]])) -> 46152 | L399: =IF(Table2[[#This Row],[Overdue_Amount]]<1,"",MAX(0,TODAY()-Table2[[#This Row],[EMI_Due_Date]])) -> 28 | M399: =IF(LEN(Table2[[#This Row],[Days_Past_Due]])=0,"Current", IF(Table2[[#This Row],[Days_Past_Due]]<=30,"1-30", IF(Table2[[#This Row],[Days_Past_Due]]<=60,"31-60", IF(Table2[[#This Row],[Days_Past_Due]]<=90,"61-90","90+")))) -> 1-30 | N399: {=_xlfn.IFS(Table2[[#This Row],[DPD_Bucket]]="1-30","Overdue",Table2[[#This Row],[DPD_Bucket]]="90+","NPA",Table2[[#This Row],[DPD_Bucket]]="Current","Active",Table2[[#This Row],[DPD_Bucket]]="31-60","Overdue")} -> Overdue
A400: CUST0471 | B400: =_xlfn.XLOOKUP(Table2[[#This Row],[Customer_ID]],Table1[Customer_ID],Table1[Customer_Name],,0,) -> Ramesh Shukla | C400: =_xlfn.XLOOKUP(Table2[[#This Row],[Customer_ID]],Table1[Customer_ID],Table1[Branch_Name],,) -> Jabalpur | D400: =_xlfn.XLOOKUP(Table2[[#This Row],[Customer_ID]],Table1[Customer_ID],Table1[Vehicle_Make],,0) -> Mahindra | E400: =_xlfn.XLOOKUP(Table2[[#This Row],[Customer_ID]],Table1[Customer_ID],Table1[Vehicle_Model],,) -> Bolero | F400: =_xlfn.XLOOKUP(Table2[[#This Row],[Customer_ID]],Table1[Customer_ID],Table1[Amount_Disbursed],,) -> 799838 | G400: =_xlfn.XLOOKUP(Table2[[#This Row],[Customer_ID]],Table1[Customer_ID],Table1[EMI_Amount],,0) -> 38315.679 | H400: =Table2[[#This Row],[EMI_Amount]] -> 38315.679 | I400: 38316 | J400: =Table2[[#This Row],[EMI_Due_May26]]-Table2[[#This Row],[Amount_Received_May26]] -> -0.32078829 | K400: =DATE(2026,5,DAY(Table1[[#This Row],[Maturity_Date]])) -> 46144 | L400: =IF(Table2[[#This Row],[Overdue_Amount]]<1,"",MAX(0,TODAY()-Table2[[#This Row],[EMI_Due_Date]])) | M400: =IF(LEN(Table2[[#This Row],[Days_Past_Due]])=0,"Current", IF(Table2[[#This Row],[Days_Past_Due]]<=30,"1-30", IF(Table2[[#This Row],[Days_Past_Due]]<=60,"31-60", IF(Table2[[#This Row],[Days_Past_Due]]<=90,"61-90","90+")))) -> Current | N400: {=_xlfn.IFS(Table2[[#This Row],[DPD_Bucket]]="1-30","Overdue",Table2[[#This Row],[DPD_Bucket]]="90+","NPA",Table2[[#This Row],[DPD_Bucket]]="Current","Active",Table2[[#This Row],[DPD_Bucket]]="31-60","Overdue")} -> Active
A401: CUST0472 | B401: =_xlfn.XLOOKUP(Table2[[#This Row],[Customer_ID]],Table1[Customer_ID],Table1[Customer_Name],,0,) -> Nisha Sharma | C401: =_xlfn.XLOOKUP(Table2[[#This Row],[Customer_ID]],Table1[Customer_ID],Table1[Branch_Name],,) -> Indore | D401: =_xlfn.XLOOKUP(Table2[[#This Row],[Customer_ID]],Table1[Customer_ID],Table1[Vehicle_Make],,0) -> Tata | E401: =_xlfn.XLOOKUP(Table2[[#This Row],[Customer_ID]],Table1[Customer_ID],Table1[Vehicle_Model],,) -> Nexon | F401: =_xlfn.XLOOKUP(Table2[[#This Row],[Customer_ID]],Table1[Customer_ID],Table1[Amount_Disbursed],,) -> 860801 | G401: =_xlfn.XLOOKUP(Table2[[#This Row],[Customer_ID]],Table1[Customer_ID],Table1[EMI_Amount],,0) -> 22394.446 | H401: =Table2[[#This Row],[EMI_Amount]] -> 22394.446 | I401: 22394 | J401: =Table2[[#This Row],[EMI_Due_May26]]-Table2[[#This Row],[Amount_Received_May26]] -> 0.44571878 | K401: =DATE(2026,5,DAY(Table1[[#This Row],[Maturity_Date]])) -> 46145 | L401: =IF(Table2[[#This Row],[Overdue_Amount]]<1,"",MAX(0,TODAY()-Table2[[#This Row],[EMI_Due_Date]])) | M401: =IF(LEN(Table2[[#This Row],[Days_Past_Due]])=0,"Current", IF(Table2[[#This Row],[Days_Past_Due]]<=30,"1-30", IF(Table2[[#This Row],[Days_Past_Due]]<=60,"31-60", IF(Table2[[#This Row],[Days_Past_Due]]<=90,"61-90","90+")))) -> Current | N401: {=_xlfn.IFS(Table2[[#This Row],[DPD_Bucket]]="1-30","Overdue",Table2[[#This Row],[DPD_Bucket]]="90+","NPA",Table2[[#This Row],[DPD_Bucket]]="Current","Active",Table2[[#This Row],[DPD_Bucket]]="31-60","Overdue")} -> Active
A402: CUST0474 | B402: =_xlfn.XLOOKUP(Table2[[#This Row],[Customer_ID]],Table1[Customer_ID],Table1[Customer_Name],,0,) -> Asha Mishra | C402: =_xlfn.XLOOKUP(Table2[[#This Row],[Customer_ID]],Table1[Customer_ID],Table1[Branch_Name],,) -> Gwalior | D402: =_xlfn.XLOOKUP(Table2[[#This Row],[Customer_ID]],Table1[Customer_ID],Table1[Vehicle_Make],,0) -> Hero | E402: =_xlfn.XLOOKUP(Table2[[#This Row],[Customer_ID]],Table1[Customer_ID],Table1[Vehicle_Model],,) -> Splendor | F402: =_xlfn.XLOOKUP(Table2[[#This Row],[Customer_ID]],Table1[Customer_ID],Table1[Amount_Disbursed],,) -> 44596 | G402: =_xlfn.XLOOKUP(Table2[[#This Row],[Customer_ID]],Table1[Customer_ID],Table1[EMI_Amount],,0) -> 2150.8865 | H402: =Table2[[#This Row],[EMI_Amount]] -> 2150.8865 | I402: 2151 | J402: =Table2[[#This Row],[EMI_Due_May26]]-Table2[[#This Row],[Amount_Received_May26]] -> -0.11353174 | K402: =DATE(2026,5,DAY(Table1[[#This Row],[Maturity_Date]])) -> 46158 | L402: =IF(Table2[[#This Row],[Overdue_Amount]]<1,"",MAX(0,TODAY()-Table2[[#This Row],[EMI_Due_Date]])) | M402: =IF(LEN(Table2[[#This Row],[Days_Past_Due]])=0,"Current", IF(Table2[[#This Row],[Days_Past_Due]]<=30,"1-30", IF(Table2[[#This Row],[Days_Past_Due]]<=60,"31-60", IF(Table2[[#This Row],[Days_Past_Due]]<=90,"61-90","90+")))) -> Current | N402: {=_xlfn.IFS(Table2[[#This Row],[DPD_Bucket]]="1-30","Overdue",Table2[[#This Row],[DPD_Bucket]]="90+","NPA",Table2[[#This Row],[DPD_Bucket]]="Current","Active",Table2[[#This Row],[DPD_Bucket]]="31-60","Overdue")} -> Active
A403: CUST0475 | B403: =_xlfn.XLOOKUP(Table2[[#This Row],[Customer_ID]],Table1[Customer_ID],Table1[Customer_Name],,0,) -> Pushpa Chauhan | C403: =_xlfn.XLOOKUP(Table2[[#This Row],[Customer_ID]],Table1[Customer_ID],Table1[Branch_Name],,) -> Jabalpur | D403: =_xlfn.XLOOKUP(Table2[[#This Row],[Customer_ID]],Table1[Customer_ID],Table1[Vehicle_Make],,0) -> Maruti | E403: =_xlfn.XLOOKUP(Table2[[#This Row],[Customer_ID]],Table1[Customer_ID],Table1[Vehicle_Model],,) -> Dzire | F403: =_xlfn.XLOOKUP(Table2[[#This Row],[Customer_ID]],Table1[Customer_ID],Table1[Amount_Disbursed],,) -> 586992 | G403: =_xlfn.XLOOKUP(Table2[[#This Row],[Customer_ID]],Table1[Customer_ID],Table1[EMI_Amount],,0) -> 19547.037 | H403: =Table2[[#This Row],[EMI_Amount]] -> 19547.037 | I403: 19547 | J403: =Table2[[#This Row],[EMI_Due_May26]]-Table2[[#This Row],[Amount_Received_May26]] -> 0.037257015 | K403: =DATE(2026,5,DAY(Table1[[#This Row],[Maturity_Date]])) -> 46147 | L403: =IF(Table2[[#This Row],[Overdue_Amount]]<1,"",MAX(0,TODAY()-Table2[[#This Row],[EMI_Due_Date]])) | M403: =IF(LEN(Table2[[#This Row],[Days_Past_Due]])=0,"Current", IF(Table2[[#This Row],[Days_Past_Due]]<=30,"1-30", IF(Table2[[#This Row],[Days_Past_Due]]<=60,"31-60", IF(Table2[[#This Row],[Days_Past_Due]]<=90,"61-90","90+")))) -> Current | N403: {=_xlfn.IFS(Table2[[#This Row],[DPD_Bucket]]="1-30","Overdue",Table2[[#This Row],[DPD_Bucket]]="90+","NPA",Table2[[#This Row],[DPD_Bucket]]="Current","Active",Table2[[#This Row],[DPD_Bucket]]="31-60","Overdue")} -> Active
A404: CUST0476 | B404: =_xlfn.XLOOKUP(Table2[[#This Row],[Customer_ID]],Table1[Customer_ID],Table1[Customer_Name],,0,) -> Kiran Singh | C404: =_xlfn.XLOOKUP(Table2[[#This Row],[Customer_ID]],Table1[Customer_ID],Table1[Branch_Name],,) -> Gwalior | D404: =_xlfn.XLOOKUP(Table2[[#This Row],[Customer_ID]],Table1[Customer_ID],Table1[Vehicle_Make],,0) -> Mahindra | E404: =_xlfn.XLOOKUP(Table2[[#This Row],[Customer_ID]],Table1[Customer_ID],Table1[Vehicle_Model],,) -> Bolero | F404: =_xlfn.XLOOKUP(Table2[[#This Row],[Customer_ID]],Table1[Customer_ID],Table1[Amount_Disbursed],,) -> 678985 | G404: =_xlfn.XLOOKUP(Table2[[#This Row],[Customer_ID]],Table1[Customer_ID],Table1[EMI_Amount],,0) -> 16199.376 | H404: =Table2[[#This Row],[EMI_Amount]] -> 16199.376 | I404: 5975 | J404: =Table2[[#This Row],[EMI_Due_May26]]-Table2[[#This Row],[Amount_Received_May26]] -> 10224.376 | K404: =DATE(2026,5,DAY(Table1[[#This Row],[Maturity_Date]])) -> 46146 | L404: =IF(Table2[[#This Row],[Overdue_Amount]]<1,"",MAX(0,TODAY()-Table2[[#This Row],[EMI_Due_Date]])) -> 34 | M404: =IF(LEN(Table2[[#This Row],[Days_Past_Due]])=0,"Current", IF(Table2[[#This Row],[Days_Past_Due]]<=30,"1-30", IF(Table2[[#This Row],[Days_Past_Due]]<=60,"31-60", IF(Table2[[#This Row],[Days_Past_Due]]<=90,"61-90","90+")))) -> 31-60 | N404: {=_xlfn.IFS(Table2[[#This Row],[DPD_Bucket]]="1-30","Overdue",Table2[[#This Row],[DPD_Bucket]]="90+","NPA",Table2[[#This Row],[DPD_Bucket]]="Current","Active",Table2[[#This Row],[DPD_Bucket]]="31-60","Overdue")} -> Overdue
A405: CUST0477 | B405: =_xlfn.XLOOKUP(Table2[[#This Row],[Customer_ID]],Table1[Customer_ID],Table1[Customer_Name],,0,) -> Anita Agarwal | C405: =_xlfn.XLOOKUP(Table2[[#This Row],[Customer_ID]],Table1[Customer_ID],Table1[Branch_Name],,) -> Jabalpur | D405: =_xlfn.XLOOKUP(Table2[[#This Row],[Customer_ID]],Table1[Customer_ID],Table1[Vehicle_Make],,0) -> Tata | E405: =_xlfn.XLOOKUP(Table2[[#This Row],[Customer_ID]],Table1[Customer_ID],Table1[Vehicle_Model],,) -> Tiago | F405: =_xlfn.XLOOKUP(Table2[[#This Row],[Customer_ID]],Table1[Customer_ID],Table1[Amount_Disbursed],,) -> 470417 | G405: =_xlfn.XLOOKUP(Table2[[#This Row],[Customer_ID]],Table1[Customer_ID],Table1[EMI_Amount],,0) -> 11134.474 | H405: =Table2[[#This Row],[EMI_Amount]] -> 11134.474 | I405: 5878 | J405: =Table2[[#This Row],[EMI_Due_May26]]-Table2[[#This Row],[Amount_Received_May26]] -> 5256.4745 | K405: =DATE(2026,5,DAY(Table1[[#This Row],[Maturity_Date]])) -> 46162 | L405: =IF(Table2[[#This Row],[Overdue_Amount]]<1,"",MAX(0,TODAY()-Table2[[#This Row],[EMI_Due_Date]])) -> 18 | M405: =IF(LEN(Table2[[#This Row],[Days_Past_Due]])=0,"Current", IF(Table2[[#This Row],[Days_Past_Due]]<=30,"1-30", IF(Table2[[#This Row],[Days_Past_Due]]<=60,"31-60", IF(Table2[[#This Row],[Days_Past_Due]]<=90,"61-90","90+")))) -> 1-30 | N405: {=_xlfn.IFS(Table2[[#This Row],[DPD_Bucket]]="1-30","Overdue",Table2[[#This Row],[DPD_Bucket]]="90+","NPA",Table2[[#This Row],[DPD_Bucket]]="Current","Active",Table2[[#This Row],[DPD_Bucket]]="31-60","Overdue")} -> Overdue
A406: CUST0478 | B406: =_xlfn.XLOOKUP(Table2[[#This Row],[Customer_ID]],Table1[Customer_ID],Table1[Customer_Name],,0,) -> Kiran Joshi | C406: =_xlfn.XLOOKUP(Table2[[#This Row],[Customer_ID]],Table1[Customer_ID],Table1[Branch_Name],,) -> Rewa | D406: =_xlfn.XLOOKUP(Table2[[#This Row],[Customer_ID]],Table1[Customer_ID],Table1[Vehicle_Make],,0) -> Hyundai | E406: =_xlfn.XLOOKUP(Table2[[#This Row],[Customer_ID]],Table1[Customer_ID],Table1[Vehicle_Model],,) -> Creta | F406: =_xlfn.XLOOKUP(Table2[[#This Row],[Customer_ID]],Table1[Customer_ID],Table1[Amount_Disbursed],,) -> 1031264 | G406: =_xlfn.XLOOKUP(Table2[[#This Row],[Customer_ID]],Table1[Customer_ID],Table1[EMI_Amount],,0) -> 62482.159 | H406: =Table2[[#This Row],[EMI_Amount]] -> 62482.159 | I406: 62482 | J406: =Table2[[#This Row],[EMI_Due_May26]]-Table2[[#This Row],[Amount_Received_May26]] -> 0.15933649 | K406: =DATE(2026,5,DAY(Table1[[#This Row],[Maturity_Date]])) -> 46167 | L406: =IF(Table2[[#This Row],[Overdue_Amount]]<1,"",MAX(0,TODAY()-Table2[[#This Row],[EMI_Due_Date]])) | M406: =IF(LEN(Table2[[#This Row],[Days_Past_Due]])=0,"Current", IF(Table2[[#This Row],[Days_Past_Due]]<=30,"1-30", IF(Table2[[#This Row],[Days_Past_Due]]<=60,"31-60", IF(Table2[[#This Row],[Days_Past_Due]]<=90,"61-90","90+")))) -> Current | N406: {=_xlfn.IFS(Table2[[#This Row],[DPD_Bucket]]="1-30","Overdue",Table2[[#This Row],[DPD_Bucket]]="90+","NPA",Table2[[#This Row],[DPD_Bucket]]="Current","Active",Table2[[#This Row],[DPD_Bucket]]="31-60","Overdue")} -> Active
A407: CUST0479 | B407: =_xlfn.XLOOKUP(Table2[[#This Row],[Customer_ID]],Table1[Customer_ID],Table1[Customer_Name],,0,) -> Priya Jain | C407: =_xlfn.XLOOKUP(Table2[[#This Row],[Customer_ID]],Table1[Customer_ID],Table1[Branch_Name],,) -> Gwalior | D407: =_xlfn.XLOOKUP(Table2[[#This Row],[Customer_ID]],Table1[Customer_ID],Table1[Vehicle_Make],,0) -> Tata | E407: =_xlfn.XLOOKUP(Table2[[#This Row],[Customer_ID]],Table1[Customer_ID],Table1[Vehicle_Model],,) -> Nexon | F407: =_xlfn.XLOOKUP(Table2[[#This Row],[Customer_ID]],Table1[Customer_ID],Table1[Amount_Disbursed],,) -> 882887 | G407: =_xlfn.XLOOKUP(Table2[[#This Row],[Customer_ID]],Table1[Customer_ID],Table1[EMI_Amount],,0) -> 30969.991 | H407: =Table2[[#This Row],[EMI_Amount]] -> 30969.991 | I407: 0 | J407: =Table2[[#This Row],[EMI_Due_May26]]-Table2[[#This Row],[Amount_Received_May26]] -> 30969.991 | K407: =DATE(2026,5,DAY(Table1[[#This Row],[Maturity_Date]])) -> 46147 | L407: =IF(Table2[[#This Row],[Overdue_Amount]]<1,"",MAX(0,TODAY()-Table2[[#This Row],[EMI_Due_Date]])) -> 33 | M407: =IF(LEN(Table2[[#This Row],[Days_Past_Due]])=0,"Current", IF(Table2[[#This Row],[Days_Past_Due]]<=30,"1-30", IF(Table2[[#This Row],[Days_Past_Due]]<=60,"31-60", IF(Table2[[#This Row],[Days_Past_Due]]<=90,"61-90","90+")))) -> 31-60 | N407: {=_xlfn.IFS(Table2[[#This Row],[DPD_Bucket]]="1-30","Overdue",Table2[[#This Row],[DPD_Bucket]]="90+","NPA",Table2[[#This Row],[DPD_Bucket]]="Current","Active",Table2[[#This Row],[DPD_Bucket]]="31-60","Overdue")} -> Overdue
... A424: CUST0500 | B424: =_xlfn.XLOOKUP(Table2[[#This Row],[Customer_ID]],Table1[Customer_ID],Table1[Customer_Name],,0,) -> Ajay Chauhan | C424: =_xlfn.XLOOKUP(Table2[[#This Row],[Customer_ID]],Table1[Customer_ID],Table1[Branch_Name],,) -> Bhopal | D424: =_xlfn.XLOOKUP(Table2[[#This Row],[Customer_ID]],Table1[Customer_ID],Table1[Vehicle_Make],,0) -> Maruti | E424: =_xlfn.XLOOKUP(Table2[[#This Row],[Customer_ID]],Table1[Customer_ID],Table1[Vehicle_Model],,) -> Swift | F424: =_xlfn.XLOOKUP(Table2[[#This Row],[Customer_ID]],Table1[Customer_ID],Table1[Amount_Disbursed],,) -> 506609 | G424: =_xlfn.XLOOKUP(Table2[[#This Row],[Customer_ID]],Table1[Customer_ID],Table1[EMI_Amount],,0) -> 16708.351 | H424: =Table2[[#This Row],[EMI_Amount]] -> 16708.351 | I424: 16708 | J424: =Table2[[#This Row],[EMI_Due_May26]]-Table2[[#This Row],[Amount_Received_May26]] -> 0.35114388 | K424: =DATE(2026,5,DAY(Table1[[#This Row],[Maturity_Date]])) -> 46173 | L424: =IF(Table2[[#This Row],[Overdue_Amount]]<1,"",MAX(0,TODAY()-Table2[[#This Row],[EMI_Due_Date]])) | M424: =IF(LEN(Table2[[#This Row],[Days_Past_Due]])=0,"Current", IF(Table2[[#This Row],[Days_Past_Due]]<=30,"1-30", IF(Table2[[#This Row],[Days_Past_Due]]<=60,"31-60", IF(Table2[[#This Row],[Days_Past_Due]]<=90,"61-90","90+")))) -> Current | N424: {=_xlfn.IFS(Table2[[#This Row],[DPD_Bucket]]="1-30","Overdue",Table2[[#This Row],[DPD_Bucket]]="90+","NPA",Table2[[#This Row],[DPD_Bucket]]="Current","Active",Table2[[#This Row],[DPD_Bucket]]="31-60","Overdue")} -> Active

Sheet collection_log
A1: ABC Finance | Collection Log | May 2026
A2: Log_ID | B2: Customer_ID | C2: Customer_Name | D2: Branch_Name | E2: Activity_Date | F2: Activity_Type | G2: Agent_Code | H2: Agent_Name | I2: Contact_Result | J2: Commitment_Taken | K2: Commitment_Date | L2: Commitment_Amount | M2: Amount_Collected | N2: Remarks
A3: LOG00001 | B3: CUST0001 | C3: =_xlfn.XLOOKUP(Table3[[#This Row],[Customer_ID]],Table1[Customer_ID],Table1[Customer_Name],,0) -> Vijay Mishra | D3: =_xlfn.XLOOKUP(Table3[[#This Row],[Customer_ID]],Table1[Customer_ID],Table1[Branch_Name],,0) -> Indore | E3: 46173 | F3: Tele-Call | G3: AG005 | H3: =_xlfn.XLOOKUP(Table3[[#This Row],[Agent_Code]],Table4[Agent_Code],Table4[Agent_Name],,0) -> Amit Thakur | I3: Not Reachable | J3: =IF(OR(Table3[[#This Row],[Contact_Result]]="Commitment Received",Table3[[#This Row],[Contact_Result]]="Will Pay Next Week"),"Yes","") | M3: 0 | N3: Not Reachable
A4: LOG00028 | B4: CUST0023 | C4: =_xlfn.XLOOKUP(Table3[[#This Row],[Customer_ID]],Table1[Customer_ID],Table1[Customer_Name],,0) -> Mohit Agarwal | D4: =_xlfn.XLOOKUP(Table3[[#This Row],[Customer_ID]],Table1[Customer_ID],Table1[Branch_Name],,0) -> Indore | E4: 46173 | F4: Tele-Call | G4: AG009 | H4: =_xlfn.XLOOKUP(Table3[[#This Row],[Agent_Code]],Table4[Agent_Code],Table4[Agent_Name],,0) -> Pankaj Joshi | I4: Not Reachable | J4: =IF(OR(Table3[[#This Row],[Contact_Result]]="Commitment Received",Table3[[#This Row],[Contact_Result]]="Will Pay Next Week"),"Yes","") | M4: 0 | N4: Not Reachable
A5: LOG00101 | B5: CUST0093 | C5: =_xlfn.XLOOKUP(Table3[[#This Row],[Customer_ID]],Table1[Customer_ID],Table1[Customer_Name],,0) -> Vijay Dubey | D5: =_xlfn.XLOOKUP(Table3[[#This Row],[Customer_ID]],Table1[Customer_ID],Table1[Branch_Name],,0) -> Jabalpur | E5: 46173 | F5: Tele-Call | G5: AG008 | H5: =_xlfn.XLOOKUP(Table3[[#This Row],[Agent_Code]],Table4[Agent_Code],Table4[Agent_Name],,0) -> Pooja Shukla | I5: Not Reachable | J5: =IF(OR(Table3[[#This Row],[Contact_Result]]="Commitment Received",Table3[[#This Row],[Contact_Result]]="Will Pay Next Week"),"Yes","") | M5: 0 | N5: Not Reachable
A6: LOG00107 | B6: CUST0097 | C6: =_xlfn.XLOOKUP(Table3[[#This Row],[Customer_ID]],Table1[Customer_ID],Table1[Customer_Name],,0) -> Amit Verma | D6: =_xlfn.XLOOKUP(Table3[[#This Row],[Customer_ID]],Table1[Customer_ID],Table1[Branch_Name],,0) -> Gwalior | E6: 46173 | F6: Tele-Call | G6: AG012 | H6: =_xlfn.XLOOKUP(Table3[[#This Row],[Agent_Code]],Table4[Agent_Code],Table4[Agent_Name],,0) -> Umesh Soni | I6: Commitment Received | J6: =IF(OR(Table3[[#This Row],[Contact_Result]]="Commitment Received",Table3[[#This Row],[Contact_Result]]="Will Pay Next Week"),"Yes","") -> Yes | K6: 46178 | L6: 11340 | M6: 0 | N6: Commitment Received
A7: LOG00190 | B7: CUST0185 | C7: =_xlfn.XLOOKUP(Table3[[#This Row],[Customer_ID]],Table1[Customer_ID],Table1[Customer_Name],,0) -> Sumit Tiwari | D7: =_xlfn.XLOOKUP(Table3[[#This Row],[Customer_ID]],Table1[Customer_ID],Table1[Branch_Name],,0) -> Gwalior | E7: 46173 | F7: WhatsApp Message | G7: AG007 | H7: =_xlfn.XLOOKUP(Table3[[#This Row],[Agent_Code]],Table4[Agent_Code],Table4[Agent_Name],,0) -> Pushpa Jain | I7: Will Pay Next Week | J7: =IF(OR(Table3[[#This Row],[Contact_Result]]="Commitment Received",Table3[[#This Row],[Contact_Result]]="Will Pay Next Week"),"Yes","") -> Yes | K7: 46178 | L7: 6224 | M7: 0 | N7: Will Pay Next Week
A8: LOG00222 | B8: CUST0209 | C8: =_xlfn.XLOOKUP(Table3[[#This Row],[Customer_ID]],Table1[Customer_ID],Table1[Customer_Name],,0) -> Santosh Soni | D8: =_xlfn.XLOOKUP(Table3[[#This Row],[Customer_ID]],Table1[Customer_ID],Table1[Branch_Name],,0) -> Bhopal | E8: 46173 | F8: Tele-Call | G8: AG010 | H8: =_xlfn.XLOOKUP(Table3[[#This Row],[Agent_Code]],Table4[Agent_Code],Table4[Agent_Name],,0) -> Kavita Tiwari | I8: Commitment Received | J8: =IF(OR(Table3[[#This Row],[Contact_Result]]="Commitment Received",Table3[[#This Row],[Contact_Result]]="Will Pay Next Week"),"Yes","") -> Yes | K8: 46178 | L8: 27851 | M8: 0 | N8: Commitment Received
A9: LOG00251 | B9: CUST0225 | C9: =_xlfn.XLOOKUP(Table3[[#This Row],[Customer_ID]],Table1[Customer_ID],Table1[Customer_Name],,0) -> Naresh Malviya | D9: =_xlfn.XLOOKUP(Table3[[#This Row],[Customer_ID]],Table1[Customer_ID],Table1[Branch_Name],,0) -> Bhopal | E9: 46173 | F9: Tele-Call | G9: AG020 | H9: =_xlfn.XLOOKUP(Table3[[#This Row],[Agent_Code]],Table4[Agent_Code],Table4[Agent_Name],,0) -> Vijay Tiwari | I9: Commitment Received | J9: =IF(OR(Table3[[#This Row],[Contact_Result]]="Commitment Received",Table3[[#This Row],[Contact_Result]]="Will Pay Next Week"),"Yes","") -> Yes | K9: 46178 | L9: 735 | M9: 0 | N9: Commitment Received
A10: LOG00315 | B10: CUST0295 | C10: =_xlfn.XLOOKUP(Table3[[#This Row],[Customer_ID]],Table1[Customer_ID],Table1[Customer_Name],,0) -> Geeta Verma | D10: =_xlfn.XLOOKUP(Table3[[#This Row],[Customer_ID]],Table1[Customer_ID],Table1[Branch_Name],,0) -> Bhopal | E10: 46173 | F10: WhatsApp Message | G10: AG002 | H10: =_xlfn.XLOOKUP(Table3[[#This Row],[Agent_Code]],Table4[Agent_Code],Table4[Agent_Name],,0) -> Sunita Patel | I10: Will Pay Next Week | J10: =IF(OR(Table3[[#This Row],[Contact_Result]]="Commitment Received",Table3[[#This Row],[Contact_Result]]="Will Pay Next Week"),"Yes","") -> Yes | K10: 46178 | L10: 24458 | M10: 0 | N10: Will Pay Next Week
A11: LOG00319 | B11: CUST0300 | C11: =_xlfn.XLOOKUP(Table3[[#This Row],[Customer_ID]],Table1[Customer_ID],Table1[Customer_Name],,0) -> Pradeep Yadav | D11: =_xlfn.XLOOKUP(Table3[[#This Row],[Customer_ID]],Table1[Customer_ID],Table1[Branch_Name],,0) -> Gwalior | E11: 46173 | F11: WhatsApp Message | G11: AG001 | H11: =_xlfn.XLOOKUP(Table3[[#This Row],[Agent_Code]],Table4[Agent_Code],Table4[Agent_Name],,0) -> Mohit Mishra | I11: Will Pay Next Week | J11: =IF(OR(Table3[[#This Row],[Contact_Result]]="Commitment Received",Table3[[#This Row],[Contact_Result]]="Will Pay Next Week"),"Yes","") -> Yes | K11: 46178 | L11: 3179 | M11: 0 | N11: Will Pay Next Week
A12: LOG00435 | B12: CUST0407 | C12: =_xlfn.XLOOKUP(Table3[[#This Row],[Customer_ID]],Table1[Customer_ID],Table1[Customer_Name],,0) -> Rekha Chauhan | D12: =_xlfn.XLOOKUP(Table3[[#This Row],[Customer_ID]],Table1[Customer_ID],Table1[Branch_Name],,0) -> Gwalior | E12: 46173 | F12: Tele-Call | G12: AG017 | H12: =_xlfn.XLOOKUP(Table3[[#This Row],[Agent_Code]],Table4[Agent_Code],Table4[Agent_Name],,0) -> Naresh Mishra | I12: Not Reachable | J12: =IF(OR(Table3[[#This Row],[Contact_Result]]="Commitment Received",Table3[[#This Row],[Contact_Result]]="Will Pay Next Week"),"Yes","") | M12: 0 | N12: Not Reachable
A13: LOG00457 | B13: CUST0424 | C13: =_xlfn.XLOOKUP(Table3[[#This Row],[Customer_ID]],Table1[Customer_ID],Table1[Customer_Name],,0) -> Manoj Sharma | D13: =_xlfn.XLOOKUP(Table3[[#This Row],[Customer_ID]],Table1[Customer_ID],Table1[Branch_Name],,0) -> Jabalpur | E13: 46173 | F13: Tele-Call | G13: AG004 | H13: =_xlfn.XLOOKUP(Table3[[#This Row],[Agent_Code]],Table4[Agent_Code],Table4[Agent_Name],,0) -> Pankaj Verma | I13: Not Reachable | J13: =IF(OR(Table3[[#This Row],[Contact_Result]]="Commitment Received",Table3[[#This Row],[Contact_Result]]="Will Pay Next Week"),"Yes","") | M13: 0 | N13: Not Reachable
A14: LOG00458 | B14: CUST0424 | C14: =_xlfn.XLOOKUP(Table3[[#This Row],[Customer_ID]],Table1[Customer_ID],Table1[Customer_Name],,0) -> Manoj Sharma | D14: =_xlfn.XLOOKUP(Table3[[#This Row],[Customer_ID]],Table1[Customer_ID],Table1[Branch_Name],,0) -> Jabalpur | E14: 46173 | F14: WhatsApp Message | G14: AG004 | H14: =_xlfn.XLOOKUP(Table3[[#This Row],[Agent_Code]],Table4[Agent_Code],Table4[Agent_Name],,0) -> Pankaj Verma | I14: Will Pay Next Week | J14: =IF(OR(Table3[[#This Row],[Contact_Result]]="Commitment Received",Table3[[#This Row],[Contact_Result]]="Will Pay Next Week"),"Yes","") -> Yes | K14: 46178 | L14: 2646 | M14: 0 | N14: Will Pay Next Week
A15: LOG00025 | B15: CUST0017 | C15: =_xlfn.XLOOKUP(Table3[[#This Row],[Customer_ID]],Table1[Customer_ID],Table1[Customer_Name],,0) -> Lata Gupta | D15: =_xlfn.XLOOKUP(Table3[[#This Row],[Customer_ID]],Table1[Customer_ID],Table1[Branch_Name],,0) -> Gwalior | E15: 46172 | F15: Tele-Call | G15: AG016 | H15: =_xlfn.XLOOKUP(Table3[[#This Row],[Agent_Code]],Table4[Agent_Code],Table4[Agent_Name],,0) -> Rekha Gupta | I15: Commitment Received | J15: =IF(OR(Table3[[#This Row],[Contact_Result]]="Commitment Received",Table3[[#This Row],[Contact_Result]]="Will Pay Next Week"),"Yes","") -> Yes | K15: 46177 | L15: 406 | M15: 0 | N15: Commitment Received
A16: LOG00076 | B16: CUST0060 | C16: =_xlfn.XLOOKUP(Table3[[#This Row],[Customer_ID]],Table1[Customer_ID],Table1[Customer_Name],,0) -> Mamta Shukla | D16: =_xlfn.XLOOKUP(Table3[[#This Row],[Customer_ID]],Table1[Customer_ID],Table1[Branch_Name],,0) -> Indore | E16: 46172 | F16: Tele-Call | G16: AG012 | H16: =_xlfn.XLOOKUP(Table3[[#This Row],[Agent_Code]],Table4[Agent_Code],Table4[Agent_Name],,0) -> Umesh Soni | I16: Not Reachable | J16: =IF(OR(Table3[[#This Row],[Contact_Result]]="Commitment Received",Table3[[#This Row],[Contact_Result]]="Will Pay Next Week"),"Yes","") | M16: 0 | N16: Not Reachable
A17: LOG00091 | B17: CUST0072 | C17: =_xlfn.XLOOKUP(Table3[[#This Row],[Customer_ID]],Table1[Customer_ID],Table1[Customer_Name],,0) -> Suresh Thakur | D17: =_xlfn.XLOOKUP(Table3[[#This Row],[Customer_ID]],Table1[Customer_ID],Table1[Branch_Name],,0) -> Rewa | E17: 46172 | F17: Field Visit | G17: AG012 | H17: =_xlfn.XLOOKUP(Table3[[#This Row],[Agent_Code]],Table4[Agent_Code],Table4[Agent_Name],,0) -> Umesh Soni | I17: Part Payment Done | J17: =IF(OR(Table3[[#This Row],[Contact_Result]]="Commitment Received",Table3[[#This Row],[Contact_Result]]="Will Pay Next Week"),"Yes","") | M17: 6121 | N17: Part Payment Done
A18: LOG00114 | B18: CUST0112 | C18: =_xlfn.XLOOKUP(Table3[[#This Row],[Customer_ID]],Table1[Customer_ID],Table1[Customer_Name],,0) -> Vijay Pandey | D18: =_xlfn.XLOOKUP(Table3[[#This Row],[Customer_ID]],Table1[Customer_ID],Table1[Branch_Name],,0) -> Bhopal | E18: 46172 | F18: WhatsApp Message | G18: AG008 | H18: =_xlfn.XLOOKUP(Table3[[#This Row],[Agent_Code]],Table4[Agent_Code],Table4[Agent_Name],,0) -> Pooja Shukla | I18: Will Pay Next Week | J18: =IF(OR(Table3[[#This Row],[Contact_Result]]="Commitment Received",Table3[[#This Row],[Contact_Result]]="Will Pay Next Week"),"Yes","") -> Yes | K18: 46177 | L18: 2726 | M18: 0 | N18: Will Pay Next Week
A19: LOG00130 | B19: CUST0122 | C19: =_xlfn.XLOOKUP(Table3[[#This Row],[Customer_ID]],Table1[Customer_ID],Table1[Customer_Name],,0) -> Santosh Malviya | D19: =_xlfn.XLOOKUP(Table3[[#This Row],[Customer_ID]],Table1[Customer_ID],Table1[Branch_Name],,0) -> Indore | E19: 46172 | F19: WhatsApp Message | G19: AG010 | H19: =_xlfn.XLOOKUP(Table3[[#This Row],[Agent_Code]],Table4[Agent_Code],Table4[Agent_Name],,0) -> Kavita Tiwari | I19: Will Pay Next Week | J19: =IF(OR(Table3[[#This Row],[Contact_Result]]="Commitment Received",Table3[[#This Row],[Contact_Result]]="Will Pay Next Week"),"Yes","") -> Yes | K19: 46177 | L19: 6329 | M19: 0 | N19: Will Pay Next Week
A20: LOG00201 | B20: CUST0192 | C20: =_xlfn.XLOOKUP(Table3[[#This Row],[Customer_ID]],Table1[Customer_ID],Table1[Customer_Name],,0) -> Ajay Pandey | D20: =_xlfn.XLOOKUP(Table3[[#This Row],[Customer_ID]],Table1[Customer_ID],Table1[Branch_Name],,0) -> Rewa | E20: 46172 | F20: Tele-Call | G20: AG014 | H20: =_xlfn.XLOOKUP(Table3[[#This Row],[Agent_Code]],Table4[Agent_Code],Table4[Agent_Name],,0) -> Manoj Gupta | I20: Commitment Received | J20: =IF(OR(Table3[[#This Row],[Contact_Result]]="Commitment Received",Table3[[#This Row],[Contact_Result]]="Will Pay Next Week"),"Yes","") -> Yes | K20: 46177 | L20: 21193 | M20: 0 | N20: Commitment Received
A21: LOG00253 | B21: CUST0229 | C21: =_xlfn.XLOOKUP(Table3[[#This Row],[Customer_ID]],Table1[Customer_ID],Table1[Customer_Name],,0) -> Vikas Malviya | D21: =_xlfn.XLOOKUP(Table3[[#This Row],[Customer_ID]],Table1[Customer_ID],Table1[Branch_Name],,0) -> Indore | E21: 46172 | F21: WhatsApp Message | G21: AG013 | H21: =_xlfn.XLOOKUP(Table3[[#This Row],[Agent_Code]],Table4[Agent_Code],Table4[Agent_Name],,0) -> Neha Malviya | I21: Will Pay Next Week | J21: =IF(OR(Table3[[#This Row],[Contact_Result]]="Commitment Received",Table3[[#This Row],[Contact_Result]]="Will Pay Next Week"),"Yes","") -> Yes | K21: 46177 | L21: 6037 | M21: 0 | N21: Will Pay Next Week
A22: LOG00275 | B22: CUST0254 | C22: =_xlfn.XLOOKUP(Table3[[#This Row],[Customer_ID]],Table1[Customer_ID],Table1[Customer_Name],,0) -> Sumit Jain | D22: =_xlfn.XLOOKUP(Table3[[#This Row],[Customer_ID]],Table1[Customer_ID],Table1[Branch_Name],,0) -> Indore | E22: 46172 | F22: Tele-Call | G22: AG003 | H22: =_xlfn.XLOOKUP(Table3[[#This Row],[Agent_Code]],Table4[Agent_Code],Table4[Agent_Name],,0) -> Pushpa Gupta | I22: Commitment Received | J22: =IF(OR(Table3[[#This Row],[Contact_Result]]="Commitment Received",Table3[[#This Row],[Contact_Result]]="Will Pay Next Week"),"Yes","") -> Yes | K22: 46177 | L22: 1552 | M22: 0 | N22: Commitment Received
A23: LOG00279 | B23: CUST0257 | C23: =_xlfn.XLOOKUP(Table3[[#This Row],[Customer_ID]],Table1[Customer_ID],Table1[Customer_Name],,0) -> Naresh Dwivedi | D23: =_xlfn.XLOOKUP(Table3[[#This Row],[Customer_ID]],Table1[Customer_ID],Table1[Branch_Name],,0) -> Rewa | E23: 46172 | F23: Tele-Call | G23: AG016 | H23: =_xlfn.XLOOKUP(Table3[[#This Row],[Agent_Code]],Table4[Agent_Code],Table4[Agent_Name],,0) -> Rekha Gupta | I23: Commitment Received | J23: =IF(OR(Table3[[#This Row],[Contact_Result]]="Commitment Received",Table3[[#This Row],[Contact_Result]]="Will Pay Next Week"),"Yes","") -> Yes | K23: 46177 | L23: 34079 | M23: 0 | N23: Commitment Received
A24: LOG00404 | B24: CUST0389 | C24: =_xlfn.XLOOKUP(Table3[[#This Row],[Customer_ID]],Table1[Customer_ID],Table1[Customer_Name],,0) -> Manoj Tiwari | D24: =_xlfn.XLOOKUP(Table3[[#This Row],[Customer_ID]],Table1[Customer_ID],Table1[Branch_Name],,0) -> Bhopal | E24: 46172 | F24: Tele-Call | G24: AG018 | H24: =_xlfn.XLOOKUP(Table3[[#This Row],[Agent_Code]],Table4[Agent_Code],Table4[Agent_Name],,0) -> Manoj Dubey | I24: Commitment Received | J24: =IF(OR(Table3[[#This Row],[Contact_Result]]="Commitment Received",Table3[[#This Row],[Contact_Result]]="Will Pay Next Week"),"Yes","") -> Yes | K24: 46177 | L24: 28721 | M24: 0 | N24: Commitment Received
A25: LOG00503 | B25: CUST0461 | C25: =_xlfn.XLOOKUP(Table3[[#This Row],[Customer_ID]],Table1[Customer_ID],Table1[Customer_Name],,0) -> Sunita Shukla | D25: =_xlfn.XLOOKUP(Table3[[#This Row],[Customer_ID]],Table1[Customer_ID],Table1[Branch_Name],,0) -> Indore | E25: 46172 | F25: Field Visit | G25: AG010 | H25: =_xlfn.XLOOKUP(Table3[[#This Row],[Agent_Code]],Table4[Agent_Code],Table4[Agent_Name],,0) -> Kavita Tiwari | I25: Part Payment Done | J25: =IF(OR(Table3[[#This Row],[Contact_Result]]="Commitment Received",Table3[[#This Row],[Contact_Result]]="Will Pay Next Week"),"Yes","") | M25: 3000 | N25: Part Payment Done
A26: LOG00048 | B26: CUST0036 | C26: =_xlfn.XLOOKUP(Table3[[#This Row],[Customer_ID]],Table1[Customer_ID],Table1[Customer_Name],,0) -> Savita Chauhan | D26: =_xlfn.XLOOKUP(Table3[[#This Row],[Customer_ID]],Table1[Customer_ID],Table1[Branch_Name],,0) -> Jabalpur | E26: 46171 | F26: WhatsApp Message | G26: AG018 | H26: =_xlfn.XLOOKUP(Table3[[#This Row],[Agent_Code]],Table4[Agent_Code],Table4[Agent_Name],,0) -> Manoj Dubey | I26: Will Pay Next Week | J26: =IF(OR(Table3[[#This Row],[Contact_Result]]="Commitment Received",Table3[[#This Row],[Contact_Result]]="Will Pay Next Week"),"Yes","") -> Yes | K26: 46176 | L26: 20823 | M26: 0 | N26: Will Pay Next Week
A27: LOG00079 | B27: CUST0060 | C27: =_xlfn.XLOOKUP(Table3[[#This Row],[Customer_ID]],Table1[Customer_ID],Table1[Customer_Name],,0) -> Mamta Shukla | D27: =_xlfn.XLOOKUP(Table3[[#This Row],[Customer_ID]],Table1[Customer_ID],Table1[Branch_Name],,0) -> Indore | E27: 46171 | F27: Field Visit | G27: AG006 | H27: =_xlfn.XLOOKUP(Table3[[#This Row],[Agent_Code]],Table4[Agent_Code],Table4[Agent_Name],,0) -> Suresh Malviya | I27: Part Payment Done | J27: =IF(OR(Table3[[#This Row],[Contact_Result]]="Commitment Received",Table3[[#This Row],[Contact_Result]]="Will Pay Next Week"),"Yes","") | M27: 1924 | N27: Part Payment Done
A28: LOG00102 | B28: CUST0093 | C28: =_xlfn.XLOOKUP(Table3[[#This Row],[Customer_ID]],Table1[Customer_ID],Table1[Customer_Name],,0) -> Vijay Dubey | D28: =_xlfn.XLOOKUP(Table3[[#This Row],[Customer_ID]],Table1[Customer_ID],Table1[Branch_Name],,0) -> Jabalpur | E28: 46171 | F28: WhatsApp Message | G28: AG009 | H28: =_xlfn.XLOOKUP(Table3[[#This Row],[Agent_Code]],Table4[Agent_Code],Table4[Agent_Name],,0) -> Pankaj Joshi | I28: Will Pay Next Week | J28: =IF(OR(Table3[[#This Row],[Contact_Result]]="Commitment Received",Table3[[#This Row],[Contact_Result]]="Will Pay Next Week"),"Yes","") -> Yes | K28: 46176 | L28: 2676 | M28: 0 | N28: Will Pay Next Week
A29: LOG00103 | B29: CUST0093 | C29: =_xlfn.XLOOKUP(Table3[[#This Row],[Customer_ID]],Table1[Customer_ID],Table1[Customer_Name],,0) -> Vijay Dubey | D29: =_xlfn.XLOOKUP(Table3[[#This Row],[Customer_ID]],Table1[Customer_ID],Table1[Branch_Name],,0) -> Jabalpur | E29: 46171 | F29: Tele-Call | G29: AG007 | H29: =_xlfn.XLOOKUP(Table3[[#This Row],[Agent_Code]],Table4[Agent_Code],Table4[Agent_Name],,0) -> Pushpa Jain | I29: Commitment Received | J29: =IF(OR(Table3[[#This Row],[Contact_Result]]="Commitment Received",Table3[[#This Row],[Contact_Result]]="Will Pay Next Week"),"Yes","") -> Yes | K29: 46176 | L29: 2676 | M29: 0 | N29: Commitment Received
A30: LOG00165 | B30: CUST0159 | C30: =_xlfn.XLOOKUP(Table3[[#This Row],[Customer_ID]],Table1[Customer_ID],Table1[Customer_Name],,0) -> Sanjay Malviya | D30: =_xlfn.XLOOKUP(Table3[[#This Row],[Customer_ID]],Table1[Customer_ID],Table1[Branch_Name],,0) -> Rewa | E30: 46171 | F30: WhatsApp Message | G30: AG018 | H30: =_xlfn.XLOOKUP(Table3[[#This Row],[Agent_Code]],Table4[Agent_Code],Table4[Agent_Name],,0) -> Manoj Dubey | I30: Will Pay Next Week | J30: =IF(OR(Table3[[#This Row],[Contact_Result]]="Commitment Received",Table3[[#This Row],[Contact_Result]]="Will Pay Next Week"),"Yes","") -> Yes | K30: 46176 | L30: 1227 | M30: 0 | N30: Will Pay Next Week
A31: LOG00176 | B31: CUST0174 | C31: =_xlfn.XLOOKUP(Table3[[#This Row],[Customer_ID]],Table1[Customer_ID],Table1[Customer_Name],,0) -> Asha Malviya | D31: =_xlfn.XLOOKUP(Table3[[#This Row],[Customer_ID]],Table1[Customer_ID],Table1[Branch_Name],,0) -> Gwalior | E31: 46171 | F31: Tele-Call | G31: AG018 | H31: =_xlfn.XLOOKUP(Table3[[#This Row],[Agent_Code]],Table4[Agent_Code],Table4[Agent_Name],,0) -> Manoj Dubey | I31: Not Reachable | J31: =IF(OR(Table3[[#This Row],[Contact_Result]]="Commitment Received",Table3[[#This Row],[Contact_Result]]="Will Pay Next Week"),"Yes","") | M31: 0 | N31: Not Reachable
A32: LOG00191 | B32: CUST0185 | C32: =_xlfn.XLOOKUP(Table3[[#This Row],[Customer_ID]],Table1[Customer_ID],Table1[Customer_Name],,0) -> Sumit Tiwari | D32: =_xlfn.XLOOKUP(Table3[[#This Row],[Customer_ID]],Table1[Customer_ID],Table1[Branch_Name],,0) -> Gwalior | E32: 46171 | F32: Tele-Call | G32: AG010 | H32: =_xlfn.XLOOKUP(Table3[[#This Row],[Agent_Code]],Table4[Agent_Code],Table4[Agent_Name],,0) -> Kavita Tiwari | I32: Commitment Received | J32: =IF(OR(Table3[[#This Row],[Contact_Result]]="Commitment Received",Table3[[#This Row],[Contact_Result]]="Will Pay Next Week"),"Yes","") -> Yes | K32: 46176 | L32: 6224 | M32: 0 | N32: Commitment Received
A33: LOG00213 | B33: CUST0207 | C33: =_xlfn.XLOOKUP(Table3[[#This Row],[Customer_ID]],Table1[Customer_ID],Table1[Customer_Name],,0) -> Kavita Agarwal | D33: =_xlfn.XLOOKUP(Table3[[#This Row],[Customer_ID]],Table1[Customer_ID],Table1[Branch_Name],,0) -> Indore | E33: 46171 | F33: WhatsApp Message | G33: AG001 | H33: =_xlfn.XLOOKUP(Table3[[#This Row],[Agent_Code]],Table4[Agent_Code],Table4[Agent_Name],,0) -> Mohit Mishra | I33: Will Pay Next Week | J33: =IF(OR(Table3[[#This Row],[Contact_Result]]="Commitment Received",Table3[[#This Row],[Contact_Result]]="Will Pay Next Week"),"Yes","") -> Yes | K33: 46176 | L33: 48786 | M33: 0 | N33: Will Pay Next Week
A34: LOG00220 | B34: CUST0209 | C34: =_xlfn.XLOOKUP(Table3[[#This Row],[Customer_ID]],Table1[Customer_ID],Table1[Customer_Name],,0) -> Santosh Soni | D34: =_xlfn.XLOOKUP(Table3[[#This Row],[Customer_ID]],Table1[Customer_ID],Table1[Branch_Name],,0) -> Bhopal | E34: 46171 | F34: Tele-Call | G34: AG008 | H34: =_xlfn.XLOOKUP(Table3[[#This Row],[Agent_Code]],Table4[Agent_Code],Table4[Agent_Name],,0) -> Pooja Shukla | I34: Not Reachable | J34: =IF(OR(Table3[[#This Row],[Contact_Result]]="Commitment Received",Table3[[#This Row],[Contact_Result]]="Will Pay Next Week"),"Yes","") | M34: 0 | N34: Not Reachable
A35: LOG00242 | B35: CUST0219 | C35: =_xlfn.XLOOKUP(Table3[[#This Row],[Customer_ID]],Table1[Customer_ID],Table1[Customer_Name],,0) -> Ramesh Rajput | D35: =_xlfn.XLOOKUP(Table3[[#This Row],[Customer_ID]],Table1[Customer_ID],Table1[Branch_Name],,0) -> Indore | E35: 46171 | F35: Field Visit | G35: AG014 | H35: =_xlfn.XLOOKUP(Table3[[#This Row],[Agent_Code]],Table4[Agent_Code],Table4[Agent_Name],,0) -> Manoj Gupta | I35: Part Payment Done | J35: =IF(OR(Table3[[#This Row],[Contact_Result]]="Commitment Received",Table3[[#This Row],[Contact_Result]]="Will Pay Next Week"),"Yes","") | M35: 2634 | N35: Part Payment Done
A36: LOG00256 | B36: CUST0232 | C36: =_xlfn.XLOOKUP(Table3[[#This Row],[Customer_ID]],Table1[Customer_ID],Table1[Customer_Name],,0) -> Pankaj Joshi | D36: =_xlfn.XLOOKUP(Table3[[#This Row],[Customer_ID]],Table1[Customer_ID],Table1[Branch_Name],,0) -> Gwalior | E36: 46171 | F36: Tele-Call | G36: AG011 | H36: =_xlfn.XLOOKUP(Table3[[#This Row],[Agent_Code]],Table4[Agent_Code],Table4[Agent_Name],,0) -> Umesh Gupta | I36: Not Reachable | J36: =IF(OR(Table3[[#This Row],[Contact_Result]]="Commitment Received",Table3[[#This Row],[Contact_Result]]="Will Pay Next Week"),"Yes","") | M36: 0 | N36: Not Reachable
A37: LOG00285 | B37: CUST0265 | C37: =_xlfn.XLOOKUP(Table3[[#This Row],[Customer_ID]],Table1[Customer_ID],Table1[Customer_Name],,0) -> Suresh Sharma | D37: =_xlfn.XLOOKUP(Table3[[#This Row],[Customer_ID]],Table1[Customer_ID],Table1[Branch_Name],,0) -> Gwalior | E37: 46171 | F37: Tele-Call | G37: AG004 | H37: =_xlfn.XLOOKUP(Table3[[#This Row],[Agent_Code]],Table4[Agent_Code],Table4[Agent_Name],,0) -> Pankaj Verma | I37: Not Reachable | J37: =IF(OR(Table3[[#This Row],[Contact_Result]]="Commitment Received",Table3[[#This Row],[Contact_Result]]="Will Pay Next Week"),"Yes","") | M37: 0 | N37: Not Reachable
A38: LOG00300 | B38: CUST0279 | C38: =_xlfn.XLOOKUP(Table3[[#This Row],[Customer_ID]],Table1[Customer_ID],Table1[Customer_Name],,0) -> Pradeep Agarwal | D38: =_xlfn.XLOOKUP(Table3[[#This Row],[Customer_ID]],Table1[Customer_ID],Table1[Branch_Name],,0) -> Bhopal | E38: 46171 | F38: Tele-Call | G38: AG010 | H38: =_xlfn.XLOOKUP(Table3[[#This Row],[Agent_Code]],Table4[Agent_Code],Table4[Agent_Name],,0) -> Kavita Tiwari | I38: Not Reachable | J38: =IF(OR(Table3[[#This Row],[Contact_Result]]="Commitment Received",Table3[[#This Row],[Contact_Result]]="Will Pay Next Week"),"Yes","") | M38: 0 | N38: Not Reachable
A39: LOG00320 | B39: CUST0300 | C39: =_xlfn.XLOOKUP(Table3[[#This Row],[Customer_ID]],Table1[Customer_ID],Table1[Customer_Name],,0) -> Pradeep Yadav | D39: =_xlfn.XLOOKUP(Table3[[#This Row],[Customer_ID]],Table1[Customer_ID],Table1[Branch_Name],,0) -> Gwalior | E39: 46171 | F39: Tele-Call | G39: AG006 | H39: =_xlfn.XLOOKUP(Table3[[#This Row],[Agent_Code]],Table4[Agent_Code],Table4[Agent_Name],,0) -> Suresh Malviya | I39: Commitment Received | J39: =IF(OR(Table3[[#This Row],[Contact_Result]]="Commitment Received",Table3[[#This Row],[Contact_Result]]="Will Pay Next Week"),"Yes","") -> Yes | K39: 46176 | L39: 3179 | M39: 0 | N39: Commitment Received
A40: LOG00331 | B40: CUST0311 | C40: =_xlfn.XLOOKUP(Table3[[#This Row],[Customer_ID]],Table1[Customer_ID],Table1[Customer_Name],,0) -> Vijay Mishra | D40: =_xlfn.XLOOKUP(Table3[[#This Row],[Customer_ID]],Table1[Customer_ID],Table1[Branch_Name],,0) -> Gwalior | E40: 46171 | F40: WhatsApp Message | G40: AG020 | H40: =_xlfn.XLOOKUP(Table3[[#This Row],[Agent_Code]],Table4[Agent_Code],Table4[Agent_Name],,0) -> Vijay Tiwari | I40: Will Pay Next Week | J40: =IF(OR(Table3[[#This Row],[Contact_Result]]="Commitment Received",Table3[[#This Row],[Contact_Result]]="Will Pay Next Week"),"Yes","") -> Yes | K40: 46176 | L40: 235 | M40: 0 | N40: Will Pay Next Week
A41: LOG00359 | B41: CUST0350 | C41: =_xlfn.XLOOKUP(Table3[[#This Row],[Customer_ID]],Table1[Customer_ID],Table1[Customer_Name],,0) -> Sanjay Chauhan | D41: =_xlfn.XLOOKUP(Table3[[#This Row],[Customer_ID]],Table1[Customer_ID],Table1[Branch_Name],,0) -> Rewa | E41: 46171 | F41: Field Visit | G41: AG013 | H41: =_xlfn.XLOOKUP(Table3[[#This Row],[Agent_Code]],Table4[Agent_Code],Table4[Agent_Name],,0) -> Neha Malviya | I41: Part Payment Done | J41: =IF(OR(Table3[[#This Row],[Contact_Result]]="Commitment Received",Table3[[#This Row],[Contact_Result]]="Will Pay Next Week"),"Yes","") | M41: 4972 | N41: Part Payment Done
A42: LOG00374 | B42: CUST0356 | C42: =_xlfn.XLOOKUP(Table3[[#This Row],[Customer_ID]],Table1[Customer_ID],Table1[Customer_Name],,0) -> Vikas Malviya | D42: =_xlfn.XLOOKUP(Table3[[#This Row],[Customer_ID]],Table1[Customer_ID],Table1[Branch_Name],,0) -> Indore | E42: 46171 | F42: Field Visit | G42: AG002 | H42: =_xlfn.XLOOKUP(Table3[[#This Row],[Agent_Code]],Table4[Agent_Code],Table4[Agent_Name],,0) -> Sunita Patel | I42: Part Payment Done | J42: =IF(OR(Table3[[#This Row],[Contact_Result]]="Commitment Received",Table3[[#This Row],[Contact_Result]]="Will Pay Next Week"),"Yes","") | M42: 1606 | N42: Part Payment Done
A43: LOG00392 | B43: CUST0380 | C43: =_xlfn.XLOOKUP(Table3[[#This Row],[Customer_ID]],Table1[Customer_ID],Table1[Customer_Name],,0) -> Umesh Shukla | D43: =_xlfn.XLOOKUP(Table3[[#This Row],[Customer_ID]],Table1[Customer_ID],Table1[Branch_Name],,0) -> Bhopal | E43: 46171 | F43: Field Visit | G43: AG016 | H43: =_xlfn.XLOOKUP(Table3[[#This Row],[Agent_Code]],Table4[Agent_Code],Table4[Agent_Name],,0) -> Rekha Gupta | I43: Part Payment Done | J43: =IF(OR(Table3[[#This Row],[Contact_Result]]="Commitment Received",Table3[[#This Row],[Contact_Result]]="Will Pay Next Week"),"Yes","") | M43: 2441 | N43: Part Payment Done
A44: LOG00406 | B44: CUST0393 | C44: =_xlfn.XLOOKUP(Table3[[#This Row],[Customer_ID]],Table1[Customer_ID],Table1[Customer_Name],,0) -> Rajesh Malviya | D44: =_xlfn.XLOOKUP(Table3[[#This Row],[Customer_ID]],Table1[Customer_ID],Table1[Branch_Name],,0) -> Bhopal | E44: 46171 | F44: Tele-Call | G44: AG010 | H44: =_xlfn.XLOOKUP(Table3[[#This Row],[Agent_Code]],Table4[Agent_Code],Table4[Agent_Name],,0) -> Kavita Tiwari | I44: Not Reachable | J44: =IF(OR(Table3[[#This Row],[Contact_Result]]="Commitment Received",Table3[[#This Row],[Contact_Result]]="Will Pay Next Week"),"Yes","") | M44: 0 | N44: Not Reachable
A45: LOG00475 | B45: CUST0444 | C45: =_xlfn.XLOOKUP(Table3[[#This Row],[Customer_ID]],Table1[Customer_ID],Table1[Customer_Name],,0) -> Renu Joshi | D45: =_xlfn.XLOOKUP(Table3[[#This Row],[Customer_ID]],Table1[Customer_ID],Table1[Branch_Name],,0) -> Indore | E45: 46171 | F45: Tele-Call | G45: AG011 | H45: =_xlfn.XLOOKUP(Table3[[#This Row],[Agent_Code]],Table4[Agent_Code],Table4[Agent_Name],,0) -> Umesh Gupta | I45: Not Reachable | J45: =IF(OR(Table3[[#This Row],[Contact_Result]]="Commitment Received",Table3[[#This Row],[Contact_Result]]="Will Pay Next Week"),"Yes","") | M45: 0 | N45: Not Reachable
A46: LOG00509 | B46: CUST0469 | C46: =_xlfn.XLOOKUP(Table3[[#This Row],[Customer_ID]],Table1[Customer_ID],Table1[Customer_Name],,0) -> Ramesh Thakur | D46: =_xlfn.XLOOKUP(Table3[[#This Row],[Customer_ID]],Table1[Customer_ID],Table1[Branch_Name],,0) -> Gwalior | E46: 46171 | F46: WhatsApp Message | G46: AG013 | H46: =_xlfn.XLOOKUP(Table3[[#This Row],[Agent_Code]],Table4[Agent_Code],Table4[Agent_Name],,0) -> Neha Malviya | I46: Will Pay Next Week | J46: =IF(OR(Table3[[#This Row],[Contact_Result]]="Commitment Received",Table3[[#This Row],[Contact_Result]]="Will Pay Next Week"),"Yes","") -> Yes | K46: 46176 | L46: 5059 | M46: 0 | N46: Will Pay Next Week
A47: LOG00039 | B47: CUST0028 | C47: =_xlfn.XLOOKUP(Table3[[#This Row],[Customer_ID]],Table1[Customer_ID],Table1[Customer_Name],,0) -> Renu Dubey | D47: =_xlfn.XLOOKUP(Table3[[#This Row],[Customer_ID]],Table1[Customer_ID],Table1[Branch_Name],,0) -> Bhopal | E47: 46170 | F47: WhatsApp Message | G47: AG018 | H47: =_xlfn.XLOOKUP(Table3[[#This Row],[Agent_Code]],Table4[Agent_Code],Table4[Agent_Name],,0) -> Manoj Dubey | I47: Will Pay Next Week | J47: =IF(OR(Table3[[#This Row],[Contact_Result]]="Commitment Received",Table3[[#This Row],[Contact_Result]]="Will Pay Next Week"),"Yes","") -> Yes | K47: 46175 | L47: 3026 | M47: 0 | N47: Will Pay Next Week
A48: LOG00064 | B48: CUST0049 | C48: =_xlfn.XLOOKUP(Table3[[#This Row],[Customer_ID]],Table1[Customer_ID],Table1[Customer_Name],,0) -> Sanjay Singh | D48: =_xlfn.XLOOKUP(Table3[[#This Row],[Customer_ID]],Table1[Customer_ID],Table1[Branch_Name],,0) -> Indore | E48: 46170 | F48: Tele-Call | G48: AG003 | H48: =_xlfn.XLOOKUP(Table3[[#This Row],[Agent_Code]],Table4[Agent_Code],Table4[Agent_Name],,0) -> Pushpa Gupta | I48: Not Reachable | J48: =IF(OR(Table3[[#This Row],[Contact_Result]]="Commitment Received",Table3[[#This Row],[Contact_Result]]="Will Pay Next Week"),"Yes","") | M48: 0 | N48: Not Reachable
A49: LOG00125 | B49: CUST0118 | C49: =_xlfn.XLOOKUP(Table3[[#This Row],[Customer_ID]],Table1[Customer_ID],Table1[Customer_Name],,0) -> Mahesh Patel | D49: =_xlfn.XLOOKUP(Table3[[#This Row],[Customer_ID]],Table1[Customer_ID],Table1[Branch_Name],,0) -> Gwalior | E49: 46170 | F49: Tele-Call | G49: AG004 | H49: =_xlfn.XLOOKUP(Table3[[#This Row],[Agent_Code]],Table4[Agent_Code],Table4[Agent_Name],,0) -> Pankaj Verma | I49: Not Reachable | J49: =IF(OR(Table3[[#This Row],[Contact_Result]]="Commitment Received",Table3[[#This Row],[Contact_Result]]="Will Pay Next Week"),"Yes","") | M49: 0 | N49: Not Reachable
A50: LOG00169 | B50: CUST0163 | C50: =_xlfn.XLOOKUP(Table3[[#This Row],[Customer_ID]],Table1[Customer_ID],Table1[Customer_Name],,0) -> Amit Singh | D50: =_xlfn.XLOOKUP(Table3[[#This Row],[Customer_ID]],Table1[Customer_ID],Table1[Branch_Name],,0) -> Gwalior | E50: 46170 | F50: Tele-Call | G50: AG013 | H50: =_xlfn.XLOOKUP(Table3[[#This Row],[Agent_Code]],Table4[Agent_Code],Table4[Agent_Name],,0) -> Neha Malviya | I50: Commitment Received | J50: =IF(OR(Table3[[#This Row],[Contact_Result]]="Commitment Received",Table3[[#This Row],[Contact_Result]]="Will Pay Next Week"),"Yes","") -> Yes | K50: 46175 | L50: 22146 | M50: 0 | N50: Commitment Received
A51: LOG00346 | B51: CUST0342 | C51: =_xlfn.XLOOKUP(Table3[[#This Row],[Customer_ID]],Table1[Customer_ID],Table1[Customer_Name],,0) -> Sumit Jain | D51: =_xlfn.XLOOKUP(Table3[[#This Row],[Customer_ID]],Table1[Customer_ID],Table1[Branch_Name],,0) -> Bhopal | E51: 46170 | F51: Tele-Call | G51: AG003 | H51: =_xlfn.XLOOKUP(Table3[[#This Row],[Agent_Code]],Table4[Agent_Code],Table4[Agent_Name],,0) -> Pushpa Gupta | I51: Not Reachable | J51: =IF(OR(Table3[[#This Row],[Contact_Result]]="Commitment Received",Table3[[#This Row],[Contact_Result]]="Will Pay Next Week"),"Yes","") | M51: 0 | N51: Not Reachable
A52: LOG00414 | B52: CUST0396 | C52: =_xlfn.XLOOKUP(Table3[[#This Row],[Customer_ID]],Table1[Customer_ID],Table1[Customer_Name],,0) -> Pushpa Tiwari | D52: =_xlfn.XLOOKUP(Table3[[#This Row],[Customer_ID]],Table1[Customer_ID],Table1[Branch_Name],,0) -> Gwalior | E52: 46170 | F52: Tele-Call | G52: AG019 | H52: =_xlfn.XLOOKUP(Table3[[#This Row],[Agent_Code]],Table4[Agent_Code],Table4[Agent_Name],,0) -> Ajay Yadav | I52: Commitment Received | J52: =IF(OR(Table3[[#This Row],[Contact_Result]]="Commitment Received",Table3[[#This Row],[Contact_Result]]="Will Pay Next Week"),"Yes","") -> Yes | K52: 46175 | L52: 3614 | M52: 0 | N52: Commitment Received
A53: LOG00479 | B53: CUST0448 | C53: =_xlfn.XLOOKUP(Table3[[#This Row],[Customer_ID]],Table1[Customer_ID],Table1[Customer_Name],,0) -> Mahesh Sharma | D53: =_xlfn.XLOOKUP(Table3[[#This Row],[Customer_ID]],Table1[Customer_ID],Table1[Branch_Name],,0) -> Jabalpur | E53: 46170 | F53: WhatsApp Message | G53: AG019 | H53: =_xlfn.XLOOKUP(Table3[[#This Row],[Agent_Code]],Table4[Agent_Code],Table4[Agent_Name],,0) -> Ajay Yadav | I53: Will Pay Next Week | J53: =IF(OR(Table3[[#This Row],[Contact_Result]]="Commitment Received",Table3[[#This Row],[Contact_Result]]="Will Pay Next Week"),"Yes","") -> Yes | K53: 46175 | L53: 1319 | M53: 0 | N53: Will Pay Next Week
A54: LOG00534 | B54: CUST0489 | C54: =_xlfn.XLOOKUP(Table3[[#This Row],[Customer_ID]],Table1[Customer_ID],Table1[Customer_Name],,0) -> Ramesh Mishra | D54: =_xlfn.XLOOKUP(Table3[[#This Row],[Customer_ID]],Table1[Customer_ID],Table1[Branch_Name],,0) -> Indore | E54: 46170 | F54: Tele-Call | G54: AG017 | H54: =_xlfn.XLOOKUP(Table3[[#This Row],[Agent_Code]],Table4[Agent_Code],Table4[Agent_Name],,0) -> Naresh Mishra | I54: Not Reachable | J54: =IF(OR(Table3[[#This Row],[Contact_Result]]="Commitment Received",Table3[[#This Row],[Contact_Result]]="Will Pay Next Week"),"Yes","") | M54: 0 | N54: Not Reachable
A55: LOG00003 | B55: CUST0001 | C55: =_xlfn.XLOOKUP(Table3[[#This Row],[Customer_ID]],Table1[Customer_ID],Table1[Customer_Name],,0) -> Vijay Mishra | D55: =_xlfn.XLOOKUP(Table3[[#This Row],[Customer_ID]],Table1[Customer_ID],Table1[Branch_Name],,0) -> Indore | E55: 46169 | F55: Tele-Call | G55: AG018 | H55: =_xlfn.XLOOKUP(Table3[[#This Row],[Agent_Code]],Table4[Agent_Code],Table4[Agent_Name],,0) -> Manoj Dubey | I55: Commitment Received | J55: =IF(OR(Table3[[#This Row],[Contact_Result]]="Commitment Received",Table3[[#This Row],[Contact_Result]]="Will Pay Next Week"),"Yes","") -> Yes | K55: 46174 | L55: 1720 | M55: 0 | N55: Commitment Received
A56: LOG00069 | B56: CUST0051 | C56: =_xlfn.XLOOKUP(Table3[[#This Row],[Customer_ID]],Table1[Customer_ID],Table1[Customer_Name],,0) -> Vikas Rajput | D56: =_xlfn.XLOOKUP(Table3[[#This Row],[Customer_ID]],Table1[Customer_ID],Table1[Branch_Name],,0) -> Bhopal | E56: 46169 | F56: WhatsApp Message | G56: AG013 | H56: =_xlfn.XLOOKUP(Table3[[#This Row],[Agent_Code]],Table4[Agent_Code],Table4[Agent_Name],,0) -> Neha Malviya | I56: Will Pay Next Week | J56: =IF(OR(Table3[[#This Row],[Contact_Result]]="Commitment Received",Table3[[#This Row],[Contact_Result]]="Will Pay Next Week"),"Yes","") -> Yes | K56: 46174 | L56: 17235 | M56: 0 | N56: Will Pay Next Week
A57: LOG00077 | B57: CUST0060 | C57: =_xlfn.XLOOKUP(Table3[[#This Row],[Customer_ID]],Table1[Customer_ID],Table1[Customer_Name],,0) -> Mamta Shukla | D57: =_xlfn.XLOOKUP(Table3[[#This Row],[Customer_ID]],Table1[Customer_ID],Table1[Branch_Name],,0) -> Indore | E57: 46169 | F57: WhatsApp Message | G57: AG004 | H57: =_xlfn.XLOOKUP(Table3[[#This Row],[Agent_Code]],Table4[Agent_Code],Table4[Agent_Name],,0) -> Pankaj Verma | I57: Will Pay Next Week | J57: =IF(OR(Table3[[#This Row],[Contact_Result]]="Commitment Received",Table3[[#This Row],[Contact_Result]]="Will Pay Next Week"),"Yes","") -> Yes | K57: 46174 | L57: 1977 | M57: 0 | N57: Will Pay Next Week
A58: LOG00117 | B58: CUST0115 | C58: =_xlfn.XLOOKUP(Table3[[#This Row],[Customer_ID]],Table1[Customer_ID],Table1[Customer_Name],,0) -> Ajay Chauhan | D58: =_xlfn.XLOOKUP(Table3[[#This Row],[Customer_ID]],Table1[Customer_ID],Table1[Branch_Name],,0) -> Rewa | E58: 46169 | F58: Tele-Call | G58: AG009 | H58: =_xlfn.XLOOKUP(Table3[[#This Row],[Agent_Code]],Table4[Agent_Code],Table4[Agent_Name],,0) -> Pankaj Joshi | I58: Not Reachable | J58: =IF(OR(Table3[[#This Row],[Contact_Result]]="Commitment Received",Table3[[#This Row],[Contact_Result]]="Will Pay Next Week"),"Yes","") | M58: 0 | N58: Not Reachable
A59: LOG00189 | B59: CUST0185 | C59: =_xlfn.XLOOKUP(Table3[[#This Row],[Customer_ID]],Table1[Customer_ID],Table1[Customer_Name],,0) -> Sumit Tiwari | D59: =_xlfn.XLOOKUP(Table3[[#This Row],[Customer_ID]],Table1[Customer_ID],Table1[Branch_Name],,0) -> Gwalior | E59: 46169 | F59: Tele-Call | G59: AG013 | H59: =_xlfn.XLOOKUP(Table3[[#This Row],[Agent_Code]],Table4[Agent_Code],Table4[Agent_Name],,0) -> Neha Malviya | I59: Not Reachable | J59: =IF(OR(Table3[[#This Row],[Contact_Result]]="Commitment Received",Table3[[#This Row],[Contact_Result]]="Will Pay Next Week"),"Yes","") | M59: 0 | N59: Not Reachable
A60: LOG00276 | B60: CUST0254 | C60: =_xlfn.XLOOKUP(Table3[[#This Row],[Customer_ID]],Table1[Customer_ID],Table1[Customer_Name],,0) -> Sumit Jain | D60: =_xlfn.XLOOKUP(Table3[[#This Row],[Customer_ID]],Table1[Customer_ID],Table1[Branch_Name],,0) -> Indore | E60: 46169 | F60: Field Visit | G60: AG008 | H60: =_xlfn.XLOOKUP(Table3[[#This Row],[Agent_Code]],Table4[Agent_Code],Table4[Agent_Name],,0) -> Pooja Shukla | I60: Part Payment Done | J60: =IF(OR(Table3[[#This Row],[Contact_Result]]="Commitment Received",Table3[[#This Row],[Contact_Result]]="Will Pay Next Week"),"Yes","") | M60: 1166 | N60: Part Payment Done
A61: LOG00278 | B61: CUST0257 | C61: =_xlfn.XLOOKUP(Table3[[#This Row],[Customer_ID]],Table1[Customer_ID],Table1[Customer_Name],,0) -> Naresh Dwivedi | D61: =_xlfn.XLOOKUP(Table3[[#This Row],[Customer_ID]],Table1[Customer_ID],Table1[Branch_Name],,0) -> Rewa | E61: 46169 | F61: WhatsApp Message | G61: AG016 | H61: =_xlfn.XLOOKUP(Table3[[#This Row],[Agent_Code]],Table4[Agent_Code],Table4[Agent_Name],,0) -> Rekha Gupta | I61: Will Pay Next Week | J61: =IF(OR(Table3[[#This Row],[Contact_Result]]="Commitment Received",Table3[[#This Row],[Contact_Result]]="Will Pay Next Week"),"Yes","") -> Yes | K61: 46174 | L61: 34079 | M61: 0 | N61: Will Pay Next Week
A62: LOG00321 | B62: CUST0301 | C62: =_xlfn.XLOOKUP(Table3[[#This Row],[Customer_ID]],Table1[Customer_ID],Table1[Customer_Name],,0) -> Shanta Yadav | D62: =_xlfn.XLOOKUP(Table3[[#This Row],[Customer_ID]],Table1[Customer_ID],Table1[Branch_Name],,0) -> Bhopal | E62: 46169 | F62: Tele-Call | G62: AG003 | H62: =_xlfn.XLOOKUP(Table3[[#This Row],[Agent_Code]],Table4[Agent_Code],Table4[Agent_Name],,0) -> Pushpa Gupta | I62: Not Reachable | J62: =IF(OR(Table3[[#This Row],[Contact_Result]]="Commitment Received",Table3[[#This Row],[Contact_Result]]="Will Pay Next Week"),"Yes","") | M62: 0 | N62: Not Reachable
A63: LOG00350 | B63: CUST0346 | C63: =_xlfn.XLOOKUP(Table3[[#This Row],[Customer_ID]],Table1[Customer_ID],Table1[Customer_Name],,0) -> Dinesh Sharma | D63: =_xlfn.XLOOKUP(Table3[[#This Row],[Customer_ID]],Table1[Customer_ID],Table1[Branch_Name],,0) -> Rewa | E63: 46169 | F63: WhatsApp Message | G63: AG012 | H63: =_xlfn.XLOOKUP(Table3[[#This Row],[Agent_Code]],Table4[Agent_Code],Table4[Agent_Name],,0) -> Umesh Soni | I63: Will Pay Next Week | J63: =IF(OR(Table3[[#This Row],[Contact_Result]]="Commitment Received",Table3[[#This Row],[Contact_Result]]="Will Pay Next Week"),"Yes","") -> Yes | K63: 46174 | L63: 26634 | M63: 0 | N63: Will Pay Next Week
A64: LOG00401 | B64: CUST0387 | C64: =_xlfn.XLOOKUP(Table3[[#This Row],[Customer_ID]],Table1[Customer_ID],Table1[Customer_Name],,0) -> Neha Malviya | D64: =_xlfn.XLOOKUP(Table3[[#This Row],[Customer_ID]],Table1[Customer_ID],Table1[Branch_Name],,0) -> Bhopal | E64: 46169 | F64: Field Visit | G64: AG007 | H64: =_xlfn.XLOOKUP(Table3[[#This Row],[Agent_Code]],Table4[Agent_Code],Table4[Agent_Name],,0) -> Pushpa Jain | I64: Part Payment Done | J64: =IF(OR(Table3[[#This Row],[Contact_Result]]="Commitment Received",Table3[[#This Row],[Contact_Result]]="Will Pay Next Week"),"Yes","") | M64: 2258 | N64: Part Payment Done
A65: LOG00430 | B65: CUST0405 | C65: =_xlfn.XLOOKUP(Table3[[#This Row],[Customer_ID]],Table1[Customer_ID],Table1[Customer_Name],,0) -> Santosh Agarwal | D65: =_xlfn.XLOOKUP(Table3[[#This Row],[Customer_ID]],Table1[Customer_ID],Table1[Branch_Name],,0) -> Indore | E65: 46169 | F65: WhatsApp Message | G65: AG010 | H65: =_xlfn.XLOOKUP(Table3[[#This Row],[Agent_Code]],Table4[Agent_Code],Table4[Agent_Name],,0) -> Kavita Tiwari | I65: Will Pay Next Week | J65: =IF(OR(Table3[[#This Row],[Contact_Result]]="Commitment Received",Table3[[#This Row],[Contact_Result]]="Will Pay Next Week"),"Yes","") -> Yes | K65: 46174 | L65: 7877 | M65: 0 | N65: Will Pay Next Week
A66: LOG00437 | B66: CUST0407 | C66: =_xlfn.XLOOKUP(Table3[[#This Row],[Customer_ID]],Table1[Customer_ID],Table1[Customer_Name],,0) -> Rekha Chauhan | D66: =_xlfn.XLOOKUP(Table3[[#This Row],[Customer_ID]],Table1[Customer_ID],Table1[Branch_Name],,0) -> Gwalior | E66: 46169 | F66: Tele-Call | G66: AG007 | H66: =_xlfn.XLOOKUP(Table3[[#This Row],[Agent_Code]],Table4[Agent_Code],Table4[Agent_Name],,0) -> Pushpa Jain | I66: Commitment Received | J66: =IF(OR(Table3[[#This Row],[Contact_Result]]="Commitment Received",Table3[[#This Row],[Contact_Result]]="Will Pay Next Week"),"Yes","") -> Yes | K66: 46174 | L66: 24120 | M66: 0 | N66: Commitment Received
A67: LOG00453 | B67: CUST0421 | C67: =_xlfn.XLOOKUP(Table3[[#This Row],[Customer_ID]],Table1[Customer_ID],Table1[Customer_Name],,0) -> Mohit Dubey | D67: =_xlfn.XLOOKUP(Table3[[#This Row],[Customer_ID]],Table1[Customer_ID],Table1[Branch_Name],,0) -> Indore | E67: 46169 | F67: Tele-Call | G67: AG020 | H67: =_xlfn.XLOOKUP(Table3[[#This Row],[Agent_Code]],Table4[Agent_Code],Table4[Agent_Name],,0) -> Vijay Tiwari | I67: Not Reachable | J67: =IF(OR(Table3[[#This Row],[Contact_Result]]="Commitment Received",Table3[[#This Row],[Contact_Result]]="Will Pay Next Week"),"Yes","") | M67: 0 | N67: Not Reachable
A68: LOG00533 | B68: CUST0484 | C68: =_xlfn.XLOOKUP(Table3[[#This Row],[Customer_ID]],Table1[Customer_ID],Table1[Customer_Name],,0) -> Pooja Dwivedi | D68: =_xlfn.XLOOKUP(Table3[[#This Row],[Customer_ID]],Table1[Customer_ID],Table1[Branch_Name],,0) -> Jabalpur | E68: 46169 | F68: Field Visit | G68: AG010 | H68: =_xlfn.XLOOKUP(Table3[[#This Row],[Agent_Code]],Table4[Agent_Code],Table4[Agent_Name],,0) -> Kavita Tiwari | I68: Callback Requested | J68: =IF(OR(Table3[[#This Row],[Contact_Result]]="Commitment Received",Table3[[#This Row],[Contact_Result]]="Will Pay Next Week"),"Yes","") | K68: 46174 | L68: 26517 | M68: 0 | N68: Commitment Broken
A69: LOG00068 | B69: CUST0051 | C69: =_xlfn.XLOOKUP(Table3[[#This Row],[Customer_ID]],Table1[Customer_ID],Table1[Customer_Name],,0) -> Vikas Rajput | D69: =_xlfn.XLOOKUP(Table3[[#This Row],[Customer_ID]],Table1[Customer_ID],Table1[Branch_Name],,0) -> Bhopal | E69: 46168 | F69: Tele-Call | G69: AG007 | H69: =_xlfn.XLOOKUP(Table3[[#This Row],[Agent_Code]],Table4[Agent_Code],Table4[Agent_Name],,0) -> Pushpa Jain | I69: Not Reachable | J69: =IF(OR(Table3[[#This Row],[Contact_Result]]="Commitment Received",Table3[[#This Row],[Contact_Result]]="Will Pay Next Week"),"Yes","") | M69: 0 | N69: Not Reachable
A70: LOG00078 | B70: CUST0060 | C70: =_xlfn.XLOOKUP(Table3[[#This Row],[Customer_ID]],Table1[Customer_ID],Table1[Customer_Name],,0) -> Mamta Shukla | D70: =_xlfn.XLOOKUP(Table3[[#This Row],[Customer_ID]],Table1[Customer_ID],Table1[Branch_Name],,0) -> Indore | E70: 46168 | F70: Tele-Call | G70: AG007 | H70: =_xlfn.XLOOKUP(Table3[[#This Row],[Agent_Code]],Table4[Agent_Code],Table4[Agent_Name],,0) -> Pushpa Jain | I70: Commitment Received | J70: =IF(OR(Table3[[#This Row],[Contact_Result]]="Commitment Received",Table3[[#This Row],[Contact_Result]]="Will Pay Next Week"),"Yes","") -> Yes | K70: 46173 | L70: 1977 | M70: 0 | N70: Commitment Received
A71: LOG00106 | B71: CUST0097 | C71: =_xlfn.XLOOKUP(Table3[[#This Row],[Customer_ID]],Table1[Customer_ID],Table1[Customer_Name],,0) -> Amit Verma | D71: =_xlfn.XLOOKUP(Table3[[#This Row],[Customer_ID]],Table1[Customer_ID],Table1[Branch_Name],,0) -> Gwalior | E71: 46168 | F71: WhatsApp Message | G71: AG004 | H71: =_xlfn.XLOOKUP(Table3[[#This Row],[Agent_Code]],Table4[Agent_Code],Table4[Agent_Name],,0) -> Pankaj Verma | I71: Will Pay Next Week | J71: =IF(OR(Table3[[#This Row],[Contact_Result]]="Commitment Received",Table3[[#This Row],[Contact_Result]]="Will Pay Next Week"),"Yes","") -> Yes | K71: 46173 | L71: 11340 | M71: 0 | N71: Will Pay Next Week
A72: LOG00123 | B72: CUST0116 | C72: =_xlfn.XLOOKUP(Table3[[#This Row],[Customer_ID]],Table1[Customer_ID],Table1[Customer_Name],,0) -> Ramesh Singh | D72: =_xlfn.XLOOKUP(Table3[[#This Row],[Customer_ID]],Table1[Customer_ID],Table1[Branch_Name],,0) -> Gwalior | E72: 46168 | F72: Tele-Call | G72: AG009 | H72: =_xlfn.XLOOKUP(Table3[[#This Row],[Agent_Code]],Table4[Agent_Code],Table4[Agent_Name],,0) -> Pankaj Joshi | I72: Commitment Received | J72: =IF(OR(Table3[[#This Row],[Contact_Result]]="Commitment Received",Table3[[#This Row],[Contact_Result]]="Will Pay Next Week"),"Yes","") -> Yes | K72: 46173 | L72: 16950 | M72: 0 | N72: Commitment Received
A73: LOG00152 | B73: CUST0146 | C73: =_xlfn.XLOOKUP(Table3[[#This Row],[Customer_ID]],Table1[Customer_ID],Table1[Customer_Name],,0) -> Neha Mishra | D73: =_xlfn.XLOOKUP(Table3[[#This Row],[Customer_ID]],Table1[Customer_ID],Table1[Branch_Name],,0) -> Bhopal | E73: 46168 | F73: Tele-Call | G73: AG019 | H73: =_xlfn.XLOOKUP(Table3[[#This Row],[Agent_Code]],Table4[Agent_Code],Table4[Agent_Name],,0) -> Ajay Yadav | I73: Payment Received | J73: =IF(OR(Table3[[#This Row],[Contact_Result]]="Commitment Received",Table3[[#This Row],[Contact_Result]]="Will Pay Next Week"),"Yes","") | M73: 3170 | N73: Customer paid after follow-up
A74: LOG00163 | B74: CUST0156 | C74: =_xlfn.XLOOKUP(Table3[[#This Row],[Customer_ID]],Table1[Customer_ID],Table1[Customer_Name],,0) -> Mahesh Pandey | D74: =_xlfn.XLOOKUP(Table3[[#This Row],[Customer_ID]],Table1[Customer_ID],Table1[Branch_Name],,0) -> Indore | E74: 46168 | F74: Tele-Call | G74: AG016 | H74: =_xlfn.XLOOKUP(Table3[[#This Row],[Agent_Code]],Table4[Agent_Code],Table4[Agent_Name],,0) -> Rekha Gupta | I74: Payment Received | J74: =IF(OR(Table3[[#This Row],[Contact_Result]]="Commitment Received",Table3[[#This Row],[Contact_Result]]="Will Pay Next Week"),"Yes","") | M74: 21188 | N74: Customer paid after follow-up
A75: LOG00198 | B75: CUST0191 | C75: =_xlfn.XLOOKUP(Table3[[#This Row],[Customer_ID]],Table1[Customer_ID],Table1[Customer_Name],,0) -> Kavita Jain | D75: =_xlfn.XLOOKUP(Table3[[#This Row],[Customer_ID]],Table1[Customer_ID],Table1[Branch_Name],,0) -> Jabalpur | E75: 46168 | F75: Field Visit | G75: AG014 | H75: =_xlfn.XLOOKUP(Table3[[#This Row],[Agent_Code]],Table4[Agent_Code],Table4[Agent_Name],,0) -> Manoj Gupta | I75: Part Payment Done | J75: =IF(OR(Table3[[#This Row],[Contact_Result]]="Commitment Received",Table3[[#This Row],[Contact_Result]]="Will Pay Next Week"),"Yes","") | M75: 5082 | N75: Part Payment Done
A76: LOG00267 | B76: CUST0250 | C76: =_xlfn.XLOOKUP(Table3[[#This Row],[Customer_ID]],Table1[Customer_ID],Table1[Customer_Name],,0) -> Suresh Thakur | D76: =_xlfn.XLOOKUP(Table3[[#This Row],[Customer_ID]],Table1[Customer_ID],Table1[Branch_Name],,0) -> Bhopal | E76: 46168 | F76: WhatsApp Message | G76: AG013 | H76: =_xlfn.XLOOKUP(Table3[[#This Row],[Agent_Code]],Table4[Agent_Code],Table4[Agent_Name],,0) -> Neha Malviya | I76: Will Pay Next Week | J76: =IF(OR(Table3[[#This Row],[Contact_Result]]="Commitment Received",Table3[[#This Row],[Contact_Result]]="Will Pay Next Week"),"Yes","") -> Yes | K76: 46173 | L76: 18246 | M76: 0 | N76: Will Pay Next Week
A77: LOG00277 | B77: CUST0257 | C77: =_xlfn.XLOOKUP(Table3[[#This Row],[Customer_ID]],Table1[Customer_ID],Table1[Customer_Name],,0) -> Naresh Dwivedi | D77: =_xlfn.XLOOKUP(Table3[[#This Row],[Customer_ID]],Table1[Customer_ID],Table1[Branch_Name],,0) -> Rewa | E77: 46168 | F77: Tele-Call | G77: AG009 | H77: =_xlfn.XLOOKUP(Table3[[#This Row],[Agent_Code]],Table4[Agent_Code],Table4[Agent_Name],,0) -> Pankaj Joshi | I77: Not Reachable | J77: =IF(OR(Table3[[#This Row],[Contact_Result]]="Commitment Received",Table3[[#This Row],[Contact_Result]]="Will Pay Next Week"),"Yes","") | M77: 0 | N77: Not Reachable
A78: LOG00325 | B78: CUST0302 | C78: =_xlfn.XLOOKUP(Table3[[#This Row],[Customer_ID]],Table1[Customer_ID],Table1[Customer_Name],,0) -> Neha Malviya | D78: =_xlfn.XLOOKUP(Table3[[#This Row],[Customer_ID]],Table1[Customer_ID],Table1[Branch_Name],,0) -> Gwalior | E78: 46168 | F78: Tele-Call | G78: AG019 | H78: =_xlfn.XLOOKUP(Table3[[#This Row],[Agent_Code]],Table4[Agent_Code],Table4[Agent_Name],,0) -> Ajay Yadav | I78: Payment Received | J78: =IF(OR(Table3[[#This Row],[Contact_Result]]="Commitment Received",Table3[[#This Row],[Contact_Result]]="Will Pay Next Week"),"Yes","") | M78: 5587 | N78: Customer paid after follow-up
A79: LOG00334 | B79: CUST0327 | C79: =_xlfn.XLOOKUP(Table3[[#This Row],[Customer_ID]],Table1[Customer_ID],Table1[Customer_Name],,0) -> Pradeep Soni | D79: =_xlfn.XLOOKUP(Table3[[#This Row],[Customer_ID]],Table1[Customer_ID],Table1[Branch_Name],,0) -> Gwalior | E79: 46168 | F79: Tele-Call | G79: AG013 | H79: =_xlfn.XLOOKUP(Table3[[#This Row],[Agent_Code]],Table4[Agent_Code],Table4[Agent_Name],,0) -> Neha Malviya | I79: Payment Received | J79: =IF(OR(Table3[[#This Row],[Contact_Result]]="Commitment Received",Table3[[#This Row],[Contact_Result]]="Will Pay Next Week"),"Yes","") | M79: 21228 | N79: Customer paid after follow-up
A80: LOG00440 | B80: CUST0408 | C80: =_xlfn.XLOOKUP(Table3[[#This Row],[Customer_ID]],Table1[Customer_ID],Table1[Customer_Name],,0) -> Pradeep Patel | D80: =_xlfn.XLOOKUP(Table3[[#This Row],[Customer_ID]],Table1[Customer_ID],Table1[Branch_Name],,0) -> Gwalior | E80: 46168 | F80: WhatsApp Message | G80: AG018 | H80: =_xlfn.XLOOKUP(Table3[[#This Row],[Agent_Code]],Table4[Agent_Code],Table4[Agent_Name],,0) -> Manoj Dubey | I80: Will Pay Next Week | J80: =IF(OR(Table3[[#This Row],[Contact_Result]]="Commitment Received",Table3[[#This Row],[Contact_Result]]="Will Pay Next Week"),"Yes","") -> Yes | K80: 46173 | L80: 1737 | M80: 0 | N80: Will Pay Next Week
A81: LOG00460 | B81: CUST0424 | C81: =_xlfn.XLOOKUP(Table3[[#This Row],[Customer_ID]],Table1[Customer_ID],Table1[Customer_Name],,0) -> Manoj Sharma | D81: =_xlfn.XLOOKUP(Table3[[#This Row],[Customer_ID]],Table1[Customer_ID],Table1[Branch_Name],,0) -> Jabalpur | E81: 46168 | F81: Field Visit | G81: AG010 | H81: =_xlfn.XLOOKUP(Table3[[#This Row],[Agent_Code]],Table4[Agent_Code],Table4[Agent_Name],,0) -> Kavita Tiwari | I81: Part Payment Done | J81: =IF(OR(Table3[[#This Row],[Contact_Result]]="Commitment Received",Table3[[#This Row],[Contact_Result]]="Will Pay Next Week"),"Yes","") | M81: 10242 | N81: Part Payment Done
A82: LOG00481 | B82: CUST0450 | C82: =_xlfn.XLOOKUP(Table3[[#This Row],[Customer_ID]],Table1[Customer_ID],Table1[Customer_Name],,0) -> Manoj Singh | D82: =_xlfn.XLOOKUP(Table3[[#This Row],[Customer_ID]],Table1[Customer_ID],Table1[Branch_Name],,0) -> Rewa | E82: 46168 | F82: Tele-Call | G82: AG012 | H82: =_xlfn.XLOOKUP(Table3[[#This Row],[Agent_Code]],Table4[Agent_Code],Table4[Agent_Name],,0) -> Umesh Soni | I82: Not Reachable | J82: =IF(OR(Table3[[#This Row],[Contact_Result]]="Commitment Received",Table3[[#This Row],[Contact_Result]]="Will Pay Next Week"),"Yes","") | M82: 0 | N82: Not Reachable
A83: LOG00492 | B83: CUST0457 | C83: =_xlfn.XLOOKUP(Table3[[#This Row],[Customer_ID]],Table1[Customer_ID],Table1[Customer_Name],,0) -> Dinesh Mishra | D83: =_xlfn.XLOOKUP(Table3[[#This Row],[Customer_ID]],Table1[Customer_ID],Table1[Branch_Name],,0) -> Gwalior | E83: 46168 | F83: WhatsApp Message | G83: AG007 | H83: =_xlfn.XLOOKUP(Table3[[#This Row],[Agent_Code]],Table4[Agent_Code],Table4[Agent_Name],,0) -> Pushpa Jain | I83: Will Pay Next Week | J83: =IF(OR(Table3[[#This Row],[Contact_Result]]="Commitment Received",Table3[[#This Row],[Contact_Result]]="Will Pay Next Week"),"Yes","") -> Yes | K83: 46173 | L83: 53995 | M83: 0 | N83: Will Pay Next Week
A84: LOG00511 | B84: CUST0469 | C84: =_xlfn.XLOOKUP(Table3[[#This Row],[Customer_ID]],Table1[Customer_ID],Table1[Customer_Name],,0) -> Ramesh Thakur | D84: =_xlfn.XLOOKUP(Table3[[#This Row],[Customer_ID]],Table1[Customer_ID],Table1[Branch_Name],,0) -> Gwalior | E84: 46168 | F84: Field Visit | G84: AG003 | H84: =_xlfn.XLOOKUP(Table3[[#This Row],[Agent_Code]],Table4[Agent_Code],Table4[Agent_Name],,0) -> Pushpa Gupta | I84: Part Payment Done | J84: =IF(OR(Table3[[#This Row],[Contact_Result]]="Commitment Received",Table3[[#This Row],[Contact_Result]]="Will Pay Next Week"),"Yes","") | M84: 7012 | N84: Part Payment Done
A85: LOG00526 | B85: CUST0480 | C85: =_xlfn.XLOOKUP(Table3[[#This Row],[Customer_ID]],Table1[Customer_ID],Table1[Customer_Name],,0) -> Anil Joshi | D85: =_xlfn.XLOOKUP(Table3[[#This Row],[Customer_ID]],Table1[Customer_ID],Table1[Branch_Name],,0) -> Rewa | E85: 46168 | F85: Field Visit | G85: AG004 | H85: =_xlfn.XLOOKUP(Table3[[#This Row],[Agent_Code]],Table4[Agent_Code],Table4[Agent_Name],,0) -> Pankaj Verma | I85: Part Payment Done | J85: =IF(OR(Table3[[#This Row],[Contact_Result]]="Commitment Received",Table3[[#This Row],[Contact_Result]]="Will Pay Next Week"),"Yes","") | M85: 26722 | N85: Part Payment Done
A86: LOG00019 | B86: CUST0011 | C86: =_xlfn.XLOOKUP(Table3[[#This Row],[Customer_ID]],Table1[Customer_ID],Table1[Customer_Name],,0) -> Naresh Dwivedi | D86: =_xlfn.XLOOKUP(Table3[[#This Row],[Customer_ID]],Table1[Customer_ID],Table1[Branch_Name],,0) -> Bhopal | E86: 46167 | F86: Tele-Call | G86: AG011 | H86: =_xlfn.XLOOKUP(Table3[[#This Row],[Agent_Code]],Table4[Agent_Code],Table4[Agent_Name],,0) -> Umesh Gupta | I86: Commitment Received | J86: =IF(OR(Table3[[#This Row],[Contact_Result]]="Commitment Received",Table3[[#This Row],[Contact_Result]]="Will Pay Next Week"),"Yes","") -> Yes | K86: 46172 | L86: 15919 | M86: 0 | N86: Commitment Received
A87: LOG00057 | B87: CUST0039 | C87: =_xlfn.XLOOKUP(Table3[[#This Row],[Customer_ID]],Table1[Customer_ID],Table1[Customer_Name],,0) -> Vijay Pandey | D87: =_xlfn.XLOOKUP(Table3[[#This Row],[Customer_ID]],Table1[Customer_ID],Table1[Branch_Name],,0) -> Bhopal | E87: 46167 | F87: Tele-Call | G87: AG009 | H87: =_xlfn.XLOOKUP(Table3[[#This Row],[Agent_Code]],Table4[Agent_Code],Table4[Agent_Name],,0) -> Pankaj Joshi | I87: Payment Received | J87: =IF(OR(Table3[[#This Row],[Contact_Result]]="Commitment Received",Table3[[#This Row],[Contact_Result]]="Will Pay Next Week"),"Yes","") | M87: 22266 | N87: Customer paid after follow-up
A88: LOG00063 | B88: CUST0048 | C88: =_xlfn.XLOOKUP(Table3[[#This Row],[Customer_ID]],Table1[Customer_ID],Table1[Customer_Name],,0) -> Anil Chauhan | D88: =_xlfn.XLOOKUP(Table3[[#This Row],[Customer_ID]],Table1[Customer_ID],Table1[Branch_Name],,0) -> Rewa | E88: 46167 | F88: Field Visit | G88: AG017 | H88: =_xlfn.XLOOKUP(Table3[[#This Row],[Agent_Code]],Table4[Agent_Code],Table4[Agent_Name],,0) -> Naresh Mishra | I88: Part Payment Done | J88: =IF(OR(Table3[[#This Row],[Contact_Result]]="Commitment Received",Table3[[#This Row],[Contact_Result]]="Will Pay Next Week"),"Yes","") | M88: 865 | N88: Part Payment Done
A89: LOG00092 | B89: CUST0082 | C89: =_xlfn.XLOOKUP(Table3[[#This Row],[Customer_ID]],Table1[Customer_ID],Table1[Customer_Name],,0) -> Geeta Gupta | D89: =_xlfn.XLOOKUP(Table3[[#This Row],[Customer_ID]],Table1[Customer_ID],Table1[Branch_Name],,0) -> Gwalior | E89: 46167 | F89: Tele-Call | G89: AG006 | H89: =_xlfn.XLOOKUP(Table3[[#This Row],[Agent_Code]],Table4[Agent_Code],Table4[Agent_Name],,0) -> Suresh Malviya | I89: Not Reachable | J89: =IF(OR(Table3[[#This Row],[Contact_Result]]="Commitment Received",Table3[[#This Row],[Contact_Result]]="Will Pay Next Week"),"Yes","") | M89: 0 | N89: Not Reachable
A90: LOG00154 | B90: CUST0147 | C90: =_xlfn.XLOOKUP(Table3[[#This Row],[Customer_ID]],Table1[Customer_ID],Table1[Customer_Name],,0) -> Mahesh Dubey | D90: =_xlfn.XLOOKUP(Table3[[#This Row],[Customer_ID]],Table1[Customer_ID],Table1[Branch_Name],,0) -> Bhopal | E90: 46167 | F90: WhatsApp Message | G90: AG011 | H90: =_xlfn.XLOOKUP(Table3[[#This Row],[Agent_Code]],Table4[Agent_Code],Table4[Agent_Name],,0) -> Umesh Gupta | I90: Will Pay Next Week | J90: =IF(OR(Table3[[#This Row],[Contact_Result]]="Commitment Received",Table3[[#This Row],[Contact_Result]]="Will Pay Next Week"),"Yes","") -> Yes | K90: 46172 | L90: 10017 | M90: 0 | N90: Will Pay Next Week
A91: LOG00216 | B91: CUST0208 | C91: =_xlfn.XLOOKUP(Table3[[#This Row],[Customer_ID]],Table1[Customer_ID],Table1[Customer_Name],,0) -> Rajesh Dwivedi | D91: =_xlfn.XLOOKUP(Table3[[#This Row],[Customer_ID]],Table1[Customer_ID],Table1[Branch_Name],,0) -> Jabalpur | E91: 46167 | F91: Tele-Call | G91: AG002 | H91: =_xlfn.XLOOKUP(Table3[[#This Row],[Agent_Code]],Table4[Agent_Code],Table4[Agent_Name],,0) -> Sunita Patel | I91: Not Reachable | J91: =IF(OR(Table3[[#This Row],[Contact_Result]]="Commitment Received",Table3[[#This Row],[Contact_Result]]="Will Pay Next Week"),"Yes","") | M91: 0 | N91: Not Reachable
A92: LOG00224 | B92: CUST0210 | C92: =_xlfn.XLOOKUP(Table3[[#This Row],[Customer_ID]],Table1[Customer_ID],Table1[Customer_Name],,0) -> Deepak Patel | D92: =_xlfn.XLOOKUP(Table3[[#This Row],[Customer_ID]],Table1[Customer_ID],Table1[Branch_Name],,0) -> Indore | E92: 46167 | F92: Tele-Call | G92: AG016 | H92: =_xlfn.XLOOKUP(Table3[[#This Row],[Agent_Code]],Table4[Agent_Code],Table4[Agent_Name],,0) -> Rekha Gupta | I92: Not Reachable | J92: =IF(OR(Table3[[#This Row],[Contact_Result]]="Commitment Received",Table3[[#This Row],[Contact_Result]]="Will Pay Next Week"),"Yes","") | M92: 0 | N92: Not Reachable
A93: LOG00289 | B93: CUST0273 | C93: =_xlfn.XLOOKUP(Table3[[#This Row],[Customer_ID]],Table1[Customer_ID],Table1[Customer_Name],,0) -> Mahesh Singh | D93: =_xlfn.XLOOKUP(Table3[[#This Row],[Customer_ID]],Table1[Customer_ID],Table1[Branch_Name],,0) -> Jabalpur | E93: 46167 | F93: Tele-Call | G93: AG004 | H93: =_xlfn.XLOOKUP(Table3[[#This Row],[Agent_Code]],Table4[Agent_Code],Table4[Agent_Name],,0) -> Pankaj Verma | I93: Not Reachable | J93: =IF(OR(Table3[[#This Row],[Contact_Result]]="Commitment Received",Table3[[#This Row],[Contact_Result]]="Will Pay Next Week"),"Yes","") | M93: 0 | N93: Not Reachable
A94: LOG00304 | B94: CUST0282 | C94: =_xlfn.XLOOKUP(Table3[[#This Row],[Customer_ID]],Table1[Customer_ID],Table1[Customer_Name],,0) -> Usha Dubey | D94: =_xlfn.XLOOKUP(Table3[[#This Row],[Customer_ID]],Table1[Customer_ID],Table1[Branch_Name],,0) -> Bhopal | E94: 46167 | F94: WhatsApp Message | G94: AG001 | H94: =_xlfn.XLOOKUP(Table3[[#This Row],[Agent_Code]],Table4[Agent_Code],Table4[Agent_Name],,0) -> Mohit Mishra | I94: Will Pay Next Week | J94: =IF(OR(Table3[[#This Row],[Contact_Result]]="Commitment Received",Table3[[#This Row],[Contact_Result]]="Will Pay Next Week"),"Yes","") -> Yes | K94: 46172 | L94: 1390 | M94: 0 | N94: Will Pay Next Week
A95: LOG00323 | B95: CUST0301 | C95: =_xlfn.XLOOKUP(Table3[[#This Row],[Customer_ID]],Table1[Customer_ID],Table1[Customer_Name],,0) -> Shanta Yadav | D95: =_xlfn.XLOOKUP(Table3[[#This Row],[Customer_ID]],Table1[Customer_ID],Table1[Branch_Name],,0) -> Bhopal | E95: 46167 | F95: Tele-Call | G95: AG006 | H95: =_xlfn.XLOOKUP(Table3[[#This Row],[Agent_Code]],Table4[Agent_Code],Table4[Agent_Name],,0) -> Suresh Malviya | I95: Commitment Received | J95: =IF(OR(Table3[[#This Row],[Contact_Result]]="Commitment Received",Table3[[#This Row],[Contact_Result]]="Will Pay Next Week"),"Yes","") -> Yes | K95: 46172 | L95: 10042 | M95: 0 | N95: Commitment Received
A96: LOG00351 | B96: CUST0346 | C96: =_xlfn.XLOOKUP(Table3[[#This Row],[Customer_ID]],Table1[Customer_ID],Table1[Customer_Name],,0) -> Dinesh Sharma | D96: =_xlfn.XLOOKUP(Table3[[#This Row],[Customer_ID]],Table1[Customer_ID],Table1[Branch_Name],,0) -> Rewa | E96: 46167 | F96: Tele-Call | G96: AG009 | H96: =_xlfn.XLOOKUP(Table3[[#This Row],[Agent_Code]],Table4[Agent_Code],Table4[Agent_Name],,0) -> Pankaj Joshi | I96: Commitment Received | J96: =IF(OR(Table3[[#This Row],[Contact_Result]]="Commitment Received",Table3[[#This Row],[Contact_Result]]="Will Pay Next Week"),"Yes","") -> Yes | K96: 46172 | L96: 26634 | M96: 0 | N96: Commitment Received
A97: LOG00384 | B97: CUST0371 | C97: =_xlfn.XLOOKUP(Table3[[#This Row],[Customer_ID]],Table1[Customer_ID],Table1[Customer_Name],,0) -> Neha Shukla | D97: =_xlfn.XLOOKUP(Table3[[#This Row],[Customer_ID]],Table1[Customer_ID],Table1[Branch_Name],,0) -> Gwalior | E97: 46167 | F97: Tele-Call | G97: AG020 | H97: =_xlfn.XLOOKUP(Table3[[#This Row],[Agent_Code]],Table4[Agent_Code],Table4[Agent_Name],,0) -> Vijay Tiwari | I97: Payment Received | J97: =IF(OR(Table3[[#This Row],[Contact_Result]]="Commitment Received",Table3[[#This Row],[Contact_Result]]="Will Pay Next Week"),"Yes","") | M97: 21747 | N97: Customer paid after follow-up
A98: LOG00424 | B98: CUST0402 | C98: =_xlfn.XLOOKUP(Table3[[#This Row],[Customer_ID]],Table1[Customer_ID],Table1[Customer_Name],,0) -> Pooja Dubey | D98: =_xlfn.XLOOKUP(Table3[[#This Row],[Customer_ID]],Table1[Customer_ID],Table1[Branch_Name],,0) -> Rewa | E98: 46167 | F98: Tele-Call | G98: AG020 | H98: =_xlfn.XLOOKUP(Table3[[#This Row],[Agent_Code]],Table4[Agent_Code],Table4[Agent_Name],,0) -> Vijay Tiwari | I98: Commitment Received | J98: =IF(OR(Table3[[#This Row],[Contact_Result]]="Commitment Received",Table3[[#This Row],[Contact_Result]]="Will Pay Next Week"),"Yes","") -> Yes | K98: 46172 | L98: 1562 | M98: 0 | N98: Commitment Received
A99: LOG00427 | B99: CUST0404 | C99: =_xlfn.XLOOKUP(Table3[[#This Row],[Customer_ID]],Table1[Customer_ID],Table1[Customer_Name],,0) -> Sunita Singh | D99: =_xlfn.XLOOKUP(Table3[[#This Row],[Customer_ID]],Table1[Customer_ID],Table1[Branch_Name],,0) -> Indore | E99: 46167 | F99: Tele-Call | G99: AG004 | H99: =_xlfn.XLOOKUP(Table3[[#This Row],[Agent_Code]],Table4[Agent_Code],Table4[Agent_Name],,0) -> Pankaj Verma | I99: Commitment Received | J99: =IF(OR(Table3[[#This Row],[Contact_Result]]="Commitment Received",Table3[[#This Row],[Contact_Result]]="Will Pay Next Week"),"Yes","") -> Yes | K99: 46172 | L99: 77291 | M99: 0 | N99: Commitment Received
A100: LOG00439 | B100: CUST0408 | C100: =_xlfn.XLOOKUP(Table3[[#This Row],[Customer_ID]],Table1[Customer_ID],Table1[Customer_Name],,0) -> Pradeep Patel | D100: =_xlfn.XLOOKUP(Table3[[#This Row],[Customer_ID]],Table1[Customer_ID],Table1[Branch_Name],,0) -> Gwalior | E100: 46167 | F100: Tele-Call | G100: AG003 | H100: =_xlfn.XLOOKUP(Table3[[#This Row],[Agent_Code]],Table4[Agent_Code],Table4[Agent_Name],,0) -> Pushpa Gupta | I100: Not Reachable | J100: =IF(OR(Table3[[#This Row],[Contact_Result]]="Commitment Received",Table3[[#This Row],[Contact_Result]]="Will Pay Next Week"),"Yes","") | M100: 0 | N100: Not Reachable
...

Sheet Sheet2
E3: Not Reachable | F3: +
E4: Call Disconnected | F4: + | H4: Field
E5: Will Pay Next Week | F5: + | H5: Tele-Calling
E6: Commitment Received | F6: +
E7: Part Payment Done | F7: + | I7: BR001
E8: Payment Received | F8: + | I8: BR002
E9: Refused To Pay | F9: + | I9: BR003
E10: Payment Reminder | F10: + | I10: BR004
E11: Callback Requested | I11: BR005
G13: Active
G14: Inactive
G15: On Leave

Sheet Sheet1
D3: Tele-Call
D4: Field Visit
D5: Whatsapp Message | F5: Yes

Sheet overdue_&_risk_mis
A1: ABC Finance | Overdue & Risk MIS | May 2026
B5: Total Customers | E5: Total Loan Amount | H5: Total Overdue Amount | K5: Accounts at Risk (DPD > 0) | N5: Portfolio at Risk (PAR%) | R5: DPD_Bucket | S5: Total Customers | T5: Total Loan Amount | U5: Total Overdue Amount
B6: =COUNTA(customer_master!A3:A424) -> 422 | E6: =SUM(customer_master!Y3:Y424) -> 220744164 | H6: =SUM(loan_status_tracker!J3:J424) -> 1841417.9 | K6: =COUNTIF(loan_status_tracker!M3:M424,"<>Current") -> 126 | N6: =H6/E6 -> 0.0083418645 | R6: 1-30 | S6: 92 | T6: 41058183 | U6: 1262995.5
R7: 31-60 | S7: 34 | T7: 21130021 | U7: 578415.86
R8: Current | S8: 296 | T8: 158555960 | U8: 6.5385593
R9: Grand Total | S9: 422 | T9: 220744164 | U9: 1841417.9
R11: Top 20 Overdue Customers
R12: Customer ID | S12: Customer Name | T12: Branch Name | U12: Overdue Amount
R13: CUST0008 | S13: Dinesh Sharma | T13: Bhopal | U13: 42659.968
R14: CUST0027 | S14: Amit Chauhan | T14: Indore | U14: 47605.1
R15: CUST0111 | S15: Usha Chauhan | T15: Rewa | U15: 36525.294
R16: CUST0115 | S16: Ajay Chauhan | T16: Rewa | U16: 39567.006
R17: CUST0181 | S17: Ajay Sharma | T17: Bhopal | U17: 29296.38
R18: CUST0207 | S18: Kavita Agarwal | T18: Indore | U18: 48786.257
R19: CUST0209 | S19: Santosh Soni | T19: Bhopal | U19: 27850.679
R20: CUST0257 | S20: Naresh Dwivedi | T20: Rewa | U20: 34078.706
R21: CUST0263 | S21: Manoj Thakur | T21: Bhopal | U21: 48725.819
R22: CUST0265 | S22: Suresh Sharma | T22: Gwalior | U22: 52201.205
R23: CUST0273 | S23: Mahesh Singh | T23: Jabalpur | U23: 91666.986
R24: CUST0306 | S24: Vijay Gupta | T24: Bhopal | U24: 53966.222
... R32: CUST0480 | S32: Anil Joshi | T32: Rewa | U32: 28978.424
R33: Grand Total | U33: 895705.34

Sheet Sheet3
A3: Branch Name | B3: Collection Efficiency
A4: Bhopal | B4: 0.52414308
A5: Rewa | B5: 0.84410598
A6: Jabalpur | B6: 0.88247254
A7: Gwalior | B7: 0.89709161
A8: Indore | B8: 0.98126983
A9: Grand Total | B9: 0.80441327

Sheet branch_performance_tracker
A1: ABC Finance | Branch Performance Tracker | May 2026
B5: Total Branch | E5: Amount Collected | H5: Collection Efficiency % | K5: Best Performing Branch | N5: Highest Overdue Branch | Q5: Branch Performance Summary
B6: =COUNTA(_xlfn.UNIQUE(customer_master!W3:W424,FALSE,FALSE)) -> 5 | E6: =SUM(collection_log!M3:M548) -> 1481261 | H6: =V12 -> 0.80441327 | K6: =_xlfn.XLOOKUP(MAX(V7:V11),V7:V11,Q7:Q11)&" ("&TEXT(MAX(V7:V11),"0%")&")" -> Indore (98%) | N6: =_xlfn.XLOOKUP(MAX(T7:T11),T7:T11,Q7:Q11)&" ("&TEXT(MAX(T7:T11),"₹#,##0")&")" -> Bhopal (₹4,71,234) | Q6: Branch_Name | R6: Total Customers | S6: Total Disbursed Amount | T6: Overdue Amount | U6: Amount Collected | V6: Collection Efficiency
Q7: Indore | R7: 90 | S7: 46517353 | T7: 376292.01 | U7: 369244 | V7: 0.98126983
Q8: Gwalior | R8: 84 | S8: 41540126 | T8: 283889.62 | U8: 254675 | V8: 0.89709161
Q9: Jabalpur | R9: 76 | S9: 38879899 | T9: 287510.36 | U9: 253720 | V9: 0.88247254
Q10: Rewa | R10: 83 | S10: 47125162 | T10: 422491.97 | U10: 356628 | V10: 0.84410598
Q11: Bhopal | R11: 89 | S11: 46681624 | T11: 471233.92 | U11: 246994 | V11: 0.52414308
Q12: Grand Total | R12: 422 | S12: 220744164 | T12: 1841417.9 | U12: 1481261 | V12: 0.80441327

Sheet Sheet4
A1: Branch_Name | B1: Amount Collected
A2: Indore | B2: 369244
A3: Rewa | B3: 356628
A4: Gwalior | B4: 254675
A5: Jabalpur | B5: 253720
A6: Bhopal | B6: 246994
A7: Grand Total | B7: 1481261

Sheet vstack
A1: {=_xlfn.VSTACK(Table2[#All],Table3[#All])} -> Customer_ID | B1: Customer_Name | C1: Branch_Name | D1: Vehicle_Make | E1: Vehicle_Model | F1: Loan_Amount | G1: EMI_Amount | H1: EMI_Due_May26 | I1: Amount_Received_May26 | J1: Overdue_Amount | K1: EMI_Due_Date | L1: Days_Past_Due | M1: DPD_Bucket | N1: Loan_Status
A2: CUST0001 | B2: Vijay Mishra | C2: Indore | D2: Bajaj | E2: Pulsar | F2: 54982 | G2: 1887.4434 | H2: 1887.4434 | I2: 167 | J2: 1720.4434 | K2: 46159 | L2: 21 | M2: 1-30 | N2: Overdue
A3: CUST0003 | B3: Mamta Dwivedi | C3: Jabalpur | D3: Maruti | E3: Brezza | F3: 858828 | G3: 28439.315 | H3: 28439.315 | I3: 28439 | J3: 0.31540488 | K3: 46170 | M3: Current | N3: Active
A4: CUST0004 | B4: Mahesh Patel | C4: Gwalior | D4: Hero | E4: Splendor | F4: 35571 | G4: 960.64883 | H4: 960.64883 | I4: 194 | J4: 766.64883 | K4: 46165 | L4: 15 | M4: 1-30 | N4: Overdue
A5: CUST0005 | B5: Santosh Mishra | C5: Rewa | D5: Maruti | E5: Dzire | F5: 494849 | G5: 43747.117 | H5: 43747.117 | I5: 43747 | J5: 0.11732015 | K5: 46159 | M5: Current | N5: Active
A6: CUST0006 | B6: Deepak Malviya | C6: Jabalpur | D6: Honda | E6: Activa | F6: 38984 | G6: 1903.0086 | H6: 1903.0086 | I6: 1903 | J6: 0.0086001553 | K6: 46167 | M6: Current | N6: Active
A7: CUST0008 | B7: Dinesh Sharma | C7: Bhopal | D7: Honda | E7: City | F7: 872459 | G7: 42659.968 | H7: 42659.968 | I7: 0 | J7: 42659.968 | K7: 46157 | L7: 23 | M7: 1-30 | N7: Overdue
A8: CUST0009 | B8: Meena Gupta | C8: Bhopal | D8: Honda | E8: City | F8: 936007 | G8: 21653.284 | H8: 21653.284 | I8: 5106 | J8: 16547.284 | K8: 46159 | L8: 21 | M8: 1-30 | N8: Overdue
A9: CUST0011 | B9: Naresh Dwivedi | C9: Bhopal | D9: Honda | E9: City | F9: 874852 | G9: 41010.94 | H9: 41010.94 | I9: 25092 | J9: 15918.94 | K9: 46171 | L9: 9 | M9: 1-30 | N9: Overdue
A10: CUST0012 | B10: Asha Singh | C10: Indore | D10: Hyundai | E10: i20 | F10: 599235 | G10: 29120.422 | H10: 29120.422 | I10: 29120 | J10: 0.42152583 | K10: 46152 | M10: Current | N10: Active
A11: CUST0013 | B11: Ramesh Verma | C11: Jabalpur | D11: Maruti | E11: Swift | F11: 538554 | G11: 33246.325 | H11: 33246.325 | I11: 33246 | J11: 0.325458 | K11: 46159 | M11: Current | N11: Active
A12: CUST0014 | B12: Ajay Chauhan | C12: Rewa | D12: Honda | E12: City | F12: 866248 | G12: 19860.902 | H12: 19860.902 | I12: 19861 | J12: -0.098274357 | K12: 46161 | M12: Current | N12: Active
A13: CUST0015 | B13: Seema Joshi | C13: Bhopal | D13: Renault | E13: Kwid | F13: 363463 | G13: 7823.045 | H13: 7823.045 | I13: 5486 | J13: 2337.045 | K13: 46152 | L13: 28 | M13: 1-30 | N13: Overdue
A14: CUST0016 | B14: Asha Jain | C14: Jabalpur | D14: Hero | E14: Splendor | F14: 55853 | G14: 2707.5941 | H14: 2707.5941 | I14: 2708 | J14: -0.40594813 | K14: 46166 | M14: Current | N14: Active
A15: CUST0017 | B15: Lata Gupta | C15: Gwalior | D15: TVS | E15: Jupiter | F15: 64394 | G15: 1453.6499 | H15: 1453.6499 | I15: 1048 | J15: 405.64988 | K15: 46168 | L15: 12 | M15: 1-30 | N15: Overdue
A16: CUST0018 | B16: Kiran Sharma | C16: Bhopal | D16: Bajaj | E16: Pulsar | F16: 77753 | G16: 2686.5841 | H16: 2686.5841 | I16: 2687 | J16: -0.41594581 | K16: 46169 | M16: Current | N16: Active
A17: CUST0020 | B17: Kiran Dwivedi | C17: Gwalior | D17: Honda | E17: City | F17: 905436 | G17: 79834.006 | H17: 79834.006 | I17: 79834 | J17: 0.0062576602 | K17: 46173 | M17: Current | N17: Active
